Workbook

Sheet Details
A1: Name
A2: Abhimanyu Babbar

Sheet NSE Factsheet Details
A1: NIFTY Medium Duration G-Sec Index (3 to 4 years)
A3: Index Name | B3: Average Coupon % | C3: Average Yield % | D3: Average Macaulay Duration | E3: Average Maturity | F3: 3M | G3: 6M | H3: 1 Year | I3: 3 Year | J3: Since Inception
A4: NIFTY Medium Duration G-Sec Index | B4: 0.0715 | C4: 0.0674 | D4: 3.6 | E4: 4.14 | F4: 2.14 | G4: 4.15 | H4: 8.53 | I4: 6.27 | J4: 7.01
A9: https://www.ccilindia.com/documents/d/ccil/Outstanding_Government_Debt%20Rakshitra-pdf
A10: Yield | B10: Duration | C10: Macaulay Duration
A11: 0.0672 | B11: 3.3534 | C11: 3.2443
A12: 0.0673 | B12: 3.7318 | C12: 3.6103
A13: 0.0673 | B13: 3.8603 | C13: 3.7347

Sheet Part 1
A1: Computation of Yield, Duration and Macaulay Duration
A2: ISIN | B2: Outstanding Amount | C2: Weight | D2: Value | E2: Weight | F2: Total Weightage | G2: Maturity Date | H2: Settlement Date | I2: Frequency | J2: Last Price | K2: Face Value | L2: Coupon | M2: Yield | N2: Duration | O2: Macaulay Duration
A3: IN0020230101 (Bond 1) | B3: 750000000000 | C3: =B3/$B$6 -> 0.23321025 | D3: =(B3*J3)/K3 -> 765975000000 | E3: =D3/$D$6 -> 0.23469156 | F3: =AVERAGE(C3,E3) -> 0.2339509 | G3: 47049 | H3: 45657 | I3: 2 | J3: 102.13 | K3: 100 | L3: 0.0737 | M3: =YIELD(H3,G3,L3,J3,K3,2,1) -> 0.067227434 | N3: =DURATION(H3,G3,L3,M3,2,1) -> 3.3527358 | O3: =MDURATION(H3,G3,L3,M3,2,1) -> 3.2437029
A4: IN0020220011 (Bond 2) | B4: 1585982100000 | C4: =B4/$B$6 -> 0.49315638 | D4: =(B4*J4)/K4 -> 1607392858350 | E4: =D4/$D$6 -> 0.49249849 | F4: =AVERAGE(C4,E4) -> 0.49282744 | G4: 47226 | H4: 45657 | I4: 2 | J4: 101.35 | K4: 100 | L4: 0.071 | M4: =YIELD(H4,G4,L4,J4,K4,2,1) -> 0.067291287 | N4: =DURATION(H4,G4,L4,M4,2,1) -> 3.7312634 | O4: =MDURATION(H4,G4,L4,M4,2,1) -> 3.6098091
A5: IN0020240050 (Bond 3) | B5: 880000000000 | C5: =B5/$B$6 -> 0.27363336 | D5: =(B5*J5)/K5 -> 890384000000 | E5: =D5/$D$6 -> 0.27280996 | F5: =AVERAGE(C5,E5) -> 0.27322166 | G5: 47272 | H5: 45657 | I5: 2 | J5: 101.18 | K5: 100 | L5: 0.0704 | M5: =YIELD(H5,G5,L5,J5,K5,2,1) -> 0.067251451 | N5: =DURATION(H5,G5,L5,M5,2,1) -> 3.8611935 | O5: =MDURATION(H5,G5,L5,M5,2,1) -> 3.7355818
B6: =SUM(B3:B5) -> 3215982100000 | D6: =SUM(D3:D5) -> 3263751858350
A9: Comparison between Calculated Value and NSE Factsheet:
A10: Particulars | B10: Calculated | C10: NSE Factsheet | D10: Variance (B-C)
A11: Yield:
A12: Bond 1 | B12: =M3 -> 0.067227434 | C12: ='NSE Factsheet Details'!A11 -> 0.0672 | D12: =B12-C12 -> 2.7434394e-05
A13: Bond 2 | B13: =M4 -> 0.067291287 | C13: ='NSE Factsheet Details'!A12 -> 0.0673 | D13: =B13-C13 -> -8.7125437e-06
A14: Bond 3 | B14: =M5 -> 0.067251451 | C14: ='NSE Factsheet Details'!A13 -> 0.0673 | D14: =B14-C14 -> -4.8549272e-05
A15: Duration:
A16: Bond 1 | B16: =N3 -> 3.3527358 | C16: ='NSE Factsheet Details'!B11 -> 3.3534 | D16: =B16-C16 -> -0.00066416747
A17: Bond 2 | B17: =N4 -> 3.7312634 | C17: ='NSE Factsheet Details'!B12 -> 3.7318 | D17: =B17-C17 -> -0.00053656811
A18: Bond 3 | B18: =N5 -> 3.8611935 | C18: ='NSE Factsheet Details'!B13 -> 3.8603 | D18: =B18-C18 -> 0.00089349425
A19: Macaulay Duration:
A20: Bond 1 | B20: =O3 -> 3.2437029 | C20: ='NSE Factsheet Details'!C11 -> 3.2443 | D20: =B20-C20 -> -0.00059708009
A21: Bond 2 | B21: =O4 -> 3.6098091 | C21: ='NSE Factsheet Details'!C12 -> 3.6103 | D21: =B21-C21 -> -0.0004909184
A22: Bond 3 | B22: =O5 -> 3.7355818 | C22: ='NSE Factsheet Details'!C13 -> 3.7347 | D22: =B22-C22 -> 0.00088184505
A23: Index - Averages:
A24: Yield | B24: =($F$3*M3)+($F$4*M4)+($F$5*M5) -> 0.067265465 | C24: ='NSE Factsheet Details'!C4 -> 0.0674 | D24: =B24-C24 -> -0.00013453528
A25: Coupon | B25: =($F$3*L3)+($F$4*L4)+($F$5*L5) -> 0.071467734 | C25: ='NSE Factsheet Details'!B4 -> 0.0715 | D25: =B25-C25 -> -3.2265554e-05
A26: Duration | B26: =AVERAGE(N3:N5) -> 3.6483976 | C26: =AVERAGE('NSE Factsheet Details'!B11:B13) -> 3.6485 | D26: =B26-C26 -> -0.00010241378
A27: Macaulay Duration | B27: =($F$3*O3)+($F$4*O4)+($F$5*O5) -> 3.5585221 | C27: ='NSE Factsheet Details'!D4 -> 3.6 | D27: =B27-C27 -> -0.041477943

Sheet Part 2
A1: Analysis of UTI Nifty SDL Plus AAA PSU Bond Apr 2026 75:25 Index Fund:
A3: 1. Categorization of Holdings in Various Asset Classes:
A5: Fund Overview:
A6: The UTI Nifty SDL Plus AAA PSU Bond Apr 2026 75:25 Index Fund is an open-ended target maturity index fund that invests in the constituents of the Nifty SDL Plus AAA PSU Bond Apr 2026 75:25 Index. The fund aims to replicate the performance of the underlying index by allocating its assets as follows:
A9: State Development Loans (SDLs): Approximately 75% of the portfolio is invested in SDLs.
A10: AAA-rated Public Sector Undertaking (PSU) Bonds: The remaining 25% is allocated to AAA-rated PSU bonds.
A12: Fund seeks to track Nifty SDL Plus AAA PSU Bond Apr 2026 75:25 Index. Investors will have good liquidity throughout the term as it’s an open-ended fund without any lock-in period.
A15: This allocation strategy provides investors with exposure to sovereign and high-quality PSU debt instruments, aiming for stable and predictable returns.

Sheet Part 2a
A1: Analysis of UTI Nifty SDL Plus AAA PSU Bond Apr 2026 75:25 Index Fund:
A3: 2. Explanation of Fixed Income Instruments in the Portfolio
A5: a. State Development Loans (SDLs):
A6: Issuer: State Governments of India
A7: Characteristics:
A8: Tenure: Typically ranges from 10 to 30 years
A9: Interest Payments: Fixed coupon payments, usually made semi-annually
A10: Credit Risk: Considered low, as they are backed by the respective state governments
A11: Role in Portfolio: SDLs offer a sovereign guarantee, providing safety of principal and regular income, which aligns with the fund's objective of capital preservation and steady returns.
A15: b. AAA-rated PSU Bonds:
A16: Issuer: Public Sector Undertakings (PSUs) owned by the Central Government
A17: Characteristics:
... A26: As per the fund's Key Information Memorandum (KIM), there is no mention of derivatives being utilized within the portfolio. The fund focuses on direct investments in SDLs and AAA-rated PSU bonds to achieve its investment objectives.

Sheet Part 2b
A1: Analysis of UTI Nifty SDL Plus AAA PSU Bond Apr 2026 75:25 Index Fund:
A3: 3. Performance Analysis Relative to Benchmark (As of February 26, 2025)
A5: Benchmark Index: Nifty SDL Plus AAA PSU Bond Apr 2026 75:25 Index
A7: Performance Metrics:
A8: Fund's Annualized Return: 6.80%
A9: Benchmark's Annualized Return: 6.75%
A11: Analysis:
A12: Interest Rate Movements: The Reserve Bank of India (RBI) has maintained the policy repo rate at 6.25% as of February 25, 2025. Stable interest rates contribute to predictable returns from fixed-income instruments. The fund's slight outperformance relative to the benchmark can be attributed to effective duration management and strategic selection of securities that have benefited from the current interest rate environment.
A15: Credit Spread Dynamics: The high credit quality of the portfolio's holdings minimizes exposure to credit spread volatility. The consistent demand for sovereign and AAA-rated instruments has kept credit spreads tight, supporting the fund's performance.
A18: Duration Management: The fund's duration is closely aligned with the benchmark, maturing in April 2026. This alignment ensures that the fund's sensitivity to interest rate changes mirrors that of the benchmark, reducing tracking error and contributing to performance stability.
A22: Conclusion:
A23: The UTI Nifty SDL Plus AAA PSU Bond Apr 2026 75:25 Index Fund offers a well-structured portfolio comprising sovereign and high-quality PSU debt instruments. Its performance, slightly surpassing the benchmark, reflects prudent portfolio management in a stable interest rate environment. Investors seeking predictable income with minimal credit risk may find this fund aligns well with their investment objectives.

Sheet Part 3
A1: Outlook on Indian Fixed Income Markets
A2: The Indian bond market is going through some changes due to both global and local factors. As we move into 2025, there are both challenges and opportunities. Rising US interest rates, pressure on the Indian rupee, and tight liquidity in the banking system are some concerns. However, reports from Axis Mutual Fund and HSBC Mutual Fund suggest that things are still looking positive for bond investors.
A5: Global and Domestic Economic Factors
A6: One big factor affecting Indian bonds is the rise in US interest rates. Even though the US central bank has cut rates, their bond yields have gone up due to inflation and strong economic growth. However, this has not impacted Indian Government Bonds as much as before, since India's economy is on a different path. Also, India's government is working on reducing its fiscal deficit, which helps stabilize bond yields.
A9: In India, inflation is a key concern. Prices went up for a short while but are expected to settle at around 4.5% in the coming months, thanks to good crop production and lower food costs. The Reserve Bank of India is also likely to lower interest rates slowly, which can help businesses and consumers by making borrowing cheaper. The RBI is also taking steps to ensure enough money is available in the financial system.
A13: Banking and Liquidity Trends
A14: The amount of money available in the banking system has decreased, shifting from a surplus to a deficit of ₹1.5 trillion. This has happened due to factors like high credit demand, cash in circulation, and foreign exchange outflows. However, the RBI is expected to take steps such as foreign exchange swaps and liquidity injections to stabilize the situation. A recent ₹2 trillion dividend transfer from RBI should help improve liquidity, but further actions may still be needed.
A18: Opportunities and Risks in the Bond Market
A19: Despite some uncertainty, the long-term outlook for Indian bonds remains strong. Demand for government bonds is expected to stay high, thanks to investment from both foreign and local institutions. Additionally, Indian bonds are set to be included in major global bond indices, like the JP Morgan GBI-EM and Bloomberg Global Bond Index, bringing in an estimated USD 35-40 billion by 2026. This will increase foreign investment and market stability. Global uncertainties remain, especially regarding US policies and trade decisions. However, India's economic position is relatively stable. While the rupee has weakened slightly, it has performed better than most other emerging market currencies. Additionally, India's trade deficit is under control, reducing the risk of major financial problems.
A23: Conclusion
A24: We see India's bond market at an interesting stage. While global challenges exist, India's careful financial management, strong economic indicators, and RBI's proactive approach are providing stability. With possible rate cuts, improved liquidity, and growing foreign investments, 2025 looks promising for fixed-income investments. Investors should focus on long-term bonds and high-rated corporate securities to make the most of upcoming opportunities in the bond market.
