Workbook

Sheet About
A1: Name | B1: Abhimanyu Babbar
A2: Course | B2: Post Graduate Completion Course on Investment Banking
A3: University | B3: IIM Ranchi
A4: Title | B4: Equity Portfolio Hedging Using Futures and Options - Case of Mr. A (HNI)
A5: Date | B5: 28th October 2025

Sheet Table of Contents
A1: S.No | B1: Topic | C1: Page Link (Hyperlinks)
A2: 1 | B2: Executive Summary | C2: 1. Executive Summary
A3: 2 | B3: Introduction | C3: 2. Introduction
A4: 3 | B4: Portfolio Details of Mr. A | C4: 3. Portfolio of Mr. A
A5: 4 | B5: Market Data (As per NSE 28th October 2025). | C5: 4. Market Data (28.10.2025)
A6: 5 | B6: Q1. Hedging Strategy using Futures and Options | C6: 5. Hedging Strategy using F&O
A7: 6 | B7: Q2. Payoff Diagram | C7: 6. Payoff Diagram
A8: 7 | B8: Q3. Breakeven and Profit/Loss for Option Hedge | C8: 7. Breakeven & PL Option Hedge
A9: 8 | B9: Q4. Excel Calculation Process | C9: 8. Excel Calculation Process
A10: 9 | B10: Conclusion | C10: 9. Conclusion
A11: 10 | B11: References | C11: 10. References

Sheet 1. Executive Summary
A1: 1. Executive Summary
A2: Particulars | B2: Details
A3: Objective | B3: Mr. A's long equity portfolio (Ashok Leyland and L&T) using Futures and Options based on NSE data as on 28th October 2025.
A4: Methodology | B4: Used short futures positions and protective puts; modelled P/L, breakeven, and payoffs across scenarios.
A5: Key Results | B5: Ashok Leyland Breakeven | C5: ='7. Breakeven & PL Option Hedge'!C370 -> 189.3
B6: L&T Breakeven | C6: ='7. Breakeven & PL Option Hedge'!C397 -> 2675.3
B7: Futures Hedge | C7: Neutral Payoff
B8: Options Hedge | C8: Limited downside, open upside.
A9: Recommendation | B9: Protective Put for HNI's, allows profit potential while limiting risk.

Sheet 2. Introduction
A1: 2. Introduction
A2: This project demonstrates how an investor can hedge equity exposure using derivatives based on real NSE market data (28th October 2025).
A3: Mr. A, a high Net-Worth Individual (HNI), holds long position in Ashok Leyland and Larsen & Toubro (L&T).
A4: The objective is to design effective hedging strategies using Futures & Options, analyse their performance, and identify breakeven points and payoffs.
A6: Purpose
A7: The goal is to minimize downside risk in Mr. A's portfolio while maintaining upside potential.
A8: The analysis compares:
A9: a) Short Futures Hedge: Locks in prices, removes exposure completely.
A10: b) Protective Put Hedge: Limits losses while allowing profit if prices rise.
A12: Why Hedging?
A13: Hedging shields investors from adverse market movements without selling their holdings.
A14: For HNI's, it's a way to preserve capital and reduce volatility during uncertain markets.
A16: Instruments Used
A18: Instrument | B18: Purpose | C18: Payoff Nature
A19: Futures | B19: Offsetting price risk through short position. | C19: Linear (1:1 gain/loss)
A20: Put Options | B20: Insurance against price fall. | C20: Asymmetric (Limited Loss, Unlimited Profit)
A22: Scope
A23: 1. Apply futures and options strategies for hedging.
A24: 2. Compute profit/loss and breakeven under various price scenarios.
A25: 3. Plot payoff diagram for each case.
A26: 4. Interpret and compare hedging effectiveness.
A28: Assumptions
A29: 1. 100% hedge ratio (full hedge).
A30: 2. Data as per NSE F&O chain on 28th October 2025.
A31: 3. No transaction costs or taxes considered.
A32: 4. Time to expiry same for futures and options.

Sheet 3. Portfolio of Mr. A
A1: 3. Portfolio of Mr. A
A3: Purpose of this Sheet
A4: This sheet provides a clear snapshot of Mr. A's current equity holdings, its investment exposure, and the hedging objectives for each stock.
A5: It serves as the base reference table, from which all futures and options calculations are linked.
A8: Mr. A's Current Portfolio
A10: Stock | B10: Sector | C10: Type of Position | D10: Quantity (No: of Shares) | E10: Purchase Price ₹ | F10: Investment Value ₹ | G10: Current Market Price ₹
A11: Ashok Leyland | B11: Automobile | C11: Long | D11: ='4. Market Data (28.10.2025)'!B17 -> 5000 | E11: ='4. Market Data (28.10.2025)'!B12 -> 180 | F11: =D11*E11 -> 900000 | G11: ='4. Market Data (28.10.2025)'!B13 -> 140.28
A12: L&T | B12: Capital Goods | C12: Long | D12: ='4. Market Data (28.10.2025)'!B80 -> 300 | E12: ='4. Market Data (28.10.2025)'!B75 -> 2600 | F12: =D12*E12 -> 780000 | G12: ='4. Market Data (28.10.2025)'!B76 -> 3935.4
A15: Total Portfolio Value
A16: 1. Initial investment | B16: =SUM(F11:F12) -> 1680000
A17: 2. Current Market Value | B17: =D11*G11+D12*G12 -> 1882020
A18: 3. Total Unrealized P/(L) | B18: =B17-B16 -> 202020
A19: 4. Unrealized P/(L) in % | B19: =B18/B16 -> 0.12025
A22: Portfolio Interpretation
A23: 1. Portfolio Overview
A24: Mr. A holds a two stock equity portfolio representing different sectors - Automobile (Ashok Leyland) and Infrastructure (L&T). The portfolio is moderately concentrated but diversified across cyclical and industrial segments.
A26: 2. Current Market Standing
A27: a. Ashok Leyland: Currently trading below the purchase price.
A28: Unrealized Loss of Ashok Leyland | B28: =(G11-E11)*D11 -> -198600
A29: b. L&T: Currently trading well above the purchase price.
A30: Unrealized Gain of L&T | B30: =(G12-E12)*D12 -> 400620
A31: Overall, the portfolio is in net profit, but exposed to downside risk if the market turns bearish.
A33: 3. Hedging Objective:
A34: The investor wishes to protect existing profits in L&T and limit the further losses in Ashok Leyland.
A35: Therefore, a 100% hedge ratio will be used for both holdings, which involves the usage of futures and protective puts.
A37: 4. Rationale for Selection
A38: a. Ashok Leyland: High beta and cyclical stock, more sensitive to market volatility, hence requires downside protection.
A39: b. L&T: Large-cap infrastructure leader, it is an expensive stock, which is suitable for strategic futures hedge to lock in gains.

Sheet 4. Market Data (28.10.2025)
A1: 4. Market Data (28.10.2025)
A2: Purpose of the sheet
A3: To consolidate real-time market prices and derivatives data (Futures and Options) for both the stocks in Mr. A's portfolio, sourced directly from NSE's official F&O data as on 28th October 2025.
A5: This sheet provides the reference input for:
A6: a. Futures-based hedging.
A7: b. Options-based hedging.
A8: c. Payoff calculations and breakeven analysis.
A10: A. Ashok Leyland
A11: Parameter | B11: Data | C11: Notes/Formula
A12: Purchase Price (₹) | B12: 180 | C12: From Portfolio Details
A13: Underlying Spot Price (₹) | B13: 140.28 | C13: As per NSE Equity
A14: Futures Price (₹) | B14: 140.51 | C14: As per NSE F&O chain
A15: Expiry Date | B15: 28th October 2025
A16: Basis (₹) | B16: =B14-B13 -> 0.23 | C16: Slightly Positive
A17: Total Holding (Shares) | B17: 5000 | C17: From Portfolio Details
A18: Lot Size | B18: 5000
A19: Current Market Exposure (₹) | B19: =B17*B13 -> 701400
A21: Option Chain Data
A22: Strike (₹) | B22: Call Premium (₹) | C22: Put Premium (₹) | D22: Option Type | E22: Remarks
A23: 130 | B23: 10.2 | C23: 0.05 | D23: In The Money Call and Out of Money Put. | E23: Higher call premium due to deep ITM.
A24: 150 | B24: 0.05 | C24: 9.3 | D24: Out of Money Call and In the Money Put. | E24: Used for protective put hedge.
A27: NSE Futures Quote and Option Chain Data Snips of Ashok Leyland
A72: B. L&T
A74: Parameter | B74: Data | C74: Notes/Formula
A75: Purchase Price (₹) | B75: 2600 | C75: From Portfolio Details
A76: Underlying Spot Price (₹) | B76: 3935.4 | C76: As per NSE Equity
A77: Futures Price (₹) | B77: 3928 | C77: As per NSE F&O chain
A78: Expiry Date | B78: 28th October 2025
A79: Basis (₹) | B79: =B77-B76 -> -7.4 | C79: Negative Basis (Discount to Spot).
A80: Total Holding (Shares) | B80: 300 | C80: From Portfolio Details
A81: Lot Size | B81: 150
A82: Current Market Exposure (₹) | B82: =B80*B76 -> 1180620
A84: Option Chain Data
A85: Strike (₹) | B85: Call Premium (₹) | C85: Put Premium (₹) | D85: Option Type | E85: Remarks
A86: 3880 | B86: 46.3 | C86: 0.2 | D86: Near the Money Call. | E86: Premium reflects potential upside.
A87: 4000 | B87: 0.4 | C87: 75.3 | D87: Slightly OTM Call and ITM Put. | E87: Used for protective put hedge.
A90: NSE Futures Quote and Option Chain Data Snips of L&T
A147: Interpretation
A148: 1. Basis Analysis
A149: a. Ashok Leyland shows a slightly positive basis (₹0.23) which indicates the futures trades at a small premium, indicating a mild bullish sentiment.
A150: b. L&T shows a negative basis of ₹7.40 which indicates the Futures trades at a discount, indicating mild bearish sentiment or dividend expectation.
A151: 2. Volatility Insight
A152: a. Higher premiums for ITM puts (e.g.: L&T ₹4,000 Put at ₹75.30) indicating a strong downside protection demand.
A153: b. Ashok Leyland's OTM puts are cheap, which is suitable for a low cost hedge.
A154: 3. Data Sources:
A155: All the market data (Spat, Futures and Options) have been directly extracted from the NSE F&O chain as on 28th October 2025.
A156: The snips of the original data are attached for your validation.

Sheet 5. Hedging Strategy using F&O
A1: 5. Hedging Strategy using Futures & Options
A2: Purpose of the Sheet
A3: To demonstrate how Mr. A hedge his long equity exposure using:
A4: a. Futures Contracts (Short Hedge)
A5: b. Options Contracts (Protective Put)
A7: A. Futures Hedge
A8: Input Type | B8: Source | C8: Ashok Leyland | D8: L&T
A9: Purchase Price | B9: From Portfolio | C9: ='4. Market Data (28.10.2025)'!B12 -> 180 | D9: ='4. Market Data (28.10.2025)'!B75 -> 2600
A10: Current Spot Price | B10: From Market Data | C10: ='4. Market Data (28.10.2025)'!B13 -> 140.28 | D10: ='4. Market Data (28.10.2025)'!B76 -> 3935.4
A11: Futures Price | B11: From Market Data | C11: ='4. Market Data (28.10.2025)'!B14 -> 140.51 | D11: ='4. Market Data (28.10.2025)'!B77 -> 3928
A12: Lot Size | B12: From NSE | C12: ='4. Market Data (28.10.2025)'!B18 -> 5000 | D12: ='4. Market Data (28.10.2025)'!B81 -> 150
A13: Position Held | B13: From Portfolio | C13: ='4. Market Data (28.10.2025)'!B17 -> 5000 | D13: ='4. Market Data (28.10.2025)'!B80 -> 300
A14: Contracts Required | B14: = Quantity/Lot Size | C14: =C13/C12 -> 1 | D14: =D13/D12 -> 2
A15: Expiry Date | B15: From Market Data | C15: ='4. Market Data (28.10.2025)'!B15 -> 28th October 2025 | D15: ='4. Market Data (28.10.2025)'!B78 -> 28th October 2025
A16: Hedge Type | B16: From Hedge Strategy | C16: Short 1 Future. | D16: Short 2 Futures.
A18: Scenario Table for Futures Hedge with regards to Ashok Leyland
A19: % Change in Price | B19: Expected Spot Price at Expiry | C19: Stock P&L | D19: Futures P&L | E19: Net P&L
A20: -0.15 | B20: =$C$10*(1+A20) -> 119.238 | C20: =(B20-$C$10)*$C$13 -> -105210 | D20: =($C$11-B20)*$C$13 -> 106360 | E20: =C20+D20 -> 1150
A21: -0.14 | B21: =$C$10*(1+A21) -> 120.6408 | C21: =(B21-$C$10)*$C$13 -> -98196 | D21: =($C$11-B21)*$C$13 -> 99346 | E21: =C21+D21 -> 1150
A22: -0.13 | B22: =$C$10*(1+A22) -> 122.0436 | C22: =(B22-$C$10)*$C$13 -> -91182 | D22: =($C$11-B22)*$C$13 -> 92332 | E22: =C22+D22 -> 1150
A23: -0.12 | B23: =$C$10*(1+A23) -> 123.4464 | C23: =(B23-$C$10)*$C$13 -> -84168 | D23: =($C$11-B23)*$C$13 -> 85318 | E23: =C23+D23 -> 1150
A24: -0.11 | B24: =$C$10*(1+A24) -> 124.8492 | C24: =(B24-$C$10)*$C$13 -> -77154 | D24: =($C$11-B24)*$C$13 -> 78304 | E24: =C24+D24 -> 1150
A25: -0.1 | B25: =$C$10*(1+A25) -> 126.252 | C25: =(B25-$C$10)*$C$13 -> -70140 | D25: =($C$11-B25)*$C$13 -> 71290 | E25: =C25+D25 -> 1150
A26: -0.09 | B26: =$C$10*(1+A26) -> 127.6548 | C26: =(B26-$C$10)*$C$13 -> -63126 | D26: =($C$11-B26)*$C$13 -> 64276 | E26: =C26+D26 -> 1150
A27: -0.08 | B27: =$C$10*(1+A27) -> 129.0576 | C27: =(B27-$C$10)*$C$13 -> -56112 | D27: =($C$11-B27)*$C$13 -> 57262 | E27: =C27+D27 -> 1150
A28: -0.07 | B28: =$C$10*(1+A28) -> 130.4604 | C28: =(B28-$C$10)*$C$13 -> -49098 | D28: =($C$11-B28)*$C$13 -> 50248 | E28: =C28+D28 -> 1150
A29: -0.06 | B29: =$C$10*(1+A29) -> 131.8632 | C29: =(B29-$C$10)*$C$13 -> -42084 | D29: =($C$11-B29)*$C$13 -> 43234 | E29: =C29+D29 -> 1150
A30: -0.05 | B30: =$C$10*(1+A30) -> 133.266 | C30: =(B30-$C$10)*$C$13 -> -35070 | D30: =($C$11-B30)*$C$13 -> 36220 | E30: =C30+D30 -> 1150
A31: -0.04 | B31: =$C$10*(1+A31) -> 134.6688 | C31: =(B31-$C$10)*$C$13 -> -28056 | D31: =($C$11-B31)*$C$13 -> 29206 | E31: =C31+D31 -> 1150
... A50: 0.15 | B50: =$C$10*(1+A50) -> 161.322 | C50: =(B50-$C$10)*$C$13 -> 105210 | D50: =($C$11-B50)*$C$13 -> -104060 | E50: =C50+D50 -> 1150
A52: Scenario Table for Futures Hedge with regards to L&T
A53: % Change in Price | B53: Expected Spot Price at Expiry | C53: Stock P&L | D53: Futures P&L | E53: Net P&L
A54: -0.15 | B54: =$D$10*(1+A54) -> 3345.09 | C54: =(B54-$D$10)*$D$13 -> -177093 | D54: =($D$11-B54)*$D$12*$D$14 -> 174873 | E54: =C54+D54 -> -2220
A55: -0.14 | B55: =$D$10*(1+A55) -> 3384.444 | C55: =(B55-$D$10)*$D$13 -> -165286.8 | D55: =($D$11-B55)*$D$12*$D$14 -> 163066.8 | E55: =C55+D55 -> -2220
A56: -0.13 | B56: =$D$10*(1+A56) -> 3423.798 | C56: =(B56-$D$10)*$D$13 -> -153480.6 | D56: =($D$11-B56)*$D$12*$D$14 -> 151260.6 | E56: =C56+D56 -> -2220
A57: -0.12 | B57: =$D$10*(1+A57) -> 3463.152 | C57: =(B57-$D$10)*$D$13 -> -141674.4 | D57: =($D$11-B57)*$D$12*$D$14 -> 139454.4 | E57: =C57+D57 -> -2220
A58: -0.11 | B58: =$D$10*(1+A58) -> 3502.506 | C58: =(B58-$D$10)*$D$13 -> -129868.2 | D58: =($D$11-B58)*$D$12*$D$14 -> 127648.2 | E58: =C58+D58 -> -2220
A59: -0.1 | B59: =$D$10*(1+A59) -> 3541.86 | C59: =(B59-$D$10)*$D$13 -> -118062 | D59: =($D$11-B59)*$D$12*$D$14 -> 115842 | E59: =C59+D59 -> -2220
A60: -0.09 | B60: =$D$10*(1+A60) -> 3581.214 | C60: =(B60-$D$10)*$D$13 -> -106255.8 | D60: =($D$11-B60)*$D$12*$D$14 -> 104035.8 | E60: =C60+D60 -> -2220
A61: -0.08 | B61: =$D$10*(1+A61) -> 3620.568 | C61: =(B61-$D$10)*$D$13 -> -94449.6 | D61: =($D$11-B61)*$D$12*$D$14 -> 92229.6 | E61: =C61+D61 -> -2220
A62: -0.07 | B62: =$D$10*(1+A62) -> 3659.922 | C62: =(B62-$D$10)*$D$13 -> -82643.4 | D62: =($D$11-B62)*$D$12*$D$14 -> 80423.4 | E62: =C62+D62 -> -2220
A63: -0.06 | B63: =$D$10*(1+A63) -> 3699.276 | C63: =(B63-$D$10)*$D$13 -> -70837.2 | D63: =($D$11-B63)*$D$12*$D$14 -> 68617.2 | E63: =C63+D63 -> -2220
A64: -0.05 | B64: =$D$10*(1+A64) -> 3738.63 | C64: =(B64-$D$10)*$D$13 -> -59031 | D64: =($D$11-B64)*$D$12*$D$14 -> 56811 | E64: =C64+D64 -> -2220
A65: -0.04 | B65: =$D$10*(1+A65) -> 3777.984 | C65: =(B65-$D$10)*$D$13 -> -47224.8 | D65: =($D$11-B65)*$D$12*$D$14 -> 45004.8 | E65: =C65+D65 -> -2220
... A84: 0.15 | B84: =$D$10*(1+A84) -> 4525.71 | C84: =(B84-$D$10)*$D$13 -> 177093 | D84: =($D$11-B84)*$D$12*$D$14 -> -179313 | E84: =C84+D84 -> -2220
A86: B. Options Hedge (Protective Put)
A87: Input | B87: Ashok Leyland | C87: L&T
A88: Spot Price | B88: =C10 -> 140.28 | C88: =D10 -> 3935.4
A89: Strike Price | B89: ='4. Market Data (28.10.2025)'!A24 -> 150 | C89: ='4. Market Data (28.10.2025)'!A87 -> 4000
A90: Put Premium | B90: ='4. Market Data (28.10.2025)'!C24 -> 9.3 | C90: ='4. Market Data (28.10.2025)'!C87 -> 75.3
A91: Quantity | B91: =C13 -> 5000 | C91: ='4. Market Data (28.10.2025)'!B80 -> 300
A92: No: of Lots | B92: =C14 -> 1 | C92: =D14 -> 2
A93: Expiry | B93: =C15 -> 28th October 2025 | C93: =D15 -> 28th October 2025
A95: Scenario Table for Options Hedge with regards to Ashok Leyland
A96: % Change in Price | B96: Expected Spot Price at Expiry | C96: Stock P&L | D96: Puy Payoff | E96: Net P&L
A97: -0.15 | B97: =$C$10*(1+A97) -> 119.238 | C97: =(B97-$C$10)*$C$13 -> -105210 | D97: =MAX($B$89-B97,0)*$B$91 -> 153810 | E97: =C97+D97 -> 48600
A98: -0.14 | B98: =$C$10*(1+A98) -> 120.6408 | C98: =(B98-$C$10)*$C$13 -> -98196 | D98: =MAX($B$89-B98,0)*$B$91 -> 146796 | E98: =C98+D98 -> 48600
A99: -0.13 | B99: =$C$10*(1+A99) -> 122.0436 | C99: =(B99-$C$10)*$C$13 -> -91182 | D99: =MAX($B$89-B99,0)*$B$91 -> 139782 | E99: =C99+D99 -> 48600
A100: -0.12 | B100: =$C$10*(1+A100) -> 123.4464 | C100: =(B100-$C$10)*$C$13 -> -84168 | D100: =MAX($B$89-B100,0)*$B$91 -> 132768 | E100: =C100+D100 -> 48600
A101: -0.11 | B101: =$C$10*(1+A101) -> 124.8492 | C101: =(B101-$C$10)*$C$13 -> -77154 | D101: =MAX($B$89-B101,0)*$B$91 -> 125754 | E101: =C101+D101 -> 48600
A102: -0.1 | B102: =$C$10*(1+A102) -> 126.252 | C102: =(B102-$C$10)*$C$13 -> -70140 | D102: =MAX($B$89-B102,0)*$B$91 -> 118740 | E102: =C102+D102 -> 48600
A103: -0.09 | B103: =$C$10*(1+A103) -> 127.6548 | C103: =(B103-$C$10)*$C$13 -> -63126 | D103: =MAX($B$89-B103,0)*$B$91 -> 111726 | E103: =C103+D103 -> 48600
A104: -0.08 | B104: =$C$10*(1+A104) -> 129.0576 | C104: =(B104-$C$10)*$C$13 -> -56112 | D104: =MAX($B$89-B104,0)*$B$91 -> 104712 | E104: =C104+D104 -> 48600
A105: -0.07 | B105: =$C$10*(1+A105) -> 130.4604 | C105: =(B105-$C$10)*$C$13 -> -49098 | D105: =MAX($B$89-B105,0)*$B$91 -> 97698 | E105: =C105+D105 -> 48600
A106: -0.06 | B106: =$C$10*(1+A106) -> 131.8632 | C106: =(B106-$C$10)*$C$13 -> -42084 | D106: =MAX($B$89-B106,0)*$B$91 -> 90684 | E106: =C106+D106 -> 48600
A107: -0.05 | B107: =$C$10*(1+A107) -> 133.266 | C107: =(B107-$C$10)*$C$13 -> -35070 | D107: =MAX($B$89-B107,0)*$B$91 -> 83670 | E107: =C107+D107 -> 48600
A108: -0.04 | B108: =$C$10*(1+A108) -> 134.6688 | C108: =(B108-$C$10)*$C$13 -> -28056 | D108: =MAX($B$89-B108,0)*$B$91 -> 76656 | E108: =C108+D108 -> 48600
... A127: 0.15 | B127: =$C$10*(1+A127) -> 161.322 | C127: =(B127-$C$10)*$C$13 -> 105210 | D127: =MAX($B$89-B127,0)*$B$91 -> 0 | E127: =C127+D127 -> 105210
A129: Scenario Table for Options Hedge with regards to L&T
A130: % Change in Price | B130: Expected Spot Price at Expiry | C130: Stock P&L | D130: Puy Payoff | E130: Net P&L
A131: -0.15 | B131: =$D$10*(1+A131) -> 3345.09 | C131: =(B131-$D$10)*$D$13 -> -177093 | D131: =MAX($C$89-B131,0)*$D$13 -> 196473 | E131: =C131+D131 -> 19380
A132: -0.14 | B132: =$D$10*(1+A132) -> 3384.444 | C132: =(B132-$D$10)*$D$13 -> -165286.8 | D132: =MAX($C$89-B132,0)*$D$13 -> 184666.8 | E132: =C132+D132 -> 19380
A133: -0.13 | B133: =$D$10*(1+A133) -> 3423.798 | C133: =(B133-$D$10)*$D$13 -> -153480.6 | D133: =MAX($C$89-B133,0)*$D$13 -> 172860.6 | E133: =C133+D133 -> 19380
A134: -0.12 | B134: =$D$10*(1+A134) -> 3463.152 | C134: =(B134-$D$10)*$D$13 -> -141674.4 | D134: =MAX($C$89-B134,0)*$D$13 -> 161054.4 | E134: =C134+D134 -> 19380
A135: -0.11 | B135: =$D$10*(1+A135) -> 3502.506 | C135: =(B135-$D$10)*$D$13 -> -129868.2 | D135: =MAX($C$89-B135,0)*$D$13 -> 149248.2 | E135: =C135+D135 -> 19380
A136: -0.1 | B136: =$D$10*(1+A136) -> 3541.86 | C136: =(B136-$D$10)*$D$13 -> -118062 | D136: =MAX($C$89-B136,0)*$D$13 -> 137442 | E136: =C136+D136 -> 19380
A137: -0.09 | B137: =$D$10*(1+A137) -> 3581.214 | C137: =(B137-$D$10)*$D$13 -> -106255.8 | D137: =MAX($C$89-B137,0)*$D$13 -> 125635.8 | E137: =C137+D137 -> 19380
A138: -0.08 | B138: =$D$10*(1+A138) -> 3620.568 | C138: =(B138-$D$10)*$D$13 -> -94449.6 | D138: =MAX($C$89-B138,0)*$D$13 -> 113829.6 | E138: =C138+D138 -> 19380
A139: -0.07 | B139: =$D$10*(1+A139) -> 3659.922 | C139: =(B139-$D$10)*$D$13 -> -82643.4 | D139: =MAX($C$89-B139,0)*$D$13 -> 102023.4 | E139: =C139+D139 -> 19380
A140: -0.06 | B140: =$D$10*(1+A140) -> 3699.276 | C140: =(B140-$D$10)*$D$13 -> -70837.2 | D140: =MAX($C$89-B140,0)*$D$13 -> 90217.2 | E140: =C140+D140 -> 19380
A141: -0.05 | B141: =$D$10*(1+A141) -> 3738.63 | C141: =(B141-$D$10)*$D$13 -> -59031 | D141: =MAX($C$89-B141,0)*$D$13 -> 78411 | E141: =C141+D141 -> 19380
A142: -0.04 | B142: =$D$10*(1+A142) -> 3777.984 | C142: =(B142-$D$10)*$D$13 -> -47224.8 | D142: =MAX($C$89-B142,0)*$D$13 -> 66604.8 | E142: =C142+D142 -> 19380
... A161: 0.15 | B161: =$D$10*(1+A161) -> 4525.71 | C161: =(B161-$D$10)*$D$13 -> 177093 | D161: =MAX($C$89-B161,0)*$D$13 -> 0 | E161: =C161+D161 -> 177093
A163: Summary Table
A164: Stock | B164: Hedge Type | C164: Hedge Instrument (Future/Put Strike) (₹) | D164: Hedge Outcome | E164: P/L at Initiation (₹)
A165: Ashok Leyland | B165: Futures (Short 1 Lot) | C165: 140.51 Futures, 140.28 Initial Spot | D165: Constant Gain | E165: 1150
B166: Put Option (1 lot, Strike 150, Premium 9.30) | C166: 150 Put, 140.28 Initial Spot | D166: Minimum Profit = ₹48,600 | E166: Variable, rises when New Spot is above ₹150.
A167: L&T | B167: Futures (Short 2 Lots) | C167: 3,928 Futures, 3,935.40 Initial Spot | D167: Constant Loss | E167: -2220
B168: Put Option (2 lots, Strike 4000, Premium 75.30) | C168: 4,000 Put, 3,935.40 Initial Spot | D168: Minimum Profit = ₹19,380 | E168: Variable, rises when New Spot is above ₹4000.
A170: Interpretation of the Hedging Strategy using Futures and Options
A171: a. The futures hedge neutralizes all price risk, any gain/loss in the stock is offset by an equal and opposite change in the futures position.
A172: b. The small constant P/L arises from the initial basis (difference between futures and spot price): – Ashok Leyland locked in a ₹1,150 gain because the futures traded slightly above the spot (positive basis). – L&T incurred a ₹2,220 loss because its futures traded below the spot (negative basis).
A173: c. The options hedge behaves asymmetrically, it limits downside risk but allows upside participation.
A174: d. The minimum profit corresponds to the worst-case scenario (when the stock price falls to or below the strike).
A175: e. Beyond the strike, profit increases as the stock price rises, since the investor still owns the underlying shares.
A177: Final Insights
A178: Comparison Metric | B178: Futures Hedge | C178: Options Hedge | D178: For Mr. A, both instruments serve hedging purposes effectively. Futures provide complete protection but eliminate upside potential, whereas options require a cost (premium) but maintain growth participation, making them more suitable for HNIs seeking capital protection with upside flexibility.
A179: Risk Coverage | B179: Complete (linear) | C179: Partial but limited downside
A180: Cost | B180: Nil (only margin) | C180: Premium paid upfront
A181: Outcome if Market Rises | B181: No benefit (locked return) | C181: Gains continue after breakeven
...

Sheet 6. Payoff Diagram
A1: 6. PAYOFF DIAGRAMS
A3: Section A - Ashok Leyland
A5: Payoff Table from 5. Hedging Strategy using F&O (Previous Sheet).
A6: Spot Price (₹) | B6: Stock P/L (₹) | C6: Futures Hedge P/L (₹) | D6: Net P/L (Stock + Futures) (₹) | E6: Option Hedge P/L (₹) | F6: Net P/L (Stock + Options) (₹)
A7: ='5. Hedging Strategy using F&O'!B20 -> 119.238 | B7: ='5. Hedging Strategy using F&O'!C20 -> -105210 | C7: ='5. Hedging Strategy using F&O'!D20 -> 106360 | D7: =B7+C7 -> 1150 | E7: ='5. Hedging Strategy using F&O'!D97 -> 153810 | F7: =E7+B7 -> 48600
A8: ='5. Hedging Strategy using F&O'!B21 -> 120.6408 | B8: ='5. Hedging Strategy using F&O'!C21 -> -98196 | C8: ='5. Hedging Strategy using F&O'!D21 -> 99346 | D8: =B8+C8 -> 1150 | E8: ='5. Hedging Strategy using F&O'!D98 -> 146796 | F8: =E8+B8 -> 48600
A9: ='5. Hedging Strategy using F&O'!B22 -> 122.0436 | B9: ='5. Hedging Strategy using F&O'!C22 -> -91182 | C9: ='5. Hedging Strategy using F&O'!D22 -> 92332 | D9: =B9+C9 -> 1150 | E9: ='5. Hedging Strategy using F&O'!D99 -> 139782 | F9: =E9+B9 -> 48600
A10: ='5. Hedging Strategy using F&O'!B23 -> 123.4464 | B10: ='5. Hedging Strategy using F&O'!C23 -> -84168 | C10: ='5. Hedging Strategy using F&O'!D23 -> 85318 | D10: =B10+C10 -> 1150 | E10: ='5. Hedging Strategy using F&O'!D100 -> 132768 | F10: =E10+B10 -> 48600
A11: ='5. Hedging Strategy using F&O'!B24 -> 124.8492 | B11: ='5. Hedging Strategy using F&O'!C24 -> -77154 | C11: ='5. Hedging Strategy using F&O'!D24 -> 78304 | D11: =B11+C11 -> 1150 | E11: ='5. Hedging Strategy using F&O'!D101 -> 125754 | F11: =E11+B11 -> 48600
A12: ='5. Hedging Strategy using F&O'!B25 -> 126.252 | B12: ='5. Hedging Strategy using F&O'!C25 -> -70140 | C12: ='5. Hedging Strategy using F&O'!D25 -> 71290 | D12: =B12+C12 -> 1150 | E12: ='5. Hedging Strategy using F&O'!D102 -> 118740 | F12: =E12+B12 -> 48600
A13: ='5. Hedging Strategy using F&O'!B26 -> 127.6548 | B13: ='5. Hedging Strategy using F&O'!C26 -> -63126 | C13: ='5. Hedging Strategy using F&O'!D26 -> 64276 | D13: =B13+C13 -> 1150 | E13: ='5. Hedging Strategy using F&O'!D103 -> 111726 | F13: =E13+B13 -> 48600
A14: ='5. Hedging Strategy using F&O'!B27 -> 129.0576 | B14: ='5. Hedging Strategy using F&O'!C27 -> -56112 | C14: ='5. Hedging Strategy using F&O'!D27 -> 57262 | D14: =B14+C14 -> 1150 | E14: ='5. Hedging Strategy using F&O'!D104 -> 104712 | F14: =E14+B14 -> 48600
A15: ='5. Hedging Strategy using F&O'!B28 -> 130.4604 | B15: ='5. Hedging Strategy using F&O'!C28 -> -49098 | C15: ='5. Hedging Strategy using F&O'!D28 -> 50248 | D15: =B15+C15 -> 1150 | E15: ='5. Hedging Strategy using F&O'!D105 -> 97698 | F15: =E15+B15 -> 48600
A16: ='5. Hedging Strategy using F&O'!B29 -> 131.8632 | B16: ='5. Hedging Strategy using F&O'!C29 -> -42084 | C16: ='5. Hedging Strategy using F&O'!D29 -> 43234 | D16: =B16+C16 -> 1150 | E16: ='5. Hedging Strategy using F&O'!D106 -> 90684 | F16: =E16+B16 -> 48600
A17: ='5. Hedging Strategy using F&O'!B30 -> 133.266 | B17: ='5. Hedging Strategy using F&O'!C30 -> -35070 | C17: ='5. Hedging Strategy using F&O'!D30 -> 36220 | D17: =B17+C17 -> 1150 | E17: ='5. Hedging Strategy using F&O'!D107 -> 83670 | F17: =E17+B17 -> 48600
A18: ='5. Hedging Strategy using F&O'!B31 -> 134.6688 | B18: ='5. Hedging Strategy using F&O'!C31 -> -28056 | C18: ='5. Hedging Strategy using F&O'!D31 -> 29206 | D18: =B18+C18 -> 1150 | E18: ='5. Hedging Strategy using F&O'!D108 -> 76656 | F18: =E18+B18 -> 48600
... A37: ='5. Hedging Strategy using F&O'!B50 -> 161.322 | B37: ='5. Hedging Strategy using F&O'!C50 -> 105210 | C37: ='5. Hedging Strategy using F&O'!D50 -> -104060 | D37: =B37+C37 -> 1150 | E37: ='5. Hedging Strategy using F&O'!D127 -> 0 | F37: =E37+B37 -> 105210
A82: Section B - L&T
A84: Payoff Table from 5. Hedging Strategy using F&O (Previous Sheet).
A85: Spot Price (₹) | B85: Stock P/L (₹) | C85: Futures Hedge P/L (₹) | D85: Net P/L (Stock + Futures) (₹) | E85: Option Hedge P/L (₹) | F85: Net P/L (Stock + Options) (₹)
A86: ='5. Hedging Strategy using F&O'!B131 -> 3345.09 | B86: ='5. Hedging Strategy using F&O'!C131 -> -177093 | C86: ='5. Hedging Strategy using F&O'!D54 -> 174873 | D86: =B86+C86 -> -2220 | E86: ='5. Hedging Strategy using F&O'!D131 -> 196473 | F86: =E86+B86 -> 19380
A87: ='5. Hedging Strategy using F&O'!B132 -> 3384.444 | B87: ='5. Hedging Strategy using F&O'!C132 -> -165286.8 | C87: ='5. Hedging Strategy using F&O'!D55 -> 163066.8 | D87: =B87+C87 -> -2220 | E87: ='5. Hedging Strategy using F&O'!D132 -> 184666.8 | F87: =E87+B87 -> 19380
A88: ='5. Hedging Strategy using F&O'!B133 -> 3423.798 | B88: ='5. Hedging Strategy using F&O'!C133 -> -153480.6 | C88: ='5. Hedging Strategy using F&O'!D56 -> 151260.6 | D88: =B88+C88 -> -2220 | E88: ='5. Hedging Strategy using F&O'!D133 -> 172860.6 | F88: =E88+B88 -> 19380
A89: ='5. Hedging Strategy using F&O'!B134 -> 3463.152 | B89: ='5. Hedging Strategy using F&O'!C134 -> -141674.4 | C89: ='5. Hedging Strategy using F&O'!D57 -> 139454.4 | D89: =B89+C89 -> -2220 | E89: ='5. Hedging Strategy using F&O'!D134 -> 161054.4 | F89: =E89+B89 -> 19380
A90: ='5. Hedging Strategy using F&O'!B135 -> 3502.506 | B90: ='5. Hedging Strategy using F&O'!C135 -> -129868.2 | C90: ='5. Hedging Strategy using F&O'!D58 -> 127648.2 | D90: =B90+C90 -> -2220 | E90: ='5. Hedging Strategy using F&O'!D135 -> 149248.2 | F90: =E90+B90 -> 19380
A91: ='5. Hedging Strategy using F&O'!B136 -> 3541.86 | B91: ='5. Hedging Strategy using F&O'!C136 -> -118062 | C91: ='5. Hedging Strategy using F&O'!D59 -> 115842 | D91: =B91+C91 -> -2220 | E91: ='5. Hedging Strategy using F&O'!D136 -> 137442 | F91: =E91+B91 -> 19380
A92: ='5. Hedging Strategy using F&O'!B137 -> 3581.214 | B92: ='5. Hedging Strategy using F&O'!C137 -> -106255.8 | C92: ='5. Hedging Strategy using F&O'!D60 -> 104035.8 | D92: =B92+C92 -> -2220 | E92: ='5. Hedging Strategy using F&O'!D137 -> 125635.8 | F92: =E92+B92 -> 19380
A93: ='5. Hedging Strategy using F&O'!B138 -> 3620.568 | B93: ='5. Hedging Strategy using F&O'!C138 -> -94449.6 | C93: ='5. Hedging Strategy using F&O'!D61 -> 92229.6 | D93: =B93+C93 -> -2220 | E93: ='5. Hedging Strategy using F&O'!D138 -> 113829.6 | F93: =E93+B93 -> 19380
A94: ='5. Hedging Strategy using F&O'!B139 -> 3659.922 | B94: ='5. Hedging Strategy using F&O'!C139 -> -82643.4 | C94: ='5. Hedging Strategy using F&O'!D62 -> 80423.4 | D94: =B94+C94 -> -2220 | E94: ='5. Hedging Strategy using F&O'!D139 -> 102023.4 | F94: =E94+B94 -> 19380
A95: ='5. Hedging Strategy using F&O'!B140 -> 3699.276 | B95: ='5. Hedging Strategy using F&O'!C140 -> -70837.2 | C95: ='5. Hedging Strategy using F&O'!D63 -> 68617.2 | D95: =B95+C95 -> -2220 | E95: ='5. Hedging Strategy using F&O'!D140 -> 90217.2 | F95: =E95+B95 -> 19380
A96: ='5. Hedging Strategy using F&O'!B141 -> 3738.63 | B96: ='5. Hedging Strategy using F&O'!C141 -> -59031 | C96: ='5. Hedging Strategy using F&O'!D64 -> 56811 | D96: =B96+C96 -> -2220 | E96: ='5. Hedging Strategy using F&O'!D141 -> 78411 | F96: =E96+B96 -> 19380
A97: ='5. Hedging Strategy using F&O'!B142 -> 3777.984 | B97: ='5. Hedging Strategy using F&O'!C142 -> -47224.8 | C97: ='5. Hedging Strategy using F&O'!D65 -> 45004.8 | D97: =B97+C97 -> -2220 | E97: ='5. Hedging Strategy using F&O'!D142 -> 66604.8 | F97: =E97+B97 -> 19380
... A116: ='5. Hedging Strategy using F&O'!B161 -> 4525.71 | B116: ='5. Hedging Strategy using F&O'!C161 -> 177093 | C116: ='5. Hedging Strategy using F&O'!D84 -> -179313 | D116: =B116+C116 -> -2220 | E116: ='5. Hedging Strategy using F&O'!D161 -> 0 | F116: =E116+B116 -> 177093
A162: Summary of Payoff Diagram
A163: Stock | B163: Hedge Type | C163: Shape of Payoff | D163: Key Features | E163: Breakeven (₹) | F163: Max Loss (₹)
A164: Ashok Leyland | B164: Futures | C164: Flat | D164: Full hedge, no upside. | E164: 0 | F164: 0
A165: Ashok Leyland | B165: Options | C165: Kinked (Protective Put) | D165: Downside Capped, upside open. | E165: 159.3 | F165: 46500
A166: L&T | B166: Futures | C166: Flat | D166: Full hedge, no upside. | E166: 0 | F166: 0
A167: L&T | B167: Options | C167: Kinked (Protective Put) | D167: Downside capped, upside open. | E167: 4075.3 | F167: 22590
A169: Interpretation of the Payoff Diagram
A170: a. Futures hedge neutralizes all risk, producing a flat payoff line of no loss, no gain from price movements.
A171: b. Options hedge creates an asymmetric payoff, losses are capped (premium cost) while potential gains beyond the strike are unlimited.
A172: c. Hence, for long-term investors like Mr. A, options provide flexible protection, whereas futures are more suitable for short-term certainty.

Sheet 7. Breakeven & PL Option Hedge
A1: 7. BREAKEVEN & P/L OPTION HEDGE
A3: Objective:
A4: To calculate the breakeven points and net P/L for both Call and Put Options hedges, reflecting real NSE premiums and spot levels as of 28th October 2025.
A7: 1. Inputs: Linked from the Market Data Sheet
A8: Parameter | B8: Ashok Leyland | C8: L&T
A9: Purchase Price | B9: 180 | C9: 2600
A10: Spot Price | B10: ='4. Market Data (28.10.2025)'!B13 -> 140.28 | C10: ='4. Market Data (28.10.2025)'!B76 -> 3935.4
A11: Strike (Call) | B11: ='4. Market Data (28.10.2025)'!A24 -> 150 | C11: ='4. Market Data (28.10.2025)'!A86 -> 3880
A12: Call Premium | B12: ='4. Market Data (28.10.2025)'!B24 -> 0.05 | C12: ='4. Market Data (28.10.2025)'!B86 -> 46.3
A13: Strike (Put) | B13: ='4. Market Data (28.10.2025)'!A24 -> 150 | C13: ='4. Market Data (28.10.2025)'!A87 -> 4000
A14: Put Premium | B14: ='4. Market Data (28.10.2025)'!C24 -> 9.3 | C14: ='4. Market Data (28.10.2025)'!C87 -> 75.3
A15: Lot Size | B15: ='4. Market Data (28.10.2025)'!B18 -> 5000 | C15: ='4. Market Data (28.10.2025)'!B81 -> 150
A16: No: of Contracts | B16: ='4. Market Data (28.10.2025)'!B17/'4. Market Data (28.10.2025)'!B18 -> 1 | C16: ='4. Market Data (28.10.2025)'!B80/'4. Market Data (28.10.2025)'!B81 -> 2
A18: 2. Breakeven Point Calculation
A19: There will be two breakeven per stock - one for the call hedge and one for the put hedge.
A21: Hedge type | B21: Formula | C21: Interpretation
A22: Call Option | B22: =Strike Price + Premium Paid | C22: Above this - Profit zone.
A23: Put Options | B23: =Strike Price - Premium Paid | C23: Below this - Profit zone.
A26: Stock | B26: Call Breakeven Point | C26: Put Breakeven Point
A27: Ashok Leyland | B27: =B11+B12 -> 150.05 | C27: =B13-B14 -> 140.7
A28: L&T | B28: =C11+C12 -> 3926.3 | C28: =C13-C14 -> 3924.7
A30: 3. Option Payoff Calculation
A32: Ashok Leyland
A33: Spot Price | B33: Call Option Payoff | C33: Put Option Payoff
A34: 120 | B34: =MAX(A34-$B$11,0)*$B$15*$B$16-($B$12*$B$15*$B$16) -> -250 | C34: =MAX($B$13-A34,0)*$B$15*$B$16-($B$14*$B$15*$B$16) -> 103500
A35: 122 | B35: =MAX(A35-$B$11,0)*$B$15*$B$16-($B$12*$B$15*$B$16) -> -250 | C35: =MAX($B$13-A35,0)*$B$15*$B$16-($B$14*$B$15*$B$16) -> 93500
A36: 124 | B36: =MAX(A36-$B$11,0)*$B$15*$B$16-($B$12*$B$15*$B$16) -> -250 | C36: =MAX($B$13-A36,0)*$B$15*$B$16-($B$14*$B$15*$B$16) -> 83500
A37: 126 | B37: =MAX(A37-$B$11,0)*$B$15*$B$16-($B$12*$B$15*$B$16) -> -250 | C37: =MAX($B$13-A37,0)*$B$15*$B$16-($B$14*$B$15*$B$16) -> 73500
A38: 128 | B38: =MAX(A38-$B$11,0)*$B$15*$B$16-($B$12*$B$15*$B$16) -> -250 | C38: =MAX($B$13-A38,0)*$B$15*$B$16-($B$14*$B$15*$B$16) -> 63500
A39: 130 | B39: =MAX(A39-$B$11,0)*$B$15*$B$16-($B$12*$B$15*$B$16) -> -250 | C39: =MAX($B$13-A39,0)*$B$15*$B$16-($B$14*$B$15*$B$16) -> 53500
A40: 132 | B40: =MAX(A40-$B$11,0)*$B$15*$B$16-($B$12*$B$15*$B$16) -> -250 | C40: =MAX($B$13-A40,0)*$B$15*$B$16-($B$14*$B$15*$B$16) -> 43500
A41: 134 | B41: =MAX(A41-$B$11,0)*$B$15*$B$16-($B$12*$B$15*$B$16) -> -250 | C41: =MAX($B$13-A41,0)*$B$15*$B$16-($B$14*$B$15*$B$16) -> 33500
A42: 136 | B42: =MAX(A42-$B$11,0)*$B$15*$B$16-($B$12*$B$15*$B$16) -> -250 | C42: =MAX($B$13-A42,0)*$B$15*$B$16-($B$14*$B$15*$B$16) -> 23500
A43: 138 | B43: =MAX(A43-$B$11,0)*$B$15*$B$16-($B$12*$B$15*$B$16) -> -250 | C43: =MAX($B$13-A43,0)*$B$15*$B$16-($B$14*$B$15*$B$16) -> 13500
A44: 140 | B44: =MAX(A44-$B$11,0)*$B$15*$B$16-($B$12*$B$15*$B$16) -> -250 | C44: =MAX($B$13-A44,0)*$B$15*$B$16-($B$14*$B$15*$B$16) -> 3500
A45: 142 | B45: =MAX(A45-$B$11,0)*$B$15*$B$16-($B$12*$B$15*$B$16) -> -250 | C45: =MAX($B$13-A45,0)*$B$15*$B$16-($B$14*$B$15*$B$16) -> -6500
... A71: 194 | B71: =MAX(A71-$B$11,0)*$B$15*$B$16-($B$12*$B$15*$B$16) -> 219750 | C71: =MAX($B$13-A71,0)*$B$15*$B$16-($B$14*$B$15*$B$16) -> -46500
A94: L&T
A95: Spot Price | B95: Call Option Payoff | C95: Put Option Payoff
A96: 3700 | B96: =MAX(A96-$C$11,0)*$C$15*$C$16-($C$12*$C$15*$C$16) -> -13890 | C96: =MAX($C$13-A96,0)*$C$15*$C$16-($C$14*$C$15*$C$16) -> 67410
A97: 3710 | B97: =MAX(A97-$C$11,0)*$C$15*$C$16-($C$12*$C$15*$C$16) -> -13890 | C97: =MAX($C$13-A97,0)*$C$15*$C$16-($C$14*$C$15*$C$16) -> 64410
A98: 3720 | B98: =MAX(A98-$C$11,0)*$C$15*$C$16-($C$12*$C$15*$C$16) -> -13890 | C98: =MAX($C$13-A98,0)*$C$15*$C$16-($C$14*$C$15*$C$16) -> 61410
A99: 3730 | B99: =MAX(A99-$C$11,0)*$C$15*$C$16-($C$12*$C$15*$C$16) -> -13890 | C99: =MAX($C$13-A99,0)*$C$15*$C$16-($C$14*$C$15*$C$16) -> 58410
A100: 3740 | B100: =MAX(A100-$C$11,0)*$C$15*$C$16-($C$12*$C$15*$C$16) -> -13890 | C100: =MAX($C$13-A100,0)*$C$15*$C$16-($C$14*$C$15*$C$16) -> 55410
A101: 3750 | B101: =MAX(A101-$C$11,0)*$C$15*$C$16-($C$12*$C$15*$C$16) -> -13890 | C101: =MAX($C$13-A101,0)*$C$15*$C$16-($C$14*$C$15*$C$16) -> 52410
A102: 3760 | B102: =MAX(A102-$C$11,0)*$C$15*$C$16-($C$12*$C$15*$C$16) -> -13890 | C102: =MAX($C$13-A102,0)*$C$15*$C$16-($C$14*$C$15*$C$16) -> 49410
A103: 3770 | B103: =MAX(A103-$C$11,0)*$C$15*$C$16-($C$12*$C$15*$C$16) -> -13890 | C103: =MAX($C$13-A103,0)*$C$15*$C$16-($C$14*$C$15*$C$16) -> 46410
A104: 3780 | B104: =MAX(A104-$C$11,0)*$C$15*$C$16-($C$12*$C$15*$C$16) -> -13890 | C104: =MAX($C$13-A104,0)*$C$15*$C$16-($C$14*$C$15*$C$16) -> 43410
A105: 3790 | B105: =MAX(A105-$C$11,0)*$C$15*$C$16-($C$12*$C$15*$C$16) -> -13890 | C105: =MAX($C$13-A105,0)*$C$15*$C$16-($C$14*$C$15*$C$16) -> 40410
A106: 3800 | B106: =MAX(A106-$C$11,0)*$C$15*$C$16-($C$12*$C$15*$C$16) -> -13890 | C106: =MAX($C$13-A106,0)*$C$15*$C$16-($C$14*$C$15*$C$16) -> 37410
A107: 3810 | B107: =MAX(A107-$C$11,0)*$C$15*$C$16-($C$12*$C$15*$C$16) -> -13890 | C107: =MAX($C$13-A107,0)*$C$15*$C$16-($C$14*$C$15*$C$16) -> 34410
... A146: 4200 | B146: =MAX(A146-$C$11,0)*$C$15*$C$16-($C$12*$C$15*$C$16) -> 82110 | C146: =MAX($C$13-A146,0)*$C$15*$C$16-($C$14*$C$15*$C$16) -> -22590
A169: 4. Stock P/L (Unhedged Exposure)
A171: Ashok Leyland
A172: =A33 -> Spot Price | B172: Stock P/L
A173: =A34 -> 120 | B173: =(A173-$B$9)*$B$15*$B$16 -> -300000
A174: =A35 -> 122 | B174: =(A174-$B$9)*$B$15*$B$16 -> -290000
A175: =A36 -> 124 | B175: =(A175-$B$9)*$B$15*$B$16 -> -280000
A176: =A37 -> 126 | B176: =(A176-$B$9)*$B$15*$B$16 -> -270000
A177: =A38 -> 128 | B177: =(A177-$B$9)*$B$15*$B$16 -> -260000
A178: =A39 -> 130 | B178: =(A178-$B$9)*$B$15*$B$16 -> -250000
A179: =A40 -> 132 | B179: =(A179-$B$9)*$B$15*$B$16 -> -240000
A180: =A41 -> 134 | B180: =(A180-$B$9)*$B$15*$B$16 -> -230000
A181: =A42 -> 136 | B181: =(A181-$B$9)*$B$15*$B$16 -> -220000
A182: =A43 -> 138 | B182: =(A182-$B$9)*$B$15*$B$16 -> -210000
A183: =A44 -> 140 | B183: =(A183-$B$9)*$B$15*$B$16 -> -200000
A184: =A45 -> 142 | B184: =(A184-$B$9)*$B$15*$B$16 -> -190000
... A210: =A71 -> 194 | B210: =(A210-$B$9)*$B$15*$B$16 -> 70000
A213: L&T
A214: =A95 -> Spot Price | B214: Stock P/L
A215: =A96 -> 3700 | B215: =(A215-$C$9)*$C$15*$C$16 -> 330000
A216: =A97 -> 3710 | B216: =(A216-$C$9)*$C$15*$C$16 -> 333000
A217: =A98 -> 3720 | B217: =(A217-$C$9)*$C$15*$C$16 -> 336000
A218: =A99 -> 3730 | B218: =(A218-$C$9)*$C$15*$C$16 -> 339000
A219: =A100 -> 3740 | B219: =(A219-$C$9)*$C$15*$C$16 -> 342000
A220: =A101 -> 3750 | B220: =(A220-$C$9)*$C$15*$C$16 -> 345000
A221: =A102 -> 3760 | B221: =(A221-$C$9)*$C$15*$C$16 -> 348000
A222: =A103 -> 3770 | B222: =(A222-$C$9)*$C$15*$C$16 -> 351000
A223: =A104 -> 3780 | B223: =(A223-$C$9)*$C$15*$C$16 -> 354000
A224: =A105 -> 3790 | B224: =(A224-$C$9)*$C$15*$C$16 -> 357000
A225: =A106 -> 3800 | B225: =(A225-$C$9)*$C$15*$C$16 -> 360000
A226: =A107 -> 3810 | B226: =(A226-$C$9)*$C$15*$C$16 -> 363000
... A265: =A146 -> 4200 | B265: =(A265-$C$9)*$C$15*$C$16 -> 480000
A267: 5. Option P/L and Net P/L Computation
A269: Ashok Leyland
A270: =A172 -> Spot Price | B270: =B172 -> Stock P/L | C270: Put Option (Protective Put) | D270: Net P/L
A271: =A173 -> 120 | B271: =B173 -> -300000 | C271: =C34 -> 103500 | D271: =B271+C271 -> -196500
A272: =A174 -> 122 | B272: =B174 -> -290000 | C272: =C35 -> 93500 | D272: =B272+C272 -> -196500
A273: =A175 -> 124 | B273: =B175 -> -280000 | C273: =C36 -> 83500 | D273: =B273+C273 -> -196500
A274: =A176 -> 126 | B274: =B176 -> -270000 | C274: =C37 -> 73500 | D274: =B274+C274 -> -196500
A275: =A177 -> 128 | B275: =B177 -> -260000 | C275: =C38 -> 63500 | D275: =B275+C275 -> -196500
A276: =A178 -> 130 | B276: =B178 -> -250000 | C276: =C39 -> 53500 | D276: =B276+C276 -> -196500
A277: =A179 -> 132 | B277: =B179 -> -240000 | C277: =C40 -> 43500 | D277: =B277+C277 -> -196500
A278: =A180 -> 134 | B278: =B180 -> -230000 | C278: =C41 -> 33500 | D278: =B278+C278 -> -196500
A279: =A181 -> 136 | B279: =B181 -> -220000 | C279: =C42 -> 23500 | D279: =B279+C279 -> -196500
A280: =A182 -> 138 | B280: =B182 -> -210000 | C280: =C43 -> 13500 | D280: =B280+C280 -> -196500
A281: =A183 -> 140 | B281: =B183 -> -200000 | C281: =C44 -> 3500 | D281: =B281+C281 -> -196500
A282: =A184 -> 142 | B282: =B184 -> -190000 | C282: =C45 -> -6500 | D282: =B282+C282 -> -196500
... A308: =A210 -> 194 | B308: =B210 -> 70000 | C308: =C71 -> -46500 | D308: =B308+C308 -> 23500
A310: L&T
...

Sheet 8. Excel Calculation Process
A1: 8. EXCEL CALCULATION PROCESS
A2: 1) Spot Price Range:
A3: A series of hypothetical future spot prices were generated around the current NSE spot levels to perform sensitivity analysis for both Ashok Leyland and L&T.
A4: 2) Stock P/L Calculation:
A5: Stock P/L=(Spot Price−Buy Price)×Lot Size
A6: This captures the unrealized profit or loss on the equity position as market prices fluctuate.
A7: 3) Futures Hedge P/L:
A8: Futures P/L=(Sell Price−Spot Price)×Lot Size
A9: Represents gains or losses on the short futures contract, offsetting the stock’s exposure to price changes.
A10: 4) Net P/L (Stock + Futures):
A11: The stock and futures P/L were summed to analyse the combined effect.
A12: A near-constant Net P/L indicates an effective hedge with minimal directional exposure.
... A28: All calculations were dynamically linked in Excel using cell references, ensuring real-time updates across sheets when market inputs or assumptions change.

Sheet 9. Conclusion
A1: 9. CONCLUSION
A2: The hedging analysis demonstrates that futures effectively neutralized price risk, resulting in near-constant net returns, while options provided asymmetric protection, which limited the downside losses and retaining upside potential. Ashok Leyland’s hedge yielded stable profits, whereas L&T’s minor loss highlights contract size sensitivity. Overall, both strategies reduced portfolio volatility and safeguarded Mr. A’s equity exposure under varying market conditions.

Sheet 10. References
A1: 10. REFERENCES
A2: 1) National Stock Exchange of India (NSE)
A3: Futures and Options data for Ashok Leyland and L&T, as on 28th October 2025.
A4: https://www.nseindia.com/
A5: 2) Company Financial Information
A6: Historical stock prices and equity details accessed via NSE equity section.
A7: 3) Investopedia & NSE Derivatives Module
A8: Conceptual understanding of hedging strategies, payoff diagrams, and breakeven analysis.
A9: https://www.investopedia.com
A10: https://nseindia.com/learn/ncfm
