Workbook

Sheet Details
A1: Subject: | B1: Securities Analysis and Portfolio Management
A2: Topic: | B2: Fundamental Analysis: NTPC, Dabur India, HDFC Life Insurance, Adani Enterprises and Hindalco Industries
A3: By: | B3: Abhimanyu Babbar

Sheet NTPC
A1: NTPC | H1: NTPC
A2: Consolidated Profit & Loss account | B2: ------------------- in Rs. Cr. ------------------- | H2: Consolidated Balance Sheet | I2: ------------------- in Rs. Cr. -------------------
B3: Mar '25 | C3: Mar '24 | D3: Mar '23 | E3: Mar '22 | F3: Mar '21 | I3: Mar 25 | J3: 45352 | K3: 44986 | L3: 44621 | M3: 44256
B5: 12 mths | C5: 12 mths | D5: 12 mths | E5: 12 mths | F5: 12 mths | I5: 12 mths | J5: 12 mths | K5: 12 mths | L5: 12 mths | M5: 12 mths
A7: Income | H7: EQUITIES AND LIABILITIES
A8: Sales Turnover | B8: 188138.06 | C8: 178500.88 | D8: 176206.93 | E8: 132669.28 | F8: 111531.15 | H8: SHAREHOLDER'S FUNDS
A9: Net Sales | B9: 188138.06 | C9: 178500.88 | D9: 176206.93 | E9: 132669.28 | F9: 111531.15 | H9: Equity Share Capital | I9: 9696.67 | J9: 9696.67 | K9: 9696.67 | L9: 9696.67 | M9: 9696.67
A10: Other Income | B10: 6426.31 | C10: 3541.9 | D10: 1272.58 | E10: 3709.15 | F10: 4280.91 | H10: Total Share Capital | I10: 9696.67 | J10: 9696.67 | K10: 9696.67 | L10: 9696.67 | M10: 9696.67
A11: Total Income | B11: 194564.37 | C11: 182042.78 | D11: 177479.51 | E11: 136378.43 | F11: 115812.06 | H11: Reserves and Surplus | I11: 174374.49 | J11: 151012.6 | K11: 137326.5 | L11: 125677.07 | M11: 116041.8
A12: Expenditure | H12: Total Reserves and Surplus | I12: 174374.49 | J12: 151012.6 | K12: 137326.5 | L12: 125677.07 | M12: 116041.8
A13: Raw Materials | B13: 0 | C13: 282.38 | D13: 251.96 | E13: 0 | F13: 99.49 | H13: Total Shareholders Funds | I13: 184071.16 | J13: 160709.27 | K13: 147023.17 | L13: 135373.74 | M13: 125738.47
A14: Power & Fuel Cost | B14: 101514.84 | C14: 105329.61 | D14: 110429.88 | E14: 75337.66 | F14: 62245.57 | H14: Minority Interest | I14: 7051.52 | J14: 4413.01 | K14: 3930.45 | L14: 3760.41 | M14: 3523.71
A15: Employee Cost | B15: 6796.13 | C15: 6592.03 | D15: 6528.34 | E15: 6310.09 | F15: 5953.93 | H15: NON-CURRENT LIABILITIES
A16: Selling and Admin Expenses | B16: 0 | C16: 85.78 | D16: 47.52 | E16: 0 | F16: 10.39 | H16: Long Term Borrowings | I16: 201053.88 | J16: 190214.97 | K16: 187883.57 | L16: 181871.19 | M16: 181271.91
A17: Miscellaneous Expenses | B17: 25699.52 | C17: 15118.37 | D17: 11220.32 | E17: 10741.97 | F17: 9247.94 | H17: Deferred Tax Liabilities [Net] | I17: 18998.88 | J17: 15231.83 | K17: 12690 | L17: 10951.67 | M17: 9887.82
A18: Total Expenses | B18: 134010.49 | C18: 127408.17 | D18: 128478.02 | E18: 92389.72 | F18: 77557.32 | H18: Other Long Term Liabilities | I18: 6347.98 | J18: 5188.29 | K18: 5090.92 | L18: 4033.84 | M18: 4165.74
B19: Mar '25 | C19: Mar '24 | D19: Mar '23 | E19: Mar '22 | F19: Mar '21 | H19: Long Term Provisions | I19: 2138.71 | J19: 2084.03 | K19: 1917.89 | L19: 1655.19 | M19: 1042.39
H20: Total Non-Current Liabilities | I20: 228539.45 | J20: 212719.12 | K20: 207582.38 | L20: 198511.89 | M20: 196367.86
B21: 12 mths | C21: 12 mths | D21: 12 mths | E21: 12 mths | F21: 12 mths | H21: CURRENT LIABILITIES
H22: Short Term Borrowings | I22: 46521.24 | J22: 44825.33 | K22: 31921.61 | L22: 27684.07 | M22: 15964.62
A23: Operating Profit | B23: 54127.57 | C23: 51092.71 | D23: 47728.91 | E23: 40279.56 | F23: 33973.83 | H23: Trade Payables | I23: 11159.96 | J23: 11337.95 | K23: 13822.35 | L23: 11277.32 | M23: 8726.28
A24: PBDIT | B24: 60553.88 | C24: 54634.61 | D24: 49001.49 | E24: 43988.71 | F24: 38254.74 | H24: Other Current Liabilities | I24: 39104.52 | J24: 39131.56 | K24: 33524.23 | L24: 32033.61 | M24: 40531.67
A25: Interest | B25: 13168.07 | C25: 12048.21 | D25: 11156.06 | E25: 9315.98 | F25: 9224.14 | H25: Short Term Provisions | I25: 7716.74 | J25: 7060.33 | K25: 8217.26 | L25: 7875.69 | M25: 8113.6
A26: PBDT | B26: 47385.81 | C26: 42586.4 | D26: 37845.43 | E26: 34672.73 | F26: 29030.6 | H26: Total Current Liabilities | I26: 104502.46 | J26: 102355.17 | K26: 87485.45 | L26: 78870.69 | M26: 73336.17
A27: Depreciation | B27: 17401.19 | C27: 16203.63 | D27: 14792.27 | E27: 13787.83 | F27: 12450.31 | H27: Total Capital And Liabilities | I27: 524164.59 | J27: 480196.57 | K27: 446021.45 | L27: 416516.73 | M27: 398966.21
A28: Profit Before Tax | B28: 29984.62 | C28: 26382.77 | D28: 23053.16 | E28: 20884.9 | F28: 16580.29 | H28: ASSETS
A29: PBT (Post Extra-ord Items) | B29: 29984.62 | C29: 26382.77 | D29: 23053.16 | E29: 20884.9 | F29: 16580.29 | H29: NON-CURRENT ASSETS
A30: Tax | B30: 8245.18 | C30: 6809.2 | D30: 6796.12 | E30: 5047.1 | F30: 2420.53 | H30: Tangible Assets | I30: 271019.21 | J30: 258423.86 | K30: 239882.5 | L30: 224343.75 | M30: 202598.05
A31: Reported Net Profit | B31: 21739.44 | C31: 19176.29 | D31: 16132.78 | E31: 15655.77 | F31: 13950.76 | H31: Intangible Assets | I31: 500.75 | J31: 509.77 | K31: 541.92 | L31: 579.27 | M31: 647.13
A32: Minority Interest | B32: 530.69 | C32: 0 | D32: 0 | E32: 0 | F32: 0 | H32: Capital Work-In-Progress | I32: 100775.9 | J32: 87592.8 | K32: 89133.12 | L32: 91025.21 | M32: 97404.16
A33: Share Of P/L Of Associates | B33: -2213.71 | C33: -1635.6 | D33: -779.77 | E33: -1020.13 | F33: -683.87 | H33: Intangible Assets Under Development | I33: 0 | J33: 71.65 | K33: 45.88 | L33: 101.05 | M33: 101.87
A34: Net P/L After Minority Interest & Share Of Associates | B34: 19720.54 | C34: 20332.25 | D34: 17534.47 | E34: 15473.81 | F34: 14578.4 | H34: Fixed Assets | I34: 372295.86 | J34: 346598.08 | K34: 329603.42 | L34: 316049.28 | M34: 300751.21
A35: Total Value Addition | B35: 134010.49 | C35: 127125.79 | D35: 128226.06 | E35: 92389.72 | F35: 77457.83 | H35: Non-Current Investments | I35: 19653.58 | J35: 15834.56 | K35: 13884.79 | L35: 10626.24 | M35: 10089.26
A36: Equity Dividend | B36: 0 | C36: 7272.5 | D36: 4121.08 | E36: 3878.67 | F36: 5531.06 | H36: Deferred Tax Assets [Net] | I36: 944.33 | J36: 1169.9 | K36: 937.85 | L36: 995.7 | M36: 1075.89
A37: Per share data (annualised) | H37: Long Term Loans And Advances | I37: 823.07 | J37: 570.19 | K37: 553.77 | L37: 559.81 | M37: 554.97
A38: Shares in issue (lakhs) | B38: 96966.7 | C38: 96966.66 | D38: 96966.66 | E38: 96966.66 | F38: 96966.66 | H38: Other Non-Current Assets | I38: 18665.25 | J38: 18014.51 | K38: 19873.29 | L38: 16891.84 | M38: 18124.35
A39: Earning Per Share (Rs) | B39: 8r78 | C39: 19.78 | D39: 16.64 | E39: 16.15 | F39: 14.39 | H39: Total Non-Current Assets | I39: 412382.09 | J39: 382187.24 | K39: 364853.12 | L39: 345122.87 | M39: 330595.68
A40: Book Value (Rs) | B40: 189.83 | C40: 165.74 | D40: 151.62 | E40: 139.61 | F40: 129.67 | H40: CURRENT ASSETS
H41: Current Investments | I41: 50 | J41: 50 | K41: 50 | L41: 0 | M41: 499.99 | N41: 43891
H42: Inventories | I42: 18722.26 | J42: 18019.12 | K42: 14240.37 | L42: 10139.29 | M42: 9809.6 | N42: 10731.86
H43: Trade Receivables | I43: 34720.3 | J43: 33349.68 | K43: 28825.22 | L43: 27342.08 | M43: 17718.07 | N43: 15668.11
H44: Cash And Cash Equivalents | I44: 11457.1 | J44: 6847.34 | K44: 4948.53 | L44: 4458.08 | M44: 4387.8
H45: Short Term Loans And Advances | I45: 297.86 | J45: 271.12 | K45: 268.78 | L45: 270.37 | M45: 259.13
H46: OtherCurrentAssets | I46: 46534.98 | J46: 39472.07 | K46: 32835.43 | L46: 29184.04 | M46: 35695.94
H47: Total Current Assets | I47: 111782.5 | J47: 98009.33 | K47: 81168.33 | L47: 71393.86 | M47: 68370.53
H48: Total Assets | I48: 524164.59 | J48: 480196.57 | K48: 446021.45 | L48: 416516.73 | M48: 398966.21
H49: OTHER ADDITIONAL INFORMATION
H50: CONTINGENT LIABILITIES, COMMITMENTS
H51: Contingent Liabilities | I51: 0 | J51: 427806.67 | K51: 389024.57 | L51: 101896.02 | M51: 126940.73
H52: BONUS DETAILS
H53: Bonus Equity Share Capital | I53: 0 | J53: 1616.11 | K53: 1616.11 | L53: 1616.11 | M53: 1616.11
H54: NON-CURRENT INVESTMENTS
H55: Non-Current Investments Quoted Market Value | I55: 0 | J55: 0 | K55: 0 | L55: 98.7 | M55: 93.3
H56: Non-Current Investments Unquoted Book Value | I56: 0 | J56: 0 | K56: 0 | L56: 5.4 | M56: 3.78
H57: CURRENT INVESTMENTS
H58: Current Investments Unquoted Book Value | I58: 0 | J58: 0 | K58: 0 | L58: 0 | M58: 499.99

Sheet NTPC Ratio Analysis
A1: NTPC Ratio Analysis
A2: Ratio Type | B2: Ratio Formula | C2: 2025 | D2: 2024 | E2: 2023 | F2: 2022 | G2: 2021
A3: Liquidity Ratios
A4: Current Ratio | B4: = Current Assets/Current Liabilities | C4: =NTPC!I47/NTPC!I26 -> 1.0696638 | D4: =NTPC!J47/NTPC!J26 -> 0.95754157 | E4: =NTPC!K47/NTPC!K26 -> 0.92779234 | F4: =NTPC!L47/NTPC!L26 -> 0.90520141 | G4: =NTPC!M47/NTPC!M26 -> 0.93228935
A5: Quick Ratio | B5: = (Current Assets - Inventory - Prepaid Expenses)/Current Liabilities | C5: =(NTPC!I47-NTPC!I42)/NTPC!I26 -> 0.89050765 | D5: =(NTPC!J47-NTPC!J42)/NTPC!J26 -> 0.78149653 | E5: =(NTPC!K47-NTPC!K42)/NTPC!K26 -> 0.76501818 | F5: =(NTPC!L47-NTPC!L42)/NTPC!L26 -> 0.77664554 | G5: =(NTPC!M47-NTPC!M42)/NTPC!M26 -> 0.79852725
A6: Leverage Ratios
A7: Debt-Equity Ratio | B7: = Long Term Debt/Shareholders Equity | C7: =NTPC!I16/NTPC!I13 -> 1.0922617 | D7: =NTPC!J16/NTPC!J13 -> 1.1835968 | E7: =NTPC!K16/NTPC!K13 -> 1.2779181 | F7: =NTPC!L16/NTPC!L13 -> 1.3434747 | G7: =NTPC!M16/NTPC!M13 -> 1.4416583
A8: Debt to Total Assets Ratio | B8: = Total Debt/Total Assets | C8: =(NTPC!I16+NTPC!I22)/NTPC!I48 -> 0.47232324 | D8: =(NTPC!J16+NTPC!J22)/NTPC!J48 -> 0.48946684 | E8: =(NTPC!K16+NTPC!K22)/NTPC!K48 -> 0.49281303 | F8: =(NTPC!L16+NTPC!L22)/NTPC!L48 -> 0.50311367 | G8: =(NTPC!M16+NTPC!M22)/NTPC!M48 -> 0.49436901
A9: Proprietary Ratio | B9: = Shareholders Equity/Total Assets | C9: =NTPC!I13/NTPC!I48 -> 0.35117054 | D9: =NTPC!J13/NTPC!J48 -> 0.33467392 | E9: =NTPC!K13/NTPC!K48 -> 0.32963251 | F9: =NTPC!L13/NTPC!L48 -> 0.32501393 | G9: =NTPC!M13/NTPC!M48 -> 0.3151607
A10: Interest Coverage Ratio | B10: = EBIT/Interest | C10: =NTPC!B23/NTPC!B25 -> 4.1105166 | D10: =NTPC!C23/NTPC!C25 -> 4.2406889 | E10: =NTPC!D23/NTPC!D25 -> 4.2782945 | F10: =NTPC!E23/NTPC!E25 -> 4.3237061 | G10: =NTPC!F23/NTPC!F25 -> 3.6831434
A11: Profitability Ratios related to Sales
A12: Gross Profit Ratio | B12: = Gross Profit (Sales-COGS) / Sales | C12: =(NTPC!B9-107030)/NTPC!B9 -> 0.43110926 | D12: =(NTPC!C9-104030)/NTPC!C9 -> 0.41720175 | E12: =(NTPC!D9-106010)/NTPC!D9 -> 0.39837781 | F12: =(NTPC!E9-75360)/NTPC!E9 -> 0.43197099 | G12: =(NTPC!F9-74450)/NTPC!F9 -> 0.33247348 | H12: COGS computed from Finbox.
A13: Operating Profit Ratio | B13: = EBIT/Sales | C13: =NTPC!B23/NTPC!B9 -> 0.28770133 | D13: =NTPC!C23/NTPC!C9 -> 0.28623226 | E13: =NTPC!D23/NTPC!D9 -> 0.27086852 | F13: =NTPC!E23/NTPC!E9 -> 0.30360879 | G13: =NTPC!F23/NTPC!F9 -> 0.30461293
A14: Net Profit Ratio | B14: = EAT/Sales | C14: =NTPC!B31/NTPC!B9 -> 0.11555046 | D14: =NTPC!C31/NTPC!C9 -> 0.10742967 | E14: =NTPC!D31/NTPC!D9 -> 0.091555877 | F14: =NTPC!E31/NTPC!E9 -> 0.11800599 | G14: =NTPC!F31/NTPC!F9 -> 0.12508398
A15: Administrative Expenses Ratio | B15: = Admin Expenses/Sales | C15: =NTPC!B16/NTPC!B9 -> 0 | D15: =NTPC!C16/NTPC!C9 -> 0.00048055785 | E15: =NTPC!D16/NTPC!D9 -> 0.00026968292 | F15: =NTPC!E16/NTPC!E9 -> 0 | G15: =NTPC!F16/NTPC!F9 -> 9.3157831e-05
A16: Selling Expenses Ratio | B16: = Selling Expenses/Sales | C16: =NTPC!B16/NTPC!B9 -> 0 | D16: =NTPC!C16/NTPC!C9 -> 0.00048055785 | E16: =NTPC!D16/NTPC!D9 -> 0.00026968292 | F16: =NTPC!E16/NTPC!E9 -> 0 | G16: =NTPC!F16/NTPC!F9 -> 9.3157831e-05
A17: Operating Expenses Ratio | B17: = (Admin Expenses + Selling Expenses) / Sales | C17: =NTPC!B16/NTPC!B9 -> 0 | D17: =NTPC!C16/NTPC!C9 -> 0.00048055785 | E17: =NTPC!D16/NTPC!D9 -> 0.00026968292 | F17: =NTPC!E16/NTPC!E9 -> 0 | G17: =NTPC!F16/NTPC!F9 -> 9.3157831e-05
A18: Operating Ratio | B18: = (COGS+Operating Expenses) / Sales | C18: =(107030+NTPC!B16)/NTPC!B9 -> 0.56889074 | D18: =(104030+NTPC!C16)/NTPC!C9 -> 0.58327881 | E18: =(106010+NTPC!D16)/NTPC!D9 -> 0.60189188 | F18: =(75360+NTPC!E16)/NTPC!E9 -> 0.56802901 | G18: =(74450+NTPC!F16)/NTPC!F9 -> 0.66761967 | H18: COGS computed from Finbox.
A19: Profitability Ratios related to Investment
A20: Return on Assets | B20: = EAT/Total Assets | C20: =NTPC!B31/NTPC!I48 -> 0.041474454 | D20: =NTPC!C31/NTPC!J48 -> 0.03993425 | E20: =NTPC!D31/NTPC!K48 -> 0.036170413 | F20: =NTPC!E31/NTPC!L48 -> 0.037587374 | G20: =NTPC!F31/NTPC!M48 -> 0.034967272
A21: Return on Capital Employed | B21: = EBIT/Total Capital Employed | C21: =NTPC!B31/(NTPC!I48-NTPC!I26) -> 0.051802244 | D21: =NTPC!C31/(NTPC!J48-NTPC!J26) -> 0.05075222 | E21: =NTPC!D31/(NTPC!K48-NTPC!K26) -> 0.044996263 | F21: =NTPC!E31/(NTPC!L48-NTPC!L26) -> 0.046367403 | G21: =NTPC!F31/(NTPC!M48-NTPC!M26) -> 0.042842362
A22: Return on Equity | B22: = EAT/Shareholders Equity | C22: =NTPC!B31/NTPC!I13 -> 0.11810346 | D22: =NTPC!C31/NTPC!J13 -> 0.11932286 | E22: =NTPC!D31/NTPC!K13 -> 0.10972951 | F22: =NTPC!E31/NTPC!L13 -> 0.1156485 | G22: =NTPC!F31/NTPC!M13 -> 0.11095061
A23: Profitability Ratios related to Equity Shares
A24: Earnings Per Share | B24: = Net Profit Available to Equity Shareholders/Number of Equity Shares | C24: =NTPC!B31/NTPC!B38*100 -> 22.41949 | D24: =NTPC!C31/NTPC!C38*100 -> 19.776168 | E24: =NTPC!D31/NTPC!D38*100 -> 16.63745 | F24: =NTPC!E31/NTPC!E38*100 -> 16.145518 | G24: =NTPC!F31/NTPC!F38*100 -> 14.387172
A25: Earnings Yield | B25: = EPS/Market Price Per Share | C25: =C24/357.6 -> 0.062694324 | D25: =D24/355.8 -> 0.055582261 | E25: =E24/175.1 -> 0.09501685 | F25: =F24/135 -> 0.11959643 | G25: =G24/106.55 -> 0.13502742 | H25: MPS from NSE.
A26: Dividend Yield | B26: = DPS/MPS | C26: =(NTPC!B36/NTPC!B38*100)/357.6 -> 0 | D26: =(NTPC!C36/NTPC!C38*100)/355.8 -> 0.021079259 | E26: =(NTPC!D36/NTPC!D38*100)/175.1 -> 0.024271827 | F26: =(NTPC!E36/NTPC!E38*100)/135 -> 0.029629657 | G26: =(NTPC!F36/NTPC!F38*100)/106.55 -> 0.053534343 | H26: MPS from NSE.
A27: Dividend Payout Ratio | B27: = DPS/EPS | C27: =(NTPC!B36/NTPC!B38)/C24 -> 0 | D27: =(NTPC!C36/NTPC!C38)/D24 -> 0.0037924437 | E27: =(NTPC!D36/NTPC!D38)/E24 -> 0.002554476 | F27: =(NTPC!E36/NTPC!E38)/F24 -> 0.00247747 | G27: =(NTPC!F36/NTPC!F38)/G24 -> 0.0039647016
A28: Price to Earnings Ratio | B28: = MPS/EPS | C28: =357.6/C24 -> 15.950407 | D28: =355.8/D24 -> 17.991352 | E28: =175.1/E24 -> 10.524449 | F28: =135/F24 -> 8.3614534 | G28: =106.55/G24 -> 7.4059031 | H28: MPS from NSE.
A29: Profitability Ratios related to Earning Power
A30: Return on Investment (ROI) | B30: = EAT/Total Assets | C30: =NTPC!B31/NTPC!I48 -> 0.041474454 | D30: =NTPC!C31/NTPC!J48 -> 0.03993425 | E30: =NTPC!D31/NTPC!K48 -> 0.036170413 | F30: =NTPC!E31/NTPC!L48 -> 0.037587374 | G30: =NTPC!F31/NTPC!M48 -> 0.034967272
A31: Activity or Efficiency Ratios
A32: Current Assets Turnover | B32: = Sales/Current Assets | C32: =NTPC!B9/NTPC!I47 -> 1.6830726 | D32: =NTPC!C9/NTPC!J47 -> 1.8212642 | E32: =NTPC!D9/NTPC!K47 -> 2.1708828 | F32: =NTPC!E9/NTPC!L47 -> 1.858273 | G32: =NTPC!F9/NTPC!M47 -> 1.6312752
A33: Fixed Assets Turnover | B33: = Sales/Fixed Assets | C33: =NTPC!B9/NTPC!I34 -> 0.50534556 | D33: =NTPC!C9/NTPC!J34 -> 0.51500828 | E33: =NTPC!D9/NTPC!K34 -> 0.53460286 | F33: =NTPC!E9/NTPC!L34 -> 0.41977403 | G33: =NTPC!F9/NTPC!M34 -> 0.3708419
A34: Total Assets Turnover | B34: = Sales/Total Assets | C34: =NTPC!B9/NTPC!I48 -> 0.35892936 | D34: =NTPC!C9/NTPC!J48 -> 0.3717246 | E34: =NTPC!D9/NTPC!K48 -> 0.3950638 | F34: =NTPC!E9/NTPC!L48 -> 0.31852089 | G34: =NTPC!F9/NTPC!M48 -> 0.27955037
A35: Inventory Turnover | B35: = Sales / Average Inventory | C35: =NTPC!B9/(AVERAGE(NTPC!I42:J42)) -> 10.241208 | D35: =NTPC!C9/(AVERAGE(NTPC!J42:K42)) -> 11.066566 | E35: =NTPC!D9/(AVERAGE(NTPC!K42:L42)) -> 14.455241 | F35: =NTPC!E9/(AVERAGE(NTPC!L42:M42)) -> 13.300918 | G35: =NTPC!F9/(AVERAGE(NTPC!M42:N42)) -> 10.859126
A36: Debtors Turnover | B36: = Sales / Average Debtors | C36: =NTPC!B9/(AVERAGE(NTPC!I43:J43)) -> 5.5277836 | D36: =NTPC!C9/(AVERAGE(NTPC!J43:K43)) -> 5.7418952 | E36: =NTPC!D9/(AVERAGE(NTPC!K43:L43)) -> 6.27436 | F36: =NTPC!E9/(AVERAGE(NTPC!L43:M43)) -> 5.8885414 | G36: =NTPC!F9/(AVERAGE(NTPC!M43:N43)) -> 6.6812765
A37: Assessment of Risk
A38: DTL | B38: = Contribution/EBT | C38: =(NTPC!B9-NTPC!B13-NTPC!B14-NTPC!B15-NTPC!B16)/NTPC!B28 -> 2.6622679 | D38: =(NTPC!C9-NTPC!C13-NTPC!C14-NTPC!C15-NTPC!C16)/NTPC!C28 -> 2.5096334 | E38: =(NTPC!D9-NTPC!D13-NTPC!D14-NTPC!D15-NTPC!D16)/NTPC!D28 -> 2.5570998 | F38: =(NTPC!E9-NTPC!E13-NTPC!E14-NTPC!E15-NTPC!E16)/NTPC!E28 -> 2.4429866 | G38: =(NTPC!F9-NTPC!F13-NTPC!F14-NTPC!F15-NTPC!F16)/NTPC!F28 -> 2.6068163
A39: DOL | B39: = Contribution/EBIT | C39: =(NTPC!B9-NTPC!B13-NTPC!B14-NTPC!B15-NTPC!B16)/NTPC!B23 -> 1.4747954 | D39: =(NTPC!C9-NTPC!C13-NTPC!C14-NTPC!C15-NTPC!C16)/NTPC!C23 -> 1.2959007 | E39: =(NTPC!D9-NTPC!D13-NTPC!D14-NTPC!D15-NTPC!D16)/NTPC!D23 -> 1.2350844 | F39: =(NTPC!E9-NTPC!E13-NTPC!E14-NTPC!E15-NTPC!E16)/NTPC!E23 -> 1.2666854 | G39: =(NTPC!F9-NTPC!F13-NTPC!F14-NTPC!F15-NTPC!F16)/NTPC!F23 -> 1.2722078
A40: DFL | B40: = EBIT/EBT | C40: =NTPC!B23/NTPC!B28 -> 1.8051778 | D40: =NTPC!C23/NTPC!C28 -> 1.9365938 | E40: =NTPC!D23/NTPC!D28 -> 2.0703847 | F40: =NTPC!E23/NTPC!E28 -> 1.9286451 | G40: =NTPC!F23/NTPC!F28 -> 2.0490492

Sheet Dabur India
A1: Dabur India | H1: Dabur India
A2: Consolidated Profit & Loss account | B2: ------------------- in Rs. Cr. ------------------- | H2: Consolidated Balance Sheet | I2: ------------------- in Rs. Cr. -------------------
B3: Mar '25 | C3: Mar '24 | D3: Mar '23 | E3: Mar '22 | F3: Mar '21 | I3: Mar 25 | J3: 45352 | K3: 44986 | L3: 44621 | M3: 44256
B5: 12 mths | C5: 12 mths | D5: 12 mths | E5: 12 mths | F5: 12 mths | I5: 12 mths | J5: 12 mths | K5: 12 mths | L5: 12 mths | M5: 12 mths
A7: Income | H7: EQUITIES AND LIABILITIES
A8: Sales Turnover | B8: 12563.09 | C8: 12404.01 | D8: 11529.89 | E8: 10888.68 | F8: 9561.65 | H8: SHAREHOLDER'S FUNDS
A9: Excise Duty | B9: 0 | C9: 0 | D9: 0 | E9: 0 | F9: 15.05 | H9: Equity Share Capital | I9: 177.23 | J9: 177.2 | K9: 177.18 | L9: 176.79 | M9: 176.74
A10: Net Sales | B10: 12563.09 | C10: 12404.01 | D10: 11529.89 | E10: 10888.68 | F10: 9546.6 | H10: Total Share Capital | I10: 177.23 | J10: 177.2 | K10: 177.18 | L10: 176.79 | M10: 176.74
A11: Other Income | B11: 553.2 | C11: 480.53 | D11: 443.83 | E11: 315.88 | F11: 329.49 | H11: Reserves and Surplus | I11: 10623.46 | J11: 9689.1 | K11: 8737 | L11: 8056.3 | M11: 7486.79
A12: Stock Adjustments | B12: 57.1 | C12: -48.95 | D12: 90.79 | E12: 8.55 | F12: 207.2 | H12: Total Reserves and Surplus | I12: 10623.46 | J12: 9689.1 | K12: 8737 | L12: 8056.3 | M12: 7486.79
A13: Total Income | B13: 13173.39 | C13: 12835.59 | D13: 12064.51 | E13: 11213.11 | F13: 10083.29 | H13: Employees Stock Options | I13: 0 | J13: 0 | K13: 59.08 | L13: 148.21 | M13: 0
A14: Expenditure | H14: Total Shareholders Funds | I14: 10800.69 | J14: 9866.3 | K14: 8973.26 | L14: 8381.3 | M14: 7663.53
A15: Raw Materials | B15: 6640.59 | C15: 6447.46 | D15: 6406.88 | E15: 5685.19 | F15: 5014 | H15: Minority Interest | I15: 409.57 | J15: 436.78 | K15: 468.17 | L15: 40.55 | M15: 36.69
A16: Power & Fuel Cost | B16: 155.95 | C16: 153.44 | D16: 150.59 | E16: 128.66 | F16: 104.01 | H16: NON-CURRENT LIABILITIES
A17: Employee Cost | B17: 1291.23 | C17: 1239.56 | D17: 1137 | E17: 1079.95 | F17: 1033.46 | H17: Long Term Borrowings | I17: 304.03 | J17: 535.97 | K17: 298.84 | L17: 250.36 | M17: 134.13
A18: Selling and Admin Expenses | B18: 864.64 | C18: 849.06 | D18: 640.27 | E18: 777.94 | F18: 784.36 | H18: Deferred Tax Liabilities [Net] | I18: 144.27 | J18: 109.03 | K18: 90.99 | L18: 82.27 | M18: 13.91
A19: Miscellaneous Expenses | B19: 1351.44 | C19: 1265.31 | D19: 1121.82 | E19: 971.68 | F19: 815.29 | H19: Other Long Term Liabilities | I19: 183.83 | J19: 175.86 | K19: 149.31 | L19: 143.83 | M19: 1.37
A20: Total Expenses | B20: 10303.85 | C20: 9954.83 | D20: 9456.56 | E20: 8643.42 | F20: 7751.12 | H20: Long Term Provisions | I20: 71.45 | J20: 68.31 | K20: 64.37 | L20: 63.68 | M20: 63.31
B21: Mar '25 | C21: Mar '24 | D21: Mar '23 | E21: Mar '22 | F21: Mar '21 | H21: Total Non-Current Liabilities | I21: 703.58 | J21: 889.17 | K21: 603.51 | L21: 540.14 | M21: 212.72
H22: CURRENT LIABILITIES
B23: 12 mths | C23: 12 mths | D23: 12 mths | E23: 12 mths | F23: 12 mths | H23: Short Term Borrowings | I23: 426.09 | J23: 622.1 | K23: 700.18 | L23: 617.29 | M23: 349.14
H24: Trade Payables | I24: 2825.34 | J24: 2421.71 | K24: 2186.61 | L24: 2017.95 | M24: 1915.26
A25: Operating Profit | B25: 2316.34 | C25: 2400.23 | D25: 2164.12 | E25: 2253.81 | F25: 2002.68 | H25: Other Current Liabilities | I25: 806.48 | J25: 636.73 | K25: 508.63 | L25: 501.3 | M25: 481.95
A26: PBDIT | B26: 2869.54 | C26: 2880.76 | D26: 2607.95 | E26: 2569.69 | F26: 2332.17 | H26: Short Term Provisions | I26: 260.53 | J26: 249.89 | K26: 214.01 | L26: 186 | M26: 187.84
A27: Interest | B27: 163.5 | C27: 124.18 | D27: 78.24 | E27: 38.6 | F27: 30.81 | H27: Total Current Liabilities | I27: 4318.44 | J27: 3930.43 | K27: 3609.43 | L27: 3322.54 | M27: 2934.19
A28: PBDT | B28: 2706.04 | C28: 2756.58 | D28: 2529.71 | E28: 2531.09 | F28: 2301.36 | H28: Total Capital And Liabilities | I28: 16232.28 | J28: 15122.68 | K28: 13654.37 | L28: 12284.53 | M28: 10847.13
A29: Depreciation | B29: 445.6 | C29: 399.21 | D29: 310.96 | E29: 252.89 | F29: 240.13 | H29: ASSETS
A30: Profit Before Tax | B30: 2260.44 | C30: 2357.37 | D30: 2218.75 | E30: 2278.2 | F30: 2061.23 | H30: NON-CURRENT ASSETS
A31: PBT (Post Extra-ord Items) | B31: 2260.44 | C31: 2357.37 | D31: 2218.75 | E31: 2278.2 | F31: 2061.23 | H31: Tangible Assets | I31: 2843.38 | J31: 2606.39 | K31: 2284.67 | L31: 2017.02 | M31: 1862.2
A32: Tax | B32: 517.47 | C32: 547.43 | D32: 517.35 | E32: 526.38 | F32: 361.07 | H32: Intangible Assets | I32: 741.22 | J32: 803.49 | K32: 888.73 | L32: 39.73 | M32: 44.71
A33: Reported Net Profit | B33: 1767.08 | C33: 1843.19 | D33: 1708.78 | E33: 1741.02 | F33: 1694.31 | H33: Capital Work-In-Progress | I33: 166.41 | J33: 209.09 | K33: 175.13 | L33: 167.5 | M33: 147.3
A34: Share Of P/L Of Associates | B34: -0.55 | C34: 0.51 | D34: 1.63 | E34: 1.8 | F34: 1.01 | H34: Intangible Assets Under Development | I34: 2.58 | J34: 23.14 | K34: 0 | L34: 0 | M34: 0
A35: Net P/L After Minority Interest & Share Of Associates | B35: 1740.42 | C35: 1811.31 | D35: 1701.33 | E35: 1827.3 | F35: 1694.95 | H35: Fixed Assets | I35: 3753.59 | J35: 3642.11 | K35: 3348.53 | L35: 2224.25 | M35: 2054.21
A36: Total Value Addition | B36: 3663.26 | C36: 3507.37 | D36: 3049.68 | E36: 2958.23 | F36: 2737.12 | H36: Non-Current Investments | I36: 5380.31 | J36: 5266.09 | K36: 5528.79 | L36: 5365.06 | M36: 3413.62
A37: Equity Dividend | B37: 974.78 | C37: 965.76 | D37: 921.31 | E37: 972.32 | F37: 592.09 | H37: Deferred Tax Assets [Net] | I37: 2.53 | J37: 6.32 | K37: 2.09 | L37: 0.67 | M37: 17.95
A38: Per share data (annualised) | H38: Long Term Loans And Advances | I38: 0 | J38: 0 | K38: 0 | L38: 0 | M38: 22.48
A39: Shares in issue (lakhs) | B39: 17723.18 | C39: 17720.39 | D39: 17717.63 | E39: 17678.56 | F39: 17674.25 | H39: Other Non-Current Assets | I39: 158.3 | J39: 123.42 | K39: 120.75 | L39: 126.56 | M39: 226.92
A40: Earning Per Share (Rs) | B40: 9.97 | C40: 10.4 | D40: 9.64 | E40: 9.85 | F40: 9.59 | H40: Total Non-Current Assets | I40: 9699.82 | J40: 9443.06 | K40: 9405.41 | L40: 7967.69 | M40: 6071.19
A41: Book Value (Rs) | B41: 60.94 | C41: 55.68 | D41: 50.31 | E41: 46.57 | F41: 43.36 | H41: CURRENT ASSETS
H42: Current Investments | I42: 2087.55 | J42: 1666.6 | K42: 736.47 | L42: 854.56 | M42: 746.01 | N42: 43891
H43: Inventories | I43: 2300.11 | J43: 1946.97 | K43: 2024.2 | L43: 1911.37 | M43: 1734.28 | N43: 1379.57
H44: Trade Receivables | I44: 888.5 | J44: 898.72 | K44: 848.75 | L44: 646.15 | M44: 561.58 | N44: 813.89
H45: Cash And Cash Equivalents | I45: 578.01 | J45: 666.36 | K45: 325.92 | L45: 570.14 | M45: 1329.03
H46: Short Term Loans And Advances | I46: 0 | J46: 0 | K46: 0 | L46: 0 | M46: 14.46
H47: OtherCurrentAssets | I47: 678.29 | J47: 500.97 | K47: 313.62 | L47: 334.62 | M47: 390.58
H48: Total Current Assets | I48: 6532.46 | J48: 5679.62 | K48: 4248.96 | L48: 4316.84 | M48: 4775.94
H49: Total Assets | I49: 16232.28 | J49: 15122.68 | K49: 13654.37 | L49: 12284.53 | M49: 10847.13
H50: OTHER ADDITIONAL INFORMATION
H51: CONTINGENT LIABILITIES, COMMITMENTS
H52: Contingent Liabilities | I52: 754.11 | J52: 593.44 | K52: 521.73 | L52: 555.06 | M52: 347.77
H53: BONUS DETAILS
H54: Bonus Equity Share Capital | I54: 163.23 | J54: 163.23 | K54: 163.23 | L54: 163.23 | M54: 163.23
H55: NON-CURRENT INVESTMENTS
H56: Non-Current Investments Quoted Market Value | I56: 4167.16 | J56: 4337.94 | K56: 4652.16 | L56: 4229.01 | M56: 3024.07
H57: Non-Current Investments Unquoted Book Value | I57: 1212.48 | J57: 927.81 | K57: 888.85 | L57: 1142.16 | M57: 387.9
H58: CURRENT INVESTMENTS
H59: Current Investments Quoted Market Value | I59: 1628.36 | J59: 1286.35 | K59: 275.15 | L59: 678.49 | M59: 451.14
H60: Current Investments Unquoted Book Value | I60: 459.18 | J60: 380.25 | K60: 462.83 | L60: 166.67 | M60: 320.19

Sheet Dabur India Ratio Analysis
A1: Dabur India Ratio Analysis
A2: Ratio Type | B2: Ratio Formula | C2: 2025 | D2: 2024 | E2: 2023 | F2: 2022 | G2: 2021
A3: Liquidity Ratios
A4: Current Ratio | B4: = Current Assets/Current Liabilities | C4: ='Dabur India'!I48/'Dabur India'!I27 -> 1.5126898 | D4: ='Dabur India'!J48/'Dabur India'!J27 -> 1.4450378 | E4: ='Dabur India'!K48/'Dabur India'!K27 -> 1.1771831 | F4: ='Dabur India'!L48/'Dabur India'!L27 -> 1.299259 | G4: ='Dabur India'!M48/'Dabur India'!M27 -> 1.627686
A5: Quick Ratio | B5: = (Current Assets - Inventory - Prepaid Expenses)/Current Liabilities | C5: =('Dabur India'!I48-'Dabur India'!I43)/'Dabur India'!I27 -> 0.98006456 | D5: =('Dabur India'!J48-'Dabur India'!J43)/'Dabur India'!J27 -> 0.94967981 | E5: =('Dabur India'!K48-'Dabur India'!K43)/'Dabur India'!K27 -> 0.61637433 | F5: =('Dabur India'!L48-'Dabur India'!L43)/'Dabur India'!L27 -> 0.72398526 | G5: =('Dabur India'!M48-'Dabur India'!M43)/'Dabur India'!M27 -> 1.0366268
A6: Leverage Ratios
A7: Debt-Equity Ratio | B7: = Long Term Debt/Shareholders Equity | C7: ='Dabur India'!I17/'Dabur India'!I14 -> 0.028149128 | D7: ='Dabur India'!J17/'Dabur India'!J14 -> 0.054323303 | E7: ='Dabur India'!K17/'Dabur India'!K14 -> 0.033303393 | F7: ='Dabur India'!L17/'Dabur India'!L14 -> 0.029871261 | G7: ='Dabur India'!M17/'Dabur India'!M14 -> 0.017502378
A8: Debt to Total Assets Ratio | B8: = Total Debt/Total Assets | C8: =('Dabur India'!I17+'Dabur India'!I23)/'Dabur India'!I49 -> 0.04497951 | D8: =('Dabur India'!J17+'Dabur India'!J23)/'Dabur India'!J49 -> 0.076578358 | E8: =('Dabur India'!K17+'Dabur India'!K23)/'Dabur India'!K49 -> 0.073164855 | F8: =('Dabur India'!L17+'Dabur India'!L23)/'Dabur India'!L49 -> 0.070629483 | G8: =('Dabur India'!M17+'Dabur India'!M23)/'Dabur India'!M49 -> 0.044552799
A9: Proprietary Ratio | B9: = Shareholders Equity/Total Assets | C9: ='Dabur India'!I14/'Dabur India'!I49 -> 0.66538342 | D9: ='Dabur India'!J14/'Dabur India'!J49 -> 0.65241743 | E9: ='Dabur India'!K14/'Dabur India'!K49 -> 0.65717129 | F9: ='Dabur India'!L14/'Dabur India'!L49 -> 0.6822646 | G9: ='Dabur India'!M14/'Dabur India'!M49 -> 0.70650301
A10: Interest Coverage Ratio | B10: = EBIT/Interest | C10: ='Dabur India'!B25/'Dabur India'!B27 -> 14.167217 | D10: ='Dabur India'!C25/'Dabur India'!C27 -> 19.328636 | E10: ='Dabur India'!D25/'Dabur India'!D27 -> 27.66002 | F10: ='Dabur India'!E25/'Dabur India'!E27 -> 58.38886 | G10: ='Dabur India'!F25/'Dabur India'!F27 -> 65.000974
A11: Profitability Ratios related to Sales
A12: Gross Profit Ratio | B12: = Gross Profit (Sales-COGS) / Sales | C12: =('Dabur India'!B10-('Dabur India'!J43-'Dabur India'!I43+'Dabur India'!B15))/'Dabur India'!B10 -> 0.49952997 | D12: =('Dabur India'!C10-('Dabur India'!K43-'Dabur India'!J43+'Dabur India'!C15))/'Dabur India'!C10 -> 0.47398543 | E12: =('Dabur India'!D10-('Dabur India'!L43-'Dabur India'!K43+'Dabur India'!D15))/'Dabur India'!D10 -> 0.45411014 | F12: =('Dabur India'!E10-('Dabur India'!M43-'Dabur India'!L43+'Dabur India'!E15))/'Dabur India'!E10 -> 0.49414438 | G12: =('Dabur India'!F10-('Dabur India'!N43-'Dabur India'!M43+'Dabur India'!F15))/'Dabur India'!F10 -> 0.51194247
A13: Operating Profit Ratio | B13: = EBIT/Sales | C13: ='Dabur India'!B25/'Dabur India'!B10 -> 0.18437661 | D13: ='Dabur India'!C25/'Dabur India'!C10 -> 0.19350436 | E13: ='Dabur India'!D25/'Dabur India'!D10 -> 0.1876965 | F13: ='Dabur India'!E25/'Dabur India'!E10 -> 0.20698652 | G13: ='Dabur India'!F25/'Dabur India'!F10 -> 0.2097794
A14: Net Profit Ratio | B14: = EAT/Sales | C14: ='Dabur India'!B33/'Dabur India'!B10 -> 0.14065648 | D14: ='Dabur India'!C33/'Dabur India'!C10 -> 0.1485963 | E14: ='Dabur India'!D33/'Dabur India'!D10 -> 0.14820436 | F14: ='Dabur India'!E33/'Dabur India'!E10 -> 0.15989266 | G14: ='Dabur India'!F33/'Dabur India'!F10 -> 0.17747785
A15: Administrative Expenses Ratio | B15: = Admin Expenses/Sales | C15: ='Dabur India'!B18/'Dabur India'!B10 -> 0.068823832 | D15: ='Dabur India'!C18/'Dabur India'!C10 -> 0.068450445 | E15: ='Dabur India'!D18/'Dabur India'!D10 -> 0.055531319 | F15: ='Dabur India'!E18/'Dabur India'!E10 -> 0.07144484 | G15: ='Dabur India'!F18/'Dabur India'!F10 -> 0.082161188
A16: Selling Expenses Ratio | B16: = Selling Expenses/Sales | C16: ='Dabur India'!B18/'Dabur India'!B10 -> 0.068823832 | D16: ='Dabur India'!C18/'Dabur India'!C10 -> 0.068450445 | E16: ='Dabur India'!D18/'Dabur India'!D10 -> 0.055531319 | F16: ='Dabur India'!E18/'Dabur India'!E10 -> 0.07144484 | G16: ='Dabur India'!F18/'Dabur India'!F10 -> 0.082161188
A17: Operating Expenses Ratio | B17: = (Admin Expenses + Selling Expenses) / Sales | C17: ='Dabur India'!B18/'Dabur India'!B10 -> 0.068823832 | D17: ='Dabur India'!C18/'Dabur India'!C10 -> 0.068450445 | E17: ='Dabur India'!D18/'Dabur India'!D10 -> 0.055531319 | F17: ='Dabur India'!E18/'Dabur India'!E10 -> 0.07144484 | G17: ='Dabur India'!F18/'Dabur India'!F10 -> 0.082161188
A18: Operating Ratio | B18: = (COGS+Operating Expenses) / Sales | C18: =('Dabur India'!J43-'Dabur India'!I43+'Dabur India'!B15+'Dabur India'!B18)/'Dabur India'!B10 -> 0.56929386 | D18: =('Dabur India'!K43-'Dabur India'!J43+'Dabur India'!C15+'Dabur India'!C18)/'Dabur India'!C10 -> 0.59446502 | E18: =('Dabur India'!L43-'Dabur India'!K43+'Dabur India'!D15+'Dabur India'!D18)/'Dabur India'!D10 -> 0.60142118 | F18: =('Dabur India'!M43-'Dabur India'!L43+'Dabur India'!E15+'Dabur India'!E18)/'Dabur India'!E10 -> 0.57730046 | G18: =('Dabur India'!N43-'Dabur India'!M43+'Dabur India'!F15+'Dabur India'!F18)/'Dabur India'!F10 -> 0.57021872
A19: Profitability Ratios related to Investment
A20: Return on Assets | B20: = EAT/Total Assets | C20: ='Dabur India'!B33/'Dabur India'!I49 -> 0.10886209 | D20: ='Dabur India'!C33/'Dabur India'!J49 -> 0.1218825 | E20: ='Dabur India'!D33/'Dabur India'!K49 -> 0.12514528 | F20: ='Dabur India'!E33/'Dabur India'!L49 -> 0.14172459 | G20: ='Dabur India'!F33/'Dabur India'!M49 -> 0.15619892
A21: Return on Capital Employed | B21: = EBIT/Total Capital Employed | C21: ='Dabur India'!B25/('Dabur India'!I49-'Dabur India'!I27) -> 0.1944243 | D21: ='Dabur India'!C25/('Dabur India'!J49-'Dabur India'!J27) -> 0.21445464 | E21: ='Dabur India'!D25/('Dabur India'!K49-'Dabur India'!K27) -> 0.2154438 | F21: ='Dabur India'!E25/('Dabur India'!L49-'Dabur India'!L27) -> 0.25148544 | G21: ='Dabur India'!F25/('Dabur India'!M49-'Dabur India'!M27) -> 0.25308924
A22: Return on Equity | B22: = EAT/Shareholders Equity | C22: ='Dabur India'!B33/'Dabur India'!I14 -> 0.16360807 | D22: ='Dabur India'!C33/'Dabur India'!J14 -> 0.18681674 | E22: ='Dabur India'!D33/'Dabur India'!K14 -> 0.19043023 | F22: ='Dabur India'!E33/'Dabur India'!L14 -> 0.20772672 | G22: ='Dabur India'!F33/'Dabur India'!M14 -> 0.22108741
A23: Profitability Ratios related to Equity Shares
A24: Earnings Per Share | B24: = Net Profit Available to Equity Shareholders/Number of Equity Shares | C24: ='Dabur India'!B33/'Dabur India'!B39*100 -> 9.9704455 | D24: ='Dabur India'!C33/'Dabur India'!C39*100 -> 10.401521 | E24: ='Dabur India'!D33/'Dabur India'!D39*100 -> 9.6445179 | F24: ='Dabur India'!E33/'Dabur India'!E39*100 -> 9.8482003 | G24: ='Dabur India'!F33/'Dabur India'!F39*100 -> 9.5863191
A25: Earnings Yield | B25: = EPS/Market Price Per Share | C25: =C24/506.5 -> 0.019684986 | D25: =D24/523.15 -> 0.019882482 | E25: =E24/544.9 -> 0.017699611 | F25: =F24/536.2 -> 0.018366655 | G25: =G24/540.5 -> 0.01773602 | H25: MPS from NSE.
A26: Dividend Yield | B26: = DPS/MPS | C26: =('Dabur India'!B37/'Dabur India'!B39*100)/506.5 -> 0.010858892 | D26: =('Dabur India'!C37/'Dabur India'!C39*100)/523.15 -> 0.010417649 | E26: =('Dabur India'!D37/'Dabur India'!D39*100)/544.9 -> 0.0095429654 | F26: =('Dabur India'!E37/'Dabur India'!E39*100)/536.2 -> 0.010257358 | G26: =('Dabur India'!F37/'Dabur India'!F39*100)/540.5 -> 0.0061979923 | H26: MPS from NSE.
A27: Dividend Payout Ratio | B27: = DPS/EPS | C27: =('Dabur India'!B37/'Dabur India'!B39*100)/C24 -> 0.5516332 | D27: =('Dabur India'!C37/'Dabur India'!C39*100)/D24 -> 0.52396118 | E27: =('Dabur India'!D37/'Dabur India'!D39*100)/E24 -> 0.53916244 | F27: =('Dabur India'!E37/'Dabur India'!E39*100)/F24 -> 0.55847721 | G27: =('Dabur India'!F37/'Dabur India'!F39*100)/G24 -> 0.34945789
A28: Price to Earnings Ratio | B28: = MPS/EPS | C28: =506.5/C24 -> 50.800137 | D28: =523.15/D24 -> 50.295531 | E28: =544.9/E24 -> 56.498418 | F28: =536.2/F24 -> 54.446496 | G28: =540.5/G24 -> 56.382434 | H28: MPS from NSE.
A29: Profitability Ratios related to Earning Power
A30: Return on Investment (ROI) | B30: = EAT/Total Assets | C30: ='Dabur India'!B33/'Dabur India'!I49 -> 0.10886209 | D30: ='Dabur India'!C33/'Dabur India'!J49 -> 0.1218825 | E30: ='Dabur India'!D33/'Dabur India'!K49 -> 0.12514528 | F30: ='Dabur India'!E33/'Dabur India'!L49 -> 0.14172459 | G30: ='Dabur India'!F33/'Dabur India'!M49 -> 0.15619892
A31: Activity or Efficiency Ratios
A32: Current Assets Turnover | B32: = Sales/Current Assets | C32: ='Dabur India'!B10/'Dabur India'!I48 -> 1.923179 | D32: ='Dabur India'!C10/'Dabur India'!J48 -> 2.1839507 | E32: ='Dabur India'!D10/'Dabur India'!K48 -> 2.7135793 | F32: ='Dabur India'!E10/'Dabur India'!L48 -> 2.5223728 | G32: ='Dabur India'!F10/'Dabur India'!M48 -> 1.9988945
A33: Fixed Assets Turnover | B33: = Sales/Fixed Assets | C33: ='Dabur India'!B10/'Dabur India'!I35 -> 3.3469532 | D33: ='Dabur India'!C10/'Dabur India'!J35 -> 3.4057209 | E33: ='Dabur India'!D10/'Dabur India'!K35 -> 3.4432691 | F33: ='Dabur India'!E10/'Dabur India'!L35 -> 4.8954389 | G33: ='Dabur India'!F10/'Dabur India'!M35 -> 4.647334
A34: Total Assets Turnover | B34: = Sales/Total Assets | C34: ='Dabur India'!B10/'Dabur India'!I49 -> 0.7739572 | D34: ='Dabur India'!C10/'Dabur India'!J49 -> 0.82022565 | E34: ='Dabur India'!D10/'Dabur India'!K49 -> 0.84441025 | F34: ='Dabur India'!E10/'Dabur India'!L49 -> 0.88637335 | G34: ='Dabur India'!F10/'Dabur India'!M49 -> 0.88010377
A35: Inventory Turnover | B35: = Sales / Average Inventory | C35: ='Dabur India'!B10/(AVERAGE('Dabur India'!I43:J43)) -> 5.9161071 | D35: ='Dabur India'!C10/(AVERAGE('Dabur India'!J43:K43)) -> 6.2470305 | E35: ='Dabur India'!D10/(AVERAGE('Dabur India'!K43:L43)) -> 5.8593241 | F35: ='Dabur India'!E10/(AVERAGE('Dabur India'!L43:M43)) -> 5.9735191 | G35: ='Dabur India'!F10/(AVERAGE('Dabur India'!M43:N43)) -> 6.1317019 | H35: No inventory.
A36: Debtors Turnover | B36: = Sales / Average Debtors | C36: ='Dabur India'!B10/(AVERAGE('Dabur India'!I44:J44)) -> 14.058806 | D36: ='Dabur India'!C10/(AVERAGE('Dabur India'!J44:K44)) -> 14.196536 | E36: ='Dabur India'!D10/(AVERAGE('Dabur India'!K44:L44)) -> 15.425634 | F36: ='Dabur India'!E10/(AVERAGE('Dabur India'!L44:M44)) -> 18.031646 | G36: ='Dabur India'!F10/(AVERAGE('Dabur India'!M44:N44)) -> 13.881219 | H36: No debtors.
A37: Assessment of Risk
A38: DTL | B38: = Contribution/EBT | C38: =('Dabur India'!B10-'Dabur India'!B15-'Dabur India'!B16-'Dabur India'!B17-'Dabur India'!B18)/'Dabur India'!B30 -> 1.597335 | D38: =('Dabur India'!C10-'Dabur India'!C15-'Dabur India'!C16-'Dabur India'!C17-'Dabur India'!C18)/'Dabur India'!C30 -> 1.5756924 | E38: =('Dabur India'!D10-'Dabur India'!D15-'Dabur India'!D16-'Dabur India'!D17-'Dabur India'!D18)/'Dabur India'!D30 -> 1.4400676 | F38: =('Dabur India'!E10-'Dabur India'!E15-'Dabur India'!E16-'Dabur India'!E17-'Dabur India'!E18)/'Dabur India'!E30 -> 1.4120534 | G38: =('Dabur India'!F10-'Dabur India'!F15-'Dabur India'!F16-'Dabur India'!F17-'Dabur India'!F18)/'Dabur India'!F30 -> 1.2666078
A39: DOL | B39: = Contribution/EBIT | C39: =('Dabur India'!B10-'Dabur India'!B15-'Dabur India'!B16-'Dabur India'!B17-'Dabur India'!B18)/'Dabur India'!B25 -> 1.5587867 | D39: =('Dabur India'!C10-'Dabur India'!C15-'Dabur India'!C16-'Dabur India'!C17-'Dabur India'!C18)/'Dabur India'!C25 -> 1.5475559 | E39: =('Dabur India'!D10-'Dabur India'!D15-'Dabur India'!D16-'Dabur India'!D17-'Dabur India'!D18)/'Dabur India'!D25 -> 1.47642 | F39: =('Dabur India'!E10-'Dabur India'!E15-'Dabur India'!E16-'Dabur India'!E17-'Dabur India'!E18)/'Dabur India'!E25 -> 1.4273342 | G39: =('Dabur India'!F10-'Dabur India'!F15-'Dabur India'!F16-'Dabur India'!F17-'Dabur India'!F18)/'Dabur India'!F25 -> 1.3036381
A40: DFL | B40: = EBIT/EBT | C40: ='Dabur India'!B25/'Dabur India'!B30 -> 1.0247297 | D40: ='Dabur India'!C25/'Dabur India'!C30 -> 1.0181813 | E40: ='Dabur India'!D25/'Dabur India'!D30 -> 0.97537803 | F40: ='Dabur India'!E25/'Dabur India'!E30 -> 0.98929418 | G40: ='Dabur India'!F25/'Dabur India'!F30 -> 0.97159463

Sheet HDFC Life Insurance
A1: HDFC Life Insurance Company | H1: HDFC Life Insurance Company
A2: Consolidated Profit & Loss account | B2: ------------------- in Rs. Cr. ------------------- | H2: Consolidated Balance Sheet | I2: ------------------- in Rs. Cr. -------------------
B3: Mar '25 | C3: Mar '24 | D3: Mar '23 | E3: Mar '22 | F3: Mar '21 | I3: Mar 25 | J3: 45352 | K3: 44986 | L3: 44621 | M3: 44256
B5: 12 mths | C5: 12 mths | D5: 12 mths | E5: 12 mths | F5: 12 mths | I5: 12 mths | J5: 12 mths | K5: 12 mths | L5: 12 mths | M5: 12 mths
A7: Income | H7: EQUITIES AND LIABILITIES
A8: Sales Turnover | B8: 96921.74 | C8: 101481.79 | D8: 70207.08 | E8: 67125.84 | F8: 71482.65 | H8: SHAREHOLDER'S FUNDS
A9: Net Sales | B9: 96921.74 | C9: 101481.79 | D9: 70207.08 | E9: 67125.84 | F9: 71482.65 | H9: Equity Share Capital | I9: 2152.99 | J9: 2150.94 | K9: 2149.4 | L9: 2112.62 | M9: 2020.94
A10: Other Income | B10: 417.19 | C10: 548.77 | D10: 1547.37 | E10: 828.11 | F10: 337.5 | H10: Total Share Capital | I10: 2152.99 | J10: 2150.94 | K10: 2149.4 | L10: 2112.62 | M10: 2020.94
A11: Total Income | B11: 97338.93 | C11: 102030.56 | D11: 71754.45 | E11: 67953.95 | F11: 71820.15 | H11: Reserves and Surplus | I11: 14000.99 | J11: 12515.41 | K11: 10840.59 | L11: 13497.39 | M11: 9171.88
A12: Expenditure | H12: Total Reserves and Surplus | I12: 14000.99 | J12: 12515.41 | K12: 10840.59 | L12: 13497.39 | M12: 9171.88
A13: Employee Cost | B13: 3213.39 | C13: 3267.07 | D13: 3067.88 | E13: 2132.85 | F13: 1678.83 | H13: Total Shareholders Funds | I13: 16153.98 | J13: 14666.35 | K13: 12989.99 | L13: 15610.01 | M13: 11192.83
A14: Selling and Admin Expenses | B14: 1043.49 | C14: 1770.07 | D14: 2469.32 | E14: 1890.75 | F14: 1410.25 | H14: Equity Share Application Money | I14: 0.64 | J14: 0 | K14: 3.15 | L14: 3.32 | M14: 1.97
A15: Miscellaneous Expenses | B15: 91562.1 | C15: 95857.66 | D15: 64617.81 | E15: 62361.37 | F15: 67033.29 | H15: NON-CURRENT LIABILITIES
A16: Total Expenses | B16: 95818.98 | C16: 100894.8 | D16: 70155.01 | E16: 66384.97 | F16: 70122.37 | H16: Long Term Borrowings | I16: 2950 | J16: 950 | K16: 950 | L16: 600 | M16: 600
B17: Mar '25 | C17: Mar '24 | D17: Mar '23 | E17: Mar '22 | F17: Mar '21 | H17: Other Long Term Liabilities | I17: 222825.24 | J17: 186108.56 | K17: 150374.05 | L17: 128861.47 | M17: 90362.88
H18: Long Term Provisions | I18: 97776.29 | J18: 92119.83 | K18: 75383.56 | L18: 78711.89 | M18: 70963.52
B19: 12 mths | C19: 12 mths | D19: 12 mths | E19: 12 mths | F19: 12 mths | H19: Total Non-Current Liabilities | I19: 323551.53 | J19: 279178.39 | K19: 226707.61 | L19: 208173.36 | M19: 161926.4
H20: CURRENT LIABILITIES
A21: Operating Profit | B21: 1102.76 | C21: 586.99 | D21: 52.07 | E21: 740.87 | F21: 1360.28 | H21: Other Current Liabilities | I21: 9587.87 | J21: 8728.61 | K21: 8043.03 | L21: 6836 | M21: 6440.04
A22: PBDIT | B22: 1519.95 | C22: 1135.76 | D22: 1599.44 | E22: 1568.98 | F22: 1697.78 | H22: Short Term Provisions | I22: 117.56 | J22: 113.59 | K22: 128.21 | L22: 111.76 | M22: 80.01
A23: Interest | B23: 127.46 | C23: 80.01 | D23: 82.41 | E23: 25.57 | F23: 18.43 | H23: Total Current Liabilities | I23: 9705.43 | J23: 8842.21 | K23: 8171.24 | L23: 6947.76 | M23: 6520.06
A24: PBDT | B24: 1392.49 | C24: 1055.75 | D24: 1517.03 | E24: 1543.41 | F24: 1679.35 | H24: Total Capital And Liabilities | I24: 349411.58 | J24: 302686.95 | K24: 247871.99 | L24: 230734.45 | M24: 179641.26
A25: Depreciation | B25: 102.75 | C25: 78.47 | D25: 75.71 | E25: 56.16 | F25: 50.69 | H25: ASSETS
A26: Profit Before Tax | B26: 1289.74 | C26: 977.28 | D26: 1441.32 | E26: 1487.25 | F26: 1628.66 | H26: NON-CURRENT ASSETS
A27: PBT (Post Extra-ord Items) | B27: 1289.74 | C27: 977.28 | D27: 1441.32 | E27: 1487.25 | F27: 1628.66 | H27: Tangible Assets | I27: 445.4 | J27: 316.52 | K27: 293.61 | L27: 292.01 | M27: 327.28
A28: Tax | B28: -521.08 | C28: -596.8 | D28: 73.05 | E28: 160.32 | F28: 267.8 | H28: Intangible Assets | I28: 54.03 | J28: 76.15 | K28: 57.98 | L28: 58.17 | M28: 0
A29: Reported Net Profit | B29: 1810.82 | C29: 1574.08 | D29: 1368.28 | E29: 1326.93 | F29: 1360.87 | H29: Capital Work-In-Progress | I29: 109.17 | J29: 27.67 | K29: 30.79 | L29: 19.8 | M29: 14.24
A30: Net P/L After Minority Interest & Share Of Associates | B30: 1759.5 | C30: 1550.12 | D30: 1258.22 | E30: 1264.58 | F30: 1468.42 | H30: Fixed Assets | I30: 608.6 | J30: 420.34 | K30: 382.38 | L30: 369.99 | M30: 341.52
A31: Total Value Addition | B31: 95818.98 | C31: 100894.8 | D31: 70155.01 | E31: 66384.97 | F31: 70122.36 | H31: Non-Current Investments | I31: 336398.81 | J31: 292284.25 | K31: 238842.71 | L31: 217191.54 | M31: 173820.96
A32: Equity Dividend | B32: 430.2 | C32: 408.43 | D32: 359.22 | E32: 408.47 | F32: 0 | H32: Long Term Loans And Advances | I32: 2378.3 | J32: 1897.22 | K32: 1585.31 | L32: 1271.93 | M32: 424.05
A33: Per share data (annualised) | H33: Total Non-Current Assets | I33: 339385.71 | J33: 294601.8 | K33: 240810.41 | L33: 224447.62 | M33: 174586.54
A34: Shares in issue (lakhs) | B34: 21529.88 | C34: 21509.44 | D34: 21493.96 | E34: 21126.19 | F34: 20209.44 | H34: CURRENT ASSETS
A35: Earning Per Share (Rs) | B35: 8.41 | C35: 7.32 | D35: 6.37 | E35: 6.28 | F35: 6.73 | H35: Cash And Cash Equivalents | I35: 1820.95 | J35: 1558.61 | K35: 1168.55 | L35: 1375.15 | M35: 1099.26
A36: Book Value (Rs) | B36: 75.03 | C36: 68.19 | D36: 60.44 | E36: 73.89 | F36: 55.38 | H36: Short Term Loans And Advances | I36: 8204.92 | J36: 6526.54 | K36: 5893.03 | L36: 4911.68 | M36: 3955.46
H37: Total Current Assets | I37: 10025.87 | J37: 8085.15 | K37: 7061.58 | L37: 6286.83 | M37: 5054.72
H38: Total Assets | I38: 349411.58 | J38: 302686.95 | K38: 247871.99 | L38: 230734.45 | M38: 179641.26
H39: OTHER ADDITIONAL INFORMATION
H40: CONTINGENT LIABILITIES, COMMITMENTS
H41: Contingent Liabilities | I41: 3288.9 | J41: 2726.42 | K41: 1441.58 | L41: 1795.21 | M41: 2023.49
H42: BONUS DETAILS
H43: NON-CURRENT INVESTMENTS
H44: CURRENT INVESTMENTS

Sheet HDFC Life Ratio Analysis
A1: HDFC Life Insurance Ratio Analysis
A2: Ratio Type | B2: Ratio Formula | C2: 2025 | D2: 2024 | E2: 2023 | F2: 2022 | G2: 2021
A3: Liquidity Ratios
A4: Current Ratio | B4: = Current Assets/Current Liabilities | C4: ='HDFC Life Insurance'!I37/'HDFC Life Insurance'!I23 -> 1.0330166 | D4: ='HDFC Life Insurance'!J37/'HDFC Life Insurance'!J23 -> 0.91438113 | E4: ='HDFC Life Insurance'!K37/'HDFC Life Insurance'!K23 -> 0.86419931 | F4: ='HDFC Life Insurance'!L37/'HDFC Life Insurance'!L23 -> 0.9048715 | G4: ='HDFC Life Insurance'!M37/'HDFC Life Insurance'!M23 -> 0.77525667
A5: Quick Ratio | B5: = (Current Assets - Inventory - Prepaid Expenses)/Current Liabilities | C5: =('HDFC Life Insurance'!I37/'HDFC Life Insurance'!I23) -> 1.0330166 | D5: =('HDFC Life Insurance'!J37/'HDFC Life Insurance'!J23) -> 0.91438113 | E5: =('HDFC Life Insurance'!K37/'HDFC Life Insurance'!K23) -> 0.86419931 | F5: =('HDFC Life Insurance'!L37/'HDFC Life Insurance'!L23) -> 0.9048715 | G5: =('HDFC Life Insurance'!M37/'HDFC Life Insurance'!M23) -> 0.77525667 | H5: No inventory and prepaid expenses.
A6: Leverage Ratios
A7: Debt-Equity Ratio | B7: = Long Term Debt/Shareholders Equity | C7: ='HDFC Life Insurance'!I16/'HDFC Life Insurance'!I13 -> 0.18261753 | D7: ='HDFC Life Insurance'!J16/'HDFC Life Insurance'!J13 -> 0.064774126 | E7: ='HDFC Life Insurance'!K16/'HDFC Life Insurance'!K13 -> 0.073133236 | F7: ='HDFC Life Insurance'!L16/'HDFC Life Insurance'!L13 -> 0.038436875 | G7: ='HDFC Life Insurance'!M16/'HDFC Life Insurance'!M13 -> 0.053605746
A8: Debt to Total Assets Ratio | B8: = Total Debt/Total Assets | C8: ='HDFC Life Insurance'!I16/'HDFC Life Insurance'!I38 -> 0.0084427654 | D8: ='HDFC Life Insurance'!J16/'HDFC Life Insurance'!J38 -> 0.0031385562 | E8: ='HDFC Life Insurance'!K16/'HDFC Life Insurance'!K38 -> 0.0038326234 | F8: ='HDFC Life Insurance'!L16/'HDFC Life Insurance'!L38 -> 0.0026003919 | G8: ='HDFC Life Insurance'!M16/'HDFC Life Insurance'!M38 -> 0.0033399899
A9: Proprietary Ratio | B9: = Shareholders Equity/Total Assets | C9: ='HDFC Life Insurance'!I13/'HDFC Life Insurance'!I38 -> 0.046231954 | D9: ='HDFC Life Insurance'!J13/'HDFC Life Insurance'!J38 -> 0.048453856 | E9: ='HDFC Life Insurance'!K13/'HDFC Life Insurance'!K38 -> 0.052406042 | F9: ='HDFC Life Insurance'!L13/'HDFC Life Insurance'!L38 -> 0.067653573 | G9: ='HDFC Life Insurance'!M13/'HDFC Life Insurance'!M38 -> 0.062306566
A10: Interest Coverage Ratio | B10: = EBIT/Interest | C10: ='HDFC Life Insurance'!B21/'HDFC Life Insurance'!B23 -> 8.6518123 | D10: ='HDFC Life Insurance'!C21/'HDFC Life Insurance'!C23 -> 7.3364579 | E10: ='HDFC Life Insurance'!D21/'HDFC Life Insurance'!D23 -> 0.6318408 | F10: ='HDFC Life Insurance'!E21/'HDFC Life Insurance'!E23 -> 28.974189 | G10: ='HDFC Life Insurance'!F21/'HDFC Life Insurance'!F23 -> 73.807922
A11: Profitability Ratios related to Sales
A12: Gross Profit Ratio | B12: = Gross Profit (Sales-COGS) / Sales | C12: =('HDFC Life Insurance'!B9 - 88950)/'HDFC Life Insurance'!B9 -> 0.082249246 | D12: =('HDFC Life Insurance'!C9 - 93490)/'HDFC Life Insurance'!C9 -> 0.078750976 | E12: =('HDFC Life Insurance'!D9 - 60360)/'HDFC Life Insurance'!D9 -> 0.14025765 | F12: =('HDFC Life Insurance'!E9 - 59810)/'HDFC Life Insurance'!E9 -> 0.10898694 | G12: =('HDFC Life Insurance'!F9 - 59550)/'HDFC Life Insurance'!F9 -> 0.16693072 | H12: COGS from Finbox.
A13: Operating Profit Ratio | B13: = EBIT/Sales | C13: ='HDFC Life Insurance'!B21/'HDFC Life Insurance'!B9 -> 0.011377839 | D13: ='HDFC Life Insurance'!C21/'HDFC Life Insurance'!C9 -> 0.0057841904 | E13: ='HDFC Life Insurance'!D21/'HDFC Life Insurance'!D9 -> 0.00074166309 | F13: ='HDFC Life Insurance'!E21/'HDFC Life Insurance'!E9 -> 0.011037031 | G13: ='HDFC Life Insurance'!F21/'HDFC Life Insurance'!F9 -> 0.019029513
A14: Net Profit Ratio | B14: = EAT/Sales | C14: ='HDFC Life Insurance'!B29/'HDFC Life Insurance'!B9 -> 0.018683321 | D14: ='HDFC Life Insurance'!C29/'HDFC Life Insurance'!C9 -> 0.01551096 | E14: ='HDFC Life Insurance'!D29/'HDFC Life Insurance'!D9 -> 0.019489203 | F14: ='HDFC Life Insurance'!E29/'HDFC Life Insurance'!E9 -> 0.019767797 | G14: ='HDFC Life Insurance'!F29/'HDFC Life Insurance'!F9 -> 0.019037767
A15: Administrative Expenses Ratio | B15: = Admin Expenses/Sales | C15: ='HDFC Life Insurance'!B14/'HDFC Life Insurance'!B9 -> 0.010766315 | D15: ='HDFC Life Insurance'!C14/'HDFC Life Insurance'!C9 -> 0.017442243 | E15: ='HDFC Life Insurance'!D14/'HDFC Life Insurance'!D9 -> 0.035171951 | F15: ='HDFC Life Insurance'!E14/'HDFC Life Insurance'!E9 -> 0.028167245 | G15: ='HDFC Life Insurance'!F14/'HDFC Life Insurance'!F9 -> 0.019728564
A16: Selling Expenses Ratio | B16: = Selling Expenses/Sales | C16: ='HDFC Life Insurance'!B14/'HDFC Life Insurance'!B9 -> 0.010766315 | D16: ='HDFC Life Insurance'!C14/'HDFC Life Insurance'!C9 -> 0.017442243 | E16: ='HDFC Life Insurance'!D14/'HDFC Life Insurance'!D9 -> 0.035171951 | F16: ='HDFC Life Insurance'!E14/'HDFC Life Insurance'!E9 -> 0.028167245 | G16: ='HDFC Life Insurance'!F14/'HDFC Life Insurance'!F9 -> 0.019728564
A17: Operating Expenses Ratio | B17: = (Admin Expenses + Selling Expenses) / Sales | C17: ='HDFC Life Insurance'!B14/'HDFC Life Insurance'!B9 -> 0.010766315 | D17: ='HDFC Life Insurance'!C14/'HDFC Life Insurance'!C9 -> 0.017442243 | E17: ='HDFC Life Insurance'!D14/'HDFC Life Insurance'!D9 -> 0.035171951 | F17: ='HDFC Life Insurance'!E14/'HDFC Life Insurance'!E9 -> 0.028167245 | G17: ='HDFC Life Insurance'!F14/'HDFC Life Insurance'!F9 -> 0.019728564
A18: Operating Ratio | B18: = (COGS+Operating Expenses) / Sales | C18: =(88950+'HDFC Life Insurance'!B14)/'HDFC Life Insurance'!B9 -> 0.92851707 | D18: =(93490+'HDFC Life Insurance'!C14)/'HDFC Life Insurance'!C9 -> 0.93869127 | E18: =(60360+'HDFC Life Insurance'!D14)/'HDFC Life Insurance'!D9 -> 0.8949143 | F18: =(59810+'HDFC Life Insurance'!E14)/'HDFC Life Insurance'!E9 -> 0.9191803 | G18: =(59550+'HDFC Life Insurance'!F14)/'HDFC Life Insurance'!F9 -> 0.85279785 | H18: COGS from Finbox.
A19: Profitability Ratios related to Investment
A20: Return on Assets | B20: = EAT/Total Assets | C20: ='HDFC Life Insurance'!B29/'HDFC Life Insurance'!I38 -> 0.0051824842 | D20: ='HDFC Life Insurance'!C29/'HDFC Life Insurance'!J38 -> 0.0052003563 | E20: ='HDFC Life Insurance'!D29/'HDFC Life Insurance'!K38 -> 0.0055201074 | F20: ='HDFC Life Insurance'!E29/'HDFC Life Insurance'!L38 -> 0.0057508968 | G20: ='HDFC Life Insurance'!F29/'HDFC Life Insurance'!M38 -> 0.0075754868
A21: Return on Capital Employed | B21: = EBIT/Total Capital Employed | C21: ='HDFC Life Insurance'!B21/('HDFC Life Insurance'!I38-'HDFC Life Insurance'!I23) -> 0.0032462174 | D21: ='HDFC Life Insurance'!C21/('HDFC Life Insurance'!J38-'HDFC Life Insurance'!J23) -> 0.0019976196 | E21: ='HDFC Life Insurance'!D21/('HDFC Life Insurance'!K38-'HDFC Life Insurance'!K23) -> 0.00021722919 | F21: ='HDFC Life Insurance'!E21/('HDFC Life Insurance'!L38-'HDFC Life Insurance'!L23) -> 0.003310608 | G21: ='HDFC Life Insurance'!F21/('HDFC Life Insurance'!M38-'HDFC Life Insurance'!M23) -> 0.0078573855
A22: Return on Equity | B22: = EAT/Shareholders Equity | C22: ='HDFC Life Insurance'!B29/'HDFC Life Insurance'!I13 -> 0.11209745 | D22: ='HDFC Life Insurance'!C29/'HDFC Life Insurance'!J13 -> 0.10732595 | E22: ='HDFC Life Insurance'!D29/'HDFC Life Insurance'!K13 -> 0.10533341 | F22: ='HDFC Life Insurance'!E29/'HDFC Life Insurance'!L13 -> 0.08500507 | G22: ='HDFC Life Insurance'!F29/'HDFC Life Insurance'!M13 -> 0.12158409
A23: Profitability Ratios related to Equity Shares
A24: Earnings Per Share | B24: = Net Profit Available to Equity Shareholders/Number of Equity Shares | C24: ='HDFC Life Insurance'!B29/'HDFC Life Insurance'!B34*100 -> 8.4107296 | D24: ='HDFC Life Insurance'!C29/'HDFC Life Insurance'!C34*100 -> 7.3180892 | E24: ='HDFC Life Insurance'!D29/'HDFC Life Insurance'!D34*100 -> 6.3658814 | F24: ='HDFC Life Insurance'!E29/'HDFC Life Insurance'!E34*100 -> 6.2809716 | G24: ='HDFC Life Insurance'!F29/'HDFC Life Insurance'!F34*100 -> 6.7338333
A25: Earnings Yield | B25: = EPS/Market Price Per Share | C25: =C24/685.7 -> 0.012265903 | D25: =D24/633.35 -> 0.011554574 | E25: =E24/499.2 -> 0.012752166 | F25: =F24/550.35 -> 0.011412686 | G25: =G24/691 -> 0.0097450554 | H25: MPS from NSE.
A26: Dividend Yield | B26: = DPS/MPS | C26: =('HDFC Life Insurance'!B32/'HDFC Life Insurance'!B34*100)/685.7 -> 0.0029140342 | D26: =('HDFC Life Insurance'!C32/'HDFC Life Insurance'!C34*100)/633.35 -> 0.0029980906 | E26: =('HDFC Life Insurance'!D32/'HDFC Life Insurance'!D34*100)/499.2 -> 0.003347877 | F26: =('HDFC Life Insurance'!E32/'HDFC Life Insurance'!E34*100)/550.35 -> 0.0035131769 | G26: =('HDFC Life Insurance'!F32/'HDFC Life Insurance'!F34*100)/691 -> 0 | H26: MPS from NSE.
A27: Dividend Payout Ratio | B27: = DPS/EPS | C27: =('HDFC Life Insurance'!B32/'HDFC Life Insurance'!B34*100)/C24 -> 0.23757193 | D27: =('HDFC Life Insurance'!C32/'HDFC Life Insurance'!C34*100)/D24 -> 0.2594722 | E27: =('HDFC Life Insurance'!D32/'HDFC Life Insurance'!D34*100)/E24 -> 0.26253398 | F27: =('HDFC Life Insurance'!E32/'HDFC Life Insurance'!E34*100)/F24 -> 0.30783086 | G27: =('HDFC Life Insurance'!F32/'HDFC Life Insurance'!F34*100)/G24 -> 0
A28: Price to Earnings Ratio | B28: = MPS/EPS | C28: =685.7/C24 -> 81.526815 | D28: =633.35/D24 -> 86.545816 | E28: =499.2/E24 -> 78.418049 | F28: =550.35/F24 -> 87.621794 | G28: =691/G24 -> 102.61614 | H28: MPS from NSE.
A29: Profitability Ratios related to Earning Power
A30: Return on Investment (ROI) | B30: = EAT/Total Assets | C30: ='HDFC Life Insurance'!B29/'HDFC Life Insurance'!I38 -> 0.0051824842 | D30: ='HDFC Life Insurance'!C29/'HDFC Life Insurance'!J38 -> 0.0052003563 | E30: ='HDFC Life Insurance'!D29/'HDFC Life Insurance'!K38 -> 0.0055201074 | F30: ='HDFC Life Insurance'!E29/'HDFC Life Insurance'!L38 -> 0.0057508968 | G30: ='HDFC Life Insurance'!F29/'HDFC Life Insurance'!M38 -> 0.0075754868
A31: Activity or Efficiency Ratios
A32: Current Assets Turnover | B32: = Sales/Current Assets | C32: ='HDFC Life Insurance'!B9/'HDFC Life Insurance'!I37 -> 9.667165 | D32: ='HDFC Life Insurance'!C9/'HDFC Life Insurance'!J37 -> 12.551627 | E32: ='HDFC Life Insurance'!D9/'HDFC Life Insurance'!K37 -> 9.9421206 | F32: ='HDFC Life Insurance'!E9/'HDFC Life Insurance'!L37 -> 10.677216 | G32: ='HDFC Life Insurance'!F9/'HDFC Life Insurance'!M37 -> 14.141763
A33: Fixed Assets Turnover | B33: = Sales/Fixed Assets | C33: ='HDFC Life Insurance'!B9/'HDFC Life Insurance'!I30 -> 159.2536 | D33: ='HDFC Life Insurance'!C9/'HDFC Life Insurance'!J30 -> 241.42787 | E33: ='HDFC Life Insurance'!D9/'HDFC Life Insurance'!K30 -> 183.60552 | F33: ='HDFC Life Insurance'!E9/'HDFC Life Insurance'!L30 -> 181.42609 | G33: ='HDFC Life Insurance'!F9/'HDFC Life Insurance'!M30 -> 209.30736
A34: Total Assets Turnover | B34: = Sales/Total Assets | C34: ='HDFC Life Insurance'!B9/'HDFC Life Insurance'!I38 -> 0.2773856 | D34: ='HDFC Life Insurance'!C9/'HDFC Life Insurance'!J38 -> 0.33526979 | E34: ='HDFC Life Insurance'!D9/'HDFC Life Insurance'!K38 -> 0.28323926 | F34: ='HDFC Life Insurance'!E9/'HDFC Life Insurance'!L38 -> 0.29092249 | G34: ='HDFC Life Insurance'!F9/'HDFC Life Insurance'!M38 -> 0.39791889
A35: Inventory Turnover | B35: = Sales / Average Inventory | C35: =IFERROR('HDFC Life Insurance'!B9/0,0) -> 0 | D35: =IFERROR('HDFC Life Insurance'!C9/0,0) -> 0 | E35: =IFERROR('HDFC Life Insurance'!D9/0,0) -> 0 | F35: =IFERROR('HDFC Life Insurance'!E9/0,0) -> 0 | G35: =IFERROR('HDFC Life Insurance'!F9/0,0) -> 0
A36: Debtors Turnover | B36: = Sales / Average Debtors | C36: =IFERROR('HDFC Life Insurance'!B9/0,0) -> 0 | D36: =IFERROR('HDFC Life Insurance'!C9/0,0) -> 0 | E36: =IFERROR('HDFC Life Insurance'!D9/0,0) -> 0 | F36: =IFERROR('HDFC Life Insurance'!E9/0,0) -> 0 | G36: =IFERROR('HDFC Life Insurance'!F9/0,0) -> 0
A37: Assessment of Risk
A38: DTL | B38: = Contribution/EBT | C38: =('HDFC Life Insurance'!B9-'HDFC Life Insurance'!B14-'HDFC Life Insurance'!B13-'HDFC Life Insurance'!B15)/'HDFC Life Insurance'!B26 -> 0.85502504 | D38: =('HDFC Life Insurance'!C9-'HDFC Life Insurance'!C14-'HDFC Life Insurance'!C13-'HDFC Life Insurance'!C15)/'HDFC Life Insurance'!C26 -> 0.60063646 | E38: =('HDFC Life Insurance'!D9-'HDFC Life Insurance'!D14-'HDFC Life Insurance'!D13-'HDFC Life Insurance'!D15)/'HDFC Life Insurance'!D26 -> 0.036126606 | F38: =('HDFC Life Insurance'!E9-'HDFC Life Insurance'!E14-'HDFC Life Insurance'!E13-'HDFC Life Insurance'!E15)/'HDFC Life Insurance'!E26 -> 0.49814759 | G38: =('HDFC Life Insurance'!F9-'HDFC Life Insurance'!F14-'HDFC Life Insurance'!F13-'HDFC Life Insurance'!F15)/'HDFC Life Insurance'!F26 -> 0.83521423
A39: DOL | B39: = Contribution/EBIT | C39: =('HDFC Life Insurance'!B9-'HDFC Life Insurance'!B14-'HDFC Life Insurance'!B13-'HDFC Life Insurance'!B15)/'HDFC Life Insurance'!B21 -> 1 | D39: =('HDFC Life Insurance'!C9-'HDFC Life Insurance'!C14-'HDFC Life Insurance'!C13-'HDFC Life Insurance'!C15)/'HDFC Life Insurance'!C21 -> 1 | E39: =('HDFC Life Insurance'!D9-'HDFC Life Insurance'!D14-'HDFC Life Insurance'!D13-'HDFC Life Insurance'!D15)/'HDFC Life Insurance'!D21 -> 1 | F39: =('HDFC Life Insurance'!E9-'HDFC Life Insurance'!E14-'HDFC Life Insurance'!E13-'HDFC Life Insurance'!E15)/'HDFC Life Insurance'!E21 -> 1 | G39: =('HDFC Life Insurance'!F9-'HDFC Life Insurance'!F14-'HDFC Life Insurance'!F13-'HDFC Life Insurance'!F15)/'HDFC Life Insurance'!F21 -> 1
A40: DFL | B40: = EBIT/EBT | C40: ='HDFC Life Insurance'!B21/'HDFC Life Insurance'!B29 -> 0.60898378 | D40: ='HDFC Life Insurance'!C21/'HDFC Life Insurance'!C29 -> 0.37290989 | E40: ='HDFC Life Insurance'!D21/'HDFC Life Insurance'!D29 -> 0.038055076 | F40: ='HDFC Life Insurance'!E21/'HDFC Life Insurance'!E29 -> 0.5583339 | G40: ='HDFC Life Insurance'!F21/'HDFC Life Insurance'!F29 -> 0.99956645

Sheet Adani Enterprises
A1: Adani Enterprises | H1: Adani Enterprises
A2: Consolidated Profit & Loss account | B2: ------------------- in Rs. Cr. ------------------- | H2: Consolidated Balance Sheet | I2: ------------------- in Rs. Cr. -------------------
B3: Mar '25 | C3: Mar '24 | D3: Mar '23 | E3: Mar '22 | F3: Mar '21 | I3: Mar 25 | J3: 45352 | K3: 44986 | L3: 44621 | M3: 44256
B5: 12 mths | C5: 12 mths | D5: 12 mths | E5: 12 mths | F5: 12 mths | I5: 12 mths | J5: 12 mths | K5: 12 mths | L5: 12 mths | M5: 12 mths
A7: Income | H7: EQUITIES AND LIABILITIES
A8: Sales Turnover | B8: 97894.75 | C8: 96420.98 | D8: 136977.76 | E8: 69420.18 | F8: 39537.13 | H8: SHAREHOLDER'S FUNDS
A9: Net Sales | B9: 97894.75 | C9: 96420.98 | D9: 136977.76 | E9: 69420.18 | F9: 39537.13 | H9: Equity Share Capital | I9: 115.42 | J9: 114 | K9: 114 | L9: 109.98 | M9: 109.98
A10: Other Income | B10: 6374.44 | C10: 1145.58 | D10: 828.04 | E10: 1010.08 | F10: 491.09 | H10: Total Share Capital | I10: 115.42 | J10: 114 | K10: 114 | L10: 109.98 | M10: 109.98
A11: Stock Adjustments | B11: -1844.54 | C11: 1116.49 | D11: 327.16 | E11: 3933.82 | F11: -456.74 | H11: Reserves and Surplus | I11: 47574.55 | J11: 35160.97 | K11: 31759.89 | L11: 21506.53 | M11: 17048.59
A12: Total Income | B12: 102424.65 | C12: 98683.05 | D12: 138132.96 | E12: 74364.08 | F12: 39571.48 | H12: Total Reserves and Surplus | I12: 47574.55 | J12: 35160.97 | K12: 31759.89 | L12: 21506.53 | M12: 17048.59
A13: Expenditure | H13: Total Shareholders Funds | I13: 47689.97 | J13: 35274.97 | K13: 31873.89 | L13: 21616.51 | M13: 17158.57
A14: Raw Materials | B14: 49524.73 | C14: 51507.72 | D14: 103239.89 | E14: 57651.32 | F14: 29791.08 | H14: Hybrid/Debt/Other Securities | I14: 2624 | J14: 3801.12 | K14: 1177.12 | L14: 640 | M14: 0
A15: Power & Fuel Cost | B15: 1955.65 | C15: 26.46 | D15: 0 | E15: 58.98 | F15: 13.4 | H15: Minority Interest | I15: 6156.48 | J15: 5110.2 | K15: 4839.04 | L15: 4671.86 | M15: 1751.44
A16: Employee Cost | B16: 3118.9 | C16: 2330.95 | D16: 1877.33 | E16: 1180.56 | F16: 829.31 | H16: NON-CURRENT LIABILITIES
A17: Other Manufacturing Expenses | B17: 0 | C17: 0 | D17: 0 | E17: 3101.16 | F17: 1777.54 | H17: Long Term Borrowings | I17: 64601.26 | J17: 43718.15 | K17: 32590.03 | L17: 20803.43 | M17: 9523.3
A18: Selling and Admin Expenses | B18: 823.13 | C18: 678.93 | D18: 0 | E18: 147.8 | F18: 166.91 | H18: Deferred Tax Liabilities [Net] | I18: 3362.35 | J18: 2933.84 | K18: 2979.91 | L18: 2606.27 | M18: 26.14
A19: Miscellaneous Expenses | B19: 26375.77 | C19: 31616.81 | D19: 23359.72 | E19: 7500.98 | F19: 3997.1 | H19: Other Long Term Liabilities | I19: 25829.75 | J19: 24795.43 | K19: 22823.29 | L19: 7293.37 | M19: 1623.5
A20: Total Expenses | B20: 81798.18 | C20: 86160.87 | D20: 128476.94 | E20: 69640.8 | F20: 36575.34 | H20: Long Term Provisions | I20: 488.58 | J20: 446.45 | K20: 401.49 | L20: 278.97 | M20: 76.82
B21: Mar '25 | C21: Mar '24 | D21: Mar '23 | E21: Mar '22 | F21: Mar '21 | H21: Total Non-Current Liabilities | I21: 94281.94 | J21: 71893.87 | K21: 58794.72 | L21: 30982.04 | M21: 11249.76
H22: CURRENT LIABILITIES
B23: 12 mths | C23: 12 mths | D23: 12 mths | E23: 12 mths | F23: 12 mths | H23: Short Term Borrowings | I23: 11635.15 | J23: 6405.73 | K23: 5729.59 | L23: 20220.34 | M23: 5770.01
H24: Trade Payables | I24: 20867.68 | J24: 24669.26 | K24: 28546.85 | L24: 17647.82 | M24: 11756.34
A25: Operating Profit | B25: 14252.03 | C25: 11376.6 | D25: 8827.98 | E25: 3713.2 | F25: 2505.05 | H25: Other Current Liabilities | I25: 14660.16 | J25: 13424.08 | K25: 10405.59 | L25: 5885.89 | M25: 3891.98
A26: PBDIT | B26: 20626.47 | C26: 12522.18 | D26: 9656.02 | E26: 4723.28 | F26: 2996.14 | H26: Short Term Provisions | I26: 220.16 | J26: 152.62 | K26: 121.02 | L26: 95.73 | M26: 64.76
A27: Interest | B27: 5978.02 | C27: 4554.7 | D27: 3969.98 | E27: 2525.88 | F27: 1376.85 | H27: Total Current Liabilities | I27: 47383.15 | J27: 44651.69 | K27: 44803.05 | L27: 43849.78 | M27: 21483.09
A28: PBDT | B28: 14648.45 | C28: 7967.48 | D28: 5686.04 | E28: 2197.4 | F28: 1619.29 | H28: Total Capital And Liabilities | I28: 198135.54 | J28: 160731.85 | K28: 141487.82 | L28: 101760.19 | M28: 51642.86
A29: Depreciation | B29: 4211.33 | C29: 3042.15 | D29: 2436.14 | E29: 1247.78 | F29: 537.14 | H29: ASSETS
A30: Profit Before Tax | B30: 10437.12 | C30: 4925.33 | D30: 3249.9 | E30: 949.62 | F30: 1082.15 | H30: NON-CURRENT ASSETS
A31: PBT (Post Extra-ord Items) | B31: 10437.12 | C31: 4925.33 | D31: 3249.9 | E31: 949.62 | F31: 1082.15 | H31: Tangible Assets | I31: 67377.82 | J31: 58939.76 | K31: 49858.23 | L31: 20821.32 | M31: 5678.88
A32: Tax | B32: 2968.52 | C32: 1631.51 | D32: 1040.96 | E32: 476.68 | F32: 339.65 | H32: Intangible Assets | I32: 8796.27 | J32: 5998.53 | K32: 6135.74 | L32: 9000.53 | M32: 5006.76
A33: Reported Net Profit | B33: 6591.27 | C33: 3294.63 | D33: 2208.94 | E33: 464.23 | F33: 623.2 | H33: Capital Work-In-Progress | I33: 31856.6 | J33: 21930.98 | K33: 17698.96 | L33: 19564.17 | M33: 8686.27
A34: Minority Interest | B34: 0 | C34: 0 | D34: -51.34 | E34: 0 | F34: 0 | H34: Intangible Assets Under Development | I34: 19659.21 | J34: 13248.52 | K34: 6326.25 | L34: 3980.25 | M34: 139.19
A35: Share Of P/L Of Associates | B35: -507.73 | C35: -40.64 | D35: -212.66 | E35: -312.33 | F35: -299.44 | H35: Fixed Assets | I35: 127689.9 | J35: 100117.79 | K35: 80019.18 | L35: 53366.27 | M35: 19511.1
A36: Net P/L After Minority Interest & Share Of Associates | B36: 4072.22 | C36: 4049.41 | D36: 2842.26 | E36: 787.7 | F36: 1304.65 | H36: Non-Current Investments | I36: 7631.02 | J36: 7246.21 | K36: 6145.17 | L36: 4229.19 | M36: 5473.43
A37: Total Value Addition | B37: 32273.45 | C37: 34653.15 | D37: 25237.05 | E37: 11989.48 | F37: 6784.26 | H37: Deferred Tax Assets [Net] | I37: 292.66 | J37: 145.61 | K37: 209.34 | L37: 173.83 | M37: 76.54
A38: Equity Dividend | B38: 148.2 | C38: 136.8 | D38: 0 | E38: 109.98 | F38: 0 | H38: Long Term Loans And Advances | I38: 3903.4 | J38: 2300 | K38: 4577.03 | L38: 6236.53 | M38: 3199.01
A39: Per share data (annualised) | H39: Other Non-Current Assets | I39: 16788.04 | J39: 13022.14 | K39: 12528.21 | L39: 6508.06 | M39: 3267.5
A40: Shares in issue (lakhs) | B40: 11541.81 | C40: 11400.01 | D40: 11400 | E40: 10998.1 | F40: 10998.1 | H40: Total Non-Current Assets | I40: 157391.07 | J40: 123871.76 | K40: 104366.09 | L40: 70814.8 | M40: 31679.55
A41: Earning Per Share (Rs) | B41: 57.11 | C41: 28.9 | D41: 19.38 | E41: 4.22 | F41: 5.67 | H41: CURRENT ASSETS
A42: Book Value (Rs) | B42: 413.19 | C42: 309.43 | D42: 289.92 | E42: 196.55 | F42: 156.01 | H42: Current Investments | I42: 2255.59 | J42: 1454.48 | K42: 165 | L42: 63.02 | M42: 29.51 | N42: 43891
H43: Inventories | I43: 10287.39 | J43: 9486.86 | K43: 6918.05 | L43: 6788.28 | M43: 1757.04 | N43: 2562.37
H44: Trade Receivables | I44: 9616.47 | J44: 9792.93 | K44: 12552.88 | L44: 13712.19 | M44: 11982.65 | N44: 13146.53
H45: Cash And Cash Equivalents | I45: 6962.46 | J45: 7068.48 | K45: 5373.69 | L45: 3915.86 | M45: 1810.82
H46: Short Term Loans And Advances | I46: 1416.01 | J46: 1382.67 | K46: 4522.63 | L46: 1452.84 | M46: 1413.1
H47: OtherCurrentAssets | I47: 10206.55 | J47: 7674.67 | K47: 7589.48 | L47: 5013.2 | M47: 2970.19
H48: Total Current Assets | I48: 40744.47 | J48: 36860.09 | K48: 37121.73 | L48: 30945.39 | M48: 19963.31
H49: Total Assets | I49: 198135.54 | J49: 160731.85 | K49: 141487.82 | L49: 101760.19 | M49: 51642.86
H50: OTHER ADDITIONAL INFORMATION
H51: CONTINGENT LIABILITIES, COMMITMENTS
H52: Contingent Liabilities | I52: 37242.91 | J52: 35441.43 | K52: 42708.91 | L52: 23396.58 | M52: 12661.1
H53: BONUS DETAILS
H54: Bonus Equity Share Capital | I54: 41.84 | J54: 41.84 | K54: 41.84 | L54: 41.84 | M54: 41.84
H55: NON-CURRENT INVESTMENTS
H56: Non-Current Investments Quoted Market Value | I56: 10218.28 | J56: 0 | K56: 0 | L56: 0 | M56: 0
H57: Non-Current Investments Unquoted Book Value | I57: 4571.82 | J57: 171.26 | K57: 168.9 | L57: 4229.19 | M57: 5473.43
H58: CURRENT INVESTMENTS
H59: Current Investments Unquoted Book Value | I59: 2255.59 | J59: 1454.48 | K59: 165 | L59: 63.02 | M59: 29.51

Sheet Adani Enterprise Ratio Analysis
A1: Adani Enterprises Ratio Analysis
A2: Ratio Type | B2: Ratio Formula | C2: 2025 | D2: 2024 | E2: 2023 | F2: 2022 | G2: 2021
A3: Liquidity Ratios
A4: Current Ratio | B4: = Current Assets/Current Liabilities | C4: ='Adani Enterprises'!I48/'Adani Enterprises'!I27 -> 0.85989365 | D4: ='Adani Enterprises'!J48/'Adani Enterprises'!J27 -> 0.82550269 | E4: ='Adani Enterprises'!K48/'Adani Enterprises'!K27 -> 0.82855364 | F4: ='Adani Enterprises'!L48/'Adani Enterprises'!L27 -> 0.70571369 | G4: ='Adani Enterprises'!M48/'Adani Enterprises'!M27 -> 0.92925692
A5: Quick Ratio | B5: = (Current Assets - Inventory - Prepaid Expenses)/Current Liabilities | C5: =('Adani Enterprises'!I48-'Adani Enterprises'!I43)/'Adani Enterprises'!I27 -> 0.64278293 | D5: =('Adani Enterprises'!J48-'Adani Enterprises'!J43)/'Adani Enterprises'!J27 -> 0.61303906 | E5: =('Adani Enterprises'!K48-'Adani Enterprises'!K43)/'Adani Enterprises'!K27 -> 0.67414339 | F5: =('Adani Enterprises'!L48-'Adani Enterprises'!L43)/'Adani Enterprises'!L27 -> 0.55090607 | G5: =('Adani Enterprises'!M48-'Adani Enterprises'!M43)/'Adani Enterprises'!M27 -> 0.8474698
A6: Leverage Ratios
A7: Debt-Equity Ratio | B7: = Long Term Debt/Shareholders Equity | C7: ='Adani Enterprises'!I17/'Adani Enterprises'!I13 -> 1.3546089 | D7: ='Adani Enterprises'!J17/'Adani Enterprises'!J13 -> 1.2393533 | E7: ='Adani Enterprises'!K17/'Adani Enterprises'!K13 -> 1.0224679 | F7: ='Adani Enterprises'!L17/'Adani Enterprises'!L13 -> 0.96238616 | G7: ='Adani Enterprises'!M17/'Adani Enterprises'!M13 -> 0.55501711
A8: Debt to Total Assets Ratio | B8: = Total Debt/Total Assets | C8: =SUM('Adani Enterprises'!I17+'Adani Enterprises'!I23)/'Adani Enterprises'!I49 -> 0.38476898 | D8: =SUM('Adani Enterprises'!J17+'Adani Enterprises'!J23)/'Adani Enterprises'!J49 -> 0.31184784 | E8: =SUM('Adani Enterprises'!K17+'Adani Enterprises'!K23)/'Adani Enterprises'!K49 -> 0.27083335 | F8: =SUM('Adani Enterprises'!L17+'Adani Enterprises'!L23)/'Adani Enterprises'!L49 -> 0.40314164 | G8: =SUM('Adani Enterprises'!M17+'Adani Enterprises'!M23)/'Adani Enterprises'!M49 -> 0.296136
A9: Proprietary Ratio | B9: = Shareholders Equity/Total Assets | C9: ='Adani Enterprises'!I13/'Adani Enterprises'!I49 -> 0.24069367 | D9: ='Adani Enterprises'!J13/'Adani Enterprises'!J49 -> 0.21946472 | E9: ='Adani Enterprises'!K13/'Adani Enterprises'!K49 -> 0.22527656 | F9: ='Adani Enterprises'!L13/'Adani Enterprises'!L49 -> 0.212426 | G9: ='Adani Enterprises'!M13/'Adani Enterprises'!M49 -> 0.33225445
A10: Interest Coverage Ratio | B10: = EBIT/Interest | C10: ='Adani Enterprises'!B25/'Adani Enterprises'!B27 -> 2.384072 | D10: ='Adani Enterprises'!C25/'Adani Enterprises'!C27 -> 2.4977715 | E10: ='Adani Enterprises'!D25/'Adani Enterprises'!D27 -> 2.2236837 | F10: ='Adani Enterprises'!E25/'Adani Enterprises'!E27 -> 1.4700619 | G10: ='Adani Enterprises'!F25/'Adani Enterprises'!F27 -> 1.8194066
A11: Profitability Ratios related to Sales
A12: Gross Profit Ratio | B12: = Gross Profit (Sales-COGS) / Sales | C12: =('Adani Enterprises'!B9-('Adani Enterprises'!J43-'Adani Enterprises'!I43+'Adani Enterprises'!B14))/'Adani Enterprises'!B9 -> 0.50227974 | D12: =('Adani Enterprises'!C9-('Adani Enterprises'!K43-'Adani Enterprises'!J43+'Adani Enterprises'!C14))/'Adani Enterprises'!C9 -> 0.49244542 | E12: =('Adani Enterprises'!D9-('Adani Enterprises'!L43-'Adani Enterprises'!K43+'Adani Enterprises'!D14))/'Adani Enterprises'!D9 -> 0.24724919 | F12: =('Adani Enterprises'!E9-('Adani Enterprises'!M43-'Adani Enterprises'!L43+'Adani Enterprises'!E14))/'Adani Enterprises'!E9 -> 0.242006 | G12: =('Adani Enterprises'!F9-('Adani Enterprises'!N43-'Adani Enterprises'!M43+'Adani Enterprises'!F14))/'Adani Enterprises'!F9 -> 0.22613478
A13: Operating Profit Ratio | B13: = EBIT/Sales | C13: ='Adani Enterprises'!B25/'Adani Enterprises'!B9 -> 0.14558523 | D13: ='Adani Enterprises'!C25/'Adani Enterprises'!C9 -> 0.11798884 | E13: ='Adani Enterprises'!D25/'Adani Enterprises'!D9 -> 0.064448272 | F13: ='Adani Enterprises'!E25/'Adani Enterprises'!E9 -> 0.053488769 | G13: ='Adani Enterprises'!F25/'Adani Enterprises'!F9 -> 0.063359429
A14: Net Profit Ratio | B14: = EAT/Sales | C14: ='Adani Enterprises'!B33/'Adani Enterprises'!B9 -> 0.067330168 | D14: ='Adani Enterprises'!C33/'Adani Enterprises'!C9 -> 0.034169223 | E14: ='Adani Enterprises'!D33/'Adani Enterprises'!D9 -> 0.016126268 | F14: ='Adani Enterprises'!E33/'Adani Enterprises'!E9 -> 0.0066872486 | G14: ='Adani Enterprises'!F33/'Adani Enterprises'!F9 -> 0.015762399
A15: Administrative Expenses Ratio | B15: = Admin Expenses/Sales | C15: ='Adani Enterprises'!B18/'Adani Enterprises'!B9 -> 0.0084083161 | D15: ='Adani Enterprises'!C18/'Adani Enterprises'!C9 -> 0.0070413099 | E15: ='Adani Enterprises'!D18/'Adani Enterprises'!D9 -> 0 | F15: ='Adani Enterprises'!E18/'Adani Enterprises'!E9 -> 0.0021290639 | G15: ='Adani Enterprises'!F18/'Adani Enterprises'!F9 -> 0.0042216013
A16: Selling Expenses Ratio | B16: = Selling Expenses/Sales | C16: ='Adani Enterprises'!B18/'Adani Enterprises'!B9 -> 0.0084083161 | D16: ='Adani Enterprises'!C18/'Adani Enterprises'!C9 -> 0.0070413099 | E16: ='Adani Enterprises'!D18/'Adani Enterprises'!D9 -> 0 | F16: ='Adani Enterprises'!E18/'Adani Enterprises'!E9 -> 0.0021290639 | G16: ='Adani Enterprises'!F18/'Adani Enterprises'!F9 -> 0.0042216013
A17: Operating Expenses Ratio | B17: = (Admin Expenses + Selling Expenses) / Sales | C17: ='Adani Enterprises'!B18/'Adani Enterprises'!B9 -> 0.0084083161 | D17: ='Adani Enterprises'!C18/'Adani Enterprises'!C9 -> 0.0070413099 | E17: ='Adani Enterprises'!D18/'Adani Enterprises'!D9 -> 0 | F17: ='Adani Enterprises'!E18/'Adani Enterprises'!E9 -> 0.0021290639 | G17: ='Adani Enterprises'!F18/'Adani Enterprises'!F9 -> 0.0042216013
A18: Operating Ratio | B18: = (COGS+Operating Expenses) / Sales | C18: =(('Adani Enterprises'!J43-'Adani Enterprises'!I43+'Adani Enterprises'!B14)+'Adani Enterprises'!B18)/'Adani Enterprises'!B9 -> 0.50612857 | D18: =(('Adani Enterprises'!K43-'Adani Enterprises'!J43+'Adani Enterprises'!C14)+'Adani Enterprises'!C18)/'Adani Enterprises'!C9 -> 0.51459589 | E18: =(('Adani Enterprises'!L43-'Adani Enterprises'!K43+'Adani Enterprises'!D14)+'Adani Enterprises'!D18)/'Adani Enterprises'!D9 -> 0.75275081 | F18: =(('Adani Enterprises'!M43-'Adani Enterprises'!L43+'Adani Enterprises'!E14)+'Adani Enterprises'!E18)/'Adani Enterprises'!E9 -> 0.76012307 | G18: =(('Adani Enterprises'!N43-'Adani Enterprises'!M43+'Adani Enterprises'!F14)+'Adani Enterprises'!F18)/'Adani Enterprises'!F9 -> 0.77808683
A19: Profitability Ratios related to Investment
A20: Return on Assets | B20: = EAT/Total Assets | C20: ='Adani Enterprises'!B33/'Adani Enterprises'!I49 -> 0.03326647 | D20: ='Adani Enterprises'!C33/'Adani Enterprises'!J49 -> 0.02049768 | E20: ='Adani Enterprises'!D33/'Adani Enterprises'!K49 -> 0.015612227 | F20: ='Adani Enterprises'!E33/'Adani Enterprises'!L49 -> 0.0045620001 | G20: ='Adani Enterprises'!F33/'Adani Enterprises'!M49 -> 0.012067496
A21: Return on Capital Employed | B21: = EBIT/Total Capital Employed | C21: ='Adani Enterprises'!B33/('Adani Enterprises'!I49-'Adani Enterprises'!I27) -> 0.043722491 | D21: ='Adani Enterprises'!C33/('Adani Enterprises'!J49-'Adani Enterprises'!J27) -> 0.02838237 | E21: ='Adani Enterprises'!D33/('Adani Enterprises'!K49-'Adani Enterprises'!K27) -> 0.022846825 | F21: ='Adani Enterprises'!E33/('Adani Enterprises'!L49-'Adani Enterprises'!L27) -> 0.008016348 | G21: ='Adani Enterprises'!F33/('Adani Enterprises'!M49-'Adani Enterprises'!M27) -> 0.020663288
A22: Return on Equity | B22: = EAT/Shareholders Equity | C22: ='Adani Enterprises'!B33/'Adani Enterprises'!I13 -> 0.13821082 | D22: ='Adani Enterprises'!C33/'Adani Enterprises'!J13 -> 0.09339852 | E22: ='Adani Enterprises'!D33/'Adani Enterprises'!K13 -> 0.069302492 | F22: ='Adani Enterprises'!E33/'Adani Enterprises'!L13 -> 0.021475715 | G22: ='Adani Enterprises'!F33/'Adani Enterprises'!M13 -> 0.036320043
A23: Profitability Ratios related to Equity Shares
A24: Earnings Per Share | B24: = Net Profit Available to Equity Shareholders/Number of Equity Shares | C24: ='Adani Enterprises'!B33/'Adani Enterprises'!B40*100 -> 57.107767 | D24: ='Adani Enterprises'!C33/'Adani Enterprises'!C40*100 -> 28.900238 | E24: ='Adani Enterprises'!D33/'Adani Enterprises'!D40*100 -> 19.376667 | F24: ='Adani Enterprises'!E33/'Adani Enterprises'!E40*100 -> 4.2210018 | G24: ='Adani Enterprises'!F33/'Adani Enterprises'!F40*100 -> 5.6664333
A25: Earnings Yield | B25: = EPS/Market Price Per Share | C25: =C24/2315.8 -> 0.02466006 | D25: =D24/3197.1 -> 0.0090395164 | E25: =E24/1750.45 -> 0.011069535 | F25: =F24/2043.65 -> 0.002065423 | G25: =G24/1107.2 -> 0.0051178046 | H25: MPS from NSE.
A26: Dividend Yield | B26: = DPS/MPS | C26: =('Adani Enterprises'!B38/'Adani Enterprises'!B40*100)/2315.8 -> 0.00055446385 | D26: =('Adani Enterprises'!C38/'Adani Enterprises'!C40*100)/3197.1 -> 0.00037533982 | E26: =('Adani Enterprises'!D38/'Adani Enterprises'!D40*100)/1750.45 -> 0 | F26: =('Adani Enterprises'!E38/'Adani Enterprises'!E40*100)/2043.65 -> 0.00048931613 | G26: =('Adani Enterprises'!F38/'Adani Enterprises'!F40*100)/1107.2 -> 0 | H26: MPS from NSE.
A27: Dividend Payout Ratio | B27: = DPS/EPS | C27: =('Adani Enterprises'!B38/'Adani Enterprises'!B40*100)/C24 -> 0.022484286 | D27: =('Adani Enterprises'!C38/'Adani Enterprises'!C40*100)/D24 -> 0.041522113 | E27: =('Adani Enterprises'!D38/'Adani Enterprises'!D40*100)/E24 -> 0 | F27: =('Adani Enterprises'!E38/'Adani Enterprises'!E40*100)/F24 -> 0.23690843 | G27: =('Adani Enterprises'!F38/'Adani Enterprises'!F40*100)/G24 -> 0
A28: Price to Earnings Ratio | B28: = MPS/EPS | C28: =2315.8/C24 -> 40.551401 | D28: =3197.1/D24 -> 110.62539 | E28: =1750.45/E24 -> 90.338035 | F28: =2043.65/F24 -> 484.16231 | G28: =1107.2/G24 -> 195.39628 | H28: MPS from NSE.
A29: Profitability Ratios related to Earning Power
A30: Return on Investment (ROI) | B30: = EAT/Total Assets | C30: ='Adani Enterprises'!B33/'Adani Enterprises'!I49 -> 0.03326647 | D30: ='Adani Enterprises'!C33/'Adani Enterprises'!J49 -> 0.02049768 | E30: ='Adani Enterprises'!D33/'Adani Enterprises'!K49 -> 0.015612227 | F30: ='Adani Enterprises'!E33/'Adani Enterprises'!L49 -> 0.0045620001 | G30: ='Adani Enterprises'!F33/'Adani Enterprises'!M49 -> 0.012067496
A31: Activity or Efficiency Ratios
A32: Current Assets Turnover | B32: = Sales/Current Assets | C32: ='Adani Enterprises'!B9/'Adani Enterprises'!I48 -> 2.4026512 | D32: ='Adani Enterprises'!C9/'Adani Enterprises'!J48 -> 2.6158639 | E32: ='Adani Enterprises'!D9/'Adani Enterprises'!K48 -> 3.6899616 | F32: ='Adani Enterprises'!E9/'Adani Enterprises'!L48 -> 2.2433125 | G32: ='Adani Enterprises'!F9/'Adani Enterprises'!M48 -> 1.9804897
A33: Fixed Assets Turnover | B33: = Sales/Fixed Assets | C33: ='Adani Enterprises'!B9/'Adani Enterprises'!I35 -> 0.76666009 | D33: ='Adani Enterprises'!C9/'Adani Enterprises'!J35 -> 0.96307539 | E33: ='Adani Enterprises'!D9/'Adani Enterprises'!K35 -> 1.7118116 | F33: ='Adani Enterprises'!E9/'Adani Enterprises'!L35 -> 1.300825 | G33: ='Adani Enterprises'!F9/'Adani Enterprises'!M35 -> 2.0263916
A34: Total Assets Turnover | B34: = Sales/Total Assets | C34: ='Adani Enterprises'!B9/'Adani Enterprises'!I49 -> 0.49407971 | D34: ='Adani Enterprises'!C9/'Adani Enterprises'!J49 -> 0.5998872 | E34: ='Adani Enterprises'!D9/'Adani Enterprises'!K49 -> 0.96812404 | F34: ='Adani Enterprises'!E9/'Adani Enterprises'!L49 -> 0.68219389 | G34: ='Adani Enterprises'!F9/'Adani Enterprises'!M49 -> 0.76558754
A35: Inventory Turnover | B35: = Sales / Average Inventory | C35: ='Adani Enterprises'!B9/(AVERAGE('Adani Enterprises'!I43:J43)) -> 9.9012352 | D35: ='Adani Enterprises'!C9/(AVERAGE('Adani Enterprises'!J43:K43)) -> 11.755137 | E35: ='Adani Enterprises'!D9/(AVERAGE('Adani Enterprises'!K43:L43)) -> 19.987518 | F35: ='Adani Enterprises'!E9/(AVERAGE('Adani Enterprises'!L43:M43)) -> 16.247532 | G35: ='Adani Enterprises'!F9/(AVERAGE('Adani Enterprises'!M43:N43)) -> 18.306727
A36: Debtors Turnover | B36: = Sales / Average Debtors | C36: ='Adani Enterprises'!B9/(AVERAGE('Adani Enterprises'!I44:J44)) -> 10.087355 | D36: ='Adani Enterprises'!C9/(AVERAGE('Adani Enterprises'!J44:K44)) -> 8.6298935 | E36: ='Adani Enterprises'!D9/(AVERAGE('Adani Enterprises'!K44:L44)) -> 10.430413 | F36: ='Adani Enterprises'!E9/(AVERAGE('Adani Enterprises'!L44:M44)) -> 5.4034335 | G36: ='Adani Enterprises'!F9/(AVERAGE('Adani Enterprises'!M44:N44)) -> 3.1467107
A37: Assessment of Risk
A38: DTL | B38: = Contribution/EBT | C38: =('Adani Enterprises'!B9-'Adani Enterprises'!B14-'Adani Enterprises'!B15-'Adani Enterprises'!B16-'Adani Enterprises'!B17-'Adani Enterprises'!B18)/'Adani Enterprises'!B30 -> 4.0693544 | D38: =('Adani Enterprises'!C9-'Adani Enterprises'!C14-'Adani Enterprises'!C15-'Adani Enterprises'!C16-'Adani Enterprises'!C17-'Adani Enterprises'!C18)/'Adani Enterprises'!C30 -> 8.5023582 | E38: =('Adani Enterprises'!D9-'Adani Enterprises'!D14-'Adani Enterprises'!D15-'Adani Enterprises'!D16-'Adani Enterprises'!D17-'Adani Enterprises'!D18)/'Adani Enterprises'!D30 -> 9.8035447 | F38: =('Adani Enterprises'!E9-'Adani Enterprises'!E14-'Adani Enterprises'!E15-'Adani Enterprises'!E16-'Adani Enterprises'!E17-'Adani Enterprises'!E18)/'Adani Enterprises'!E30 -> 7.6666035 | G38: =('Adani Enterprises'!F9-'Adani Enterprises'!F14-'Adani Enterprises'!F15-'Adani Enterprises'!F16-'Adani Enterprises'!F17-'Adani Enterprises'!F18)/'Adani Enterprises'!F30 -> 6.430615
A39: DOL | B39: = Contribution/EBIT | C39: =('Adani Enterprises'!B9-'Adani Enterprises'!B14-'Adani Enterprises'!B15-'Adani Enterprises'!B16-'Adani Enterprises'!B17-'Adani Enterprises'!B18)/'Adani Enterprises'!B25 -> 2.9800906 | D39: =('Adani Enterprises'!C9-'Adani Enterprises'!C14-'Adani Enterprises'!C15-'Adani Enterprises'!C16-'Adani Enterprises'!C17-'Adani Enterprises'!C18)/'Adani Enterprises'!C25 -> 3.6809697 | E39: =('Adani Enterprises'!D9-'Adani Enterprises'!D14-'Adani Enterprises'!D15-'Adani Enterprises'!D16-'Adani Enterprises'!D17-'Adani Enterprises'!D18)/'Adani Enterprises'!D25 -> 3.6090408 | F39: =('Adani Enterprises'!E9-'Adani Enterprises'!E14-'Adani Enterprises'!E15-'Adani Enterprises'!E16-'Adani Enterprises'!E17-'Adani Enterprises'!E18)/'Adani Enterprises'!E25 -> 1.96067 | G39: =('Adani Enterprises'!F9-'Adani Enterprises'!F14-'Adani Enterprises'!F15-'Adani Enterprises'!F16-'Adani Enterprises'!F17-'Adani Enterprises'!F18)/'Adani Enterprises'!F25 -> 2.7779446
A40: DFL | B40: = EBIT/EBT | C40: ='Adani Enterprises'!B25/'Adani Enterprises'!B30 -> 1.3655137 | D40: ='Adani Enterprises'!C25/'Adani Enterprises'!C30 -> 2.3098148 | E40: ='Adani Enterprises'!D25/'Adani Enterprises'!D30 -> 2.7163851 | F40: ='Adani Enterprises'!E25/'Adani Enterprises'!E30 -> 3.9101957 | G40: ='Adani Enterprises'!F25/'Adani Enterprises'!F30 -> 2.3148824

Sheet Hindalco Industries
A1: Hindalco Industries | H1: Hindalco Industries
A2: Consolidated Profit & Loss account | B2: ------------------- in Rs. Cr. ------------------- | H2: Consolidated Balance Sheet | I2: ------------------- in Rs. Cr. -------------------
B3: Mar '25 | C3: Mar '24 | D3: Mar '23 | E3: Mar '22 | F3: Mar '21 | I3: Mar 25 | J3: 45352 | K3: 44986 | L3: 44621 | M3: 44256
B5: 12 mths | C5: 12 mths | D5: 12 mths | E5: 12 mths | F5: 12 mths | I5: 12 mths | J5: 12 mths | K5: 12 mths | L5: 12 mths | M5: 12 mths
A7: Income | H7: EQUITIES AND LIABILITIES
A8: Sales Turnover | B8: 238496 | C8: 215962 | D8: 223202 | E8: 195059 | F8: 131985 | H8: SHAREHOLDER'S FUNDS
A9: Net Sales | B9: 238496 | C9: 215962 | D9: 223202 | E9: 195059 | F9: 131985 | H9: Equity Share Capital | I9: 222 | J9: 222 | K9: 222 | L9: 222 | M9: 222
A10: Other Income | B10: 1829 | C10: 1517 | D10: 1998 | E10: 2432 | F10: -109 | H10: Total Share Capital | I10: 222 | J10: 222 | K10: 222 | L10: 222 | M10: 222
A11: Stock Adjustments | B11: 2327 | C11: -1329 | D11: -3241 | E11: 9753 | F11: 2146 | H11: Reserves and Surplus | I11: 123487 | J11: 105783 | K11: 94580 | L11: 77965 | M11: 66253
A12: Total Income | B12: 242652 | C12: 216150 | D12: 221959 | E12: 207244 | F12: 134022 | H12: Total Reserves and Surplus | I12: 123487 | J12: 105783 | K12: 94580 | L12: 77965 | M12: 66253
A13: Expenditure | H13: Employees Stock Options | I13: 0 | J13: 137 | K13: 0 | L13: 0 | M13: 54
A14: Raw Materials | B14: 147276 | C14: 132526 | D14: 142620 | E14: 131760 | F14: 82215 | H14: Total Shareholders Funds | I14: 123709 | J14: 106142 | K14: 94802 | L14: 78187 | M14: 66529
A15: Power & Fuel Cost | B15: 14396 | C15: 3624 | D15: 17346 | E15: 11146 | F15: 8646 | H15: Hybrid/Debt/Other Securities | I15: 0 | J15: 4 | K15: 4 | L15: 4 | M15: 4
A16: Employee Cost | B16: 15406 | C16: 14778 | D16: 13063 | E16: 11936 | F16: 10782 | H16: Minority Interest | I16: 12 | J16: 11 | K16: 11 | L16: 11 | M16: 10
A17: Miscellaneous Expenses | B17: 31940 | C17: 39833 | D17: 24266 | E17: 21623 | F17: 14952 | H17: NON-CURRENT LIABILITIES
A18: Total Expenses | B18: 209018 | C18: 190761 | D18: 197295 | E18: 176465 | F18: 116595 | H18: Long Term Borrowings | I18: 56217 | J18: 47395 | K18: 51434 | L18: 51635 | M18: 58985
B19: Mar '25 | C19: Mar '24 | D19: Mar '23 | E19: Mar '22 | F19: Mar '21 | H19: Deferred Tax Liabilities [Net] | I19: 10471 | J19: 9344 | K19: 8650 | L19: 5631 | M19: 4493
H20: Other Long Term Liabilities | I20: 3839 | J20: 9042 | K20: 8873 | L20: 3473 | M20: 3039
B21: 12 mths | C21: 12 mths | D21: 12 mths | E21: 12 mths | F21: 12 mths | H21: Long Term Provisions | I21: 6227 | J21: 618 | K21: 586 | L21: 6848 | M21: 8146
H22: Total Non-Current Liabilities | I22: 76754 | J22: 66399 | K22: 69543 | L22: 67587 | M22: 74663
A23: Operating Profit | B23: 31805 | C23: 23872 | D23: 22666 | E23: 28347 | F23: 17536 | H23: CURRENT LIABILITIES
A24: PBDIT | B24: 33634 | C24: 25389 | D24: 24664 | E24: 30779 | F24: 17427 | H24: Short Term Borrowings | I24: 5714 | J24: 7106 | K24: 6901 | L24: 11600 | M24: 6029
A25: Interest | B25: 3419 | C25: 3858 | D25: 3646 | E25: 3768 | F25: 3738 | H25: Trade Payables | I25: 40632 | J25: 34444 | K25: 35860 | L25: 41382 | M25: 28280
A26: PBDT | B26: 30215 | C26: 21531 | D26: 21018 | E26: 27011 | F26: 13689 | H26: Other Current Liabilities | I26: 15761 | J26: 15780 | K26: 15619 | L26: 21450 | M26: 11574
A27: Depreciation | B27: 7881 | C27: 7521 | D27: 7086 | E27: 6729 | F27: 6628 | H27: Short Term Provisions | I27: 3409 | J27: 2021 | K27: 2077 | L27: 2841 | M27: 2610
A28: Profit Before Tax | B28: 22334 | C28: 14010 | D28: 13932 | E28: 20282 | F28: 7061 | H28: Total Current Liabilities | I28: 65516 | J28: 59351 | K28: 60457 | L28: 77273 | M28: 48493
A29: PBT (Post Extra-ord Items) | B29: 22334 | C29: 14010 | D29: 13932 | E29: 20282 | F29: 7061 | H29: Total Capital And Liabilities | I29: 265991 | J29: 231907 | K29: 224817 | L29: 223062 | M29: 189699
A30: Tax | B30: 6335 | C30: 3857 | D30: 3144 | E30: 5373 | F30: 2723 | H30: ASSETS
A31: Reported Net Profit | B31: 15999 | C31: 10153 | D31: 10088 | E31: 13724 | F31: 3478 | H31: NON-CURRENT ASSETS
A32: Minority Interest | B32: 1 | C32: 0 | D32: 0 | E32: 0 | F32: 0 | H32: Tangible Assets | I32: 84656 | J32: 79744 | K32: 78550 | L32: 76491 | M32: 70870
A33: Share Of P/L Of Associates | B33: -3 | C33: -2 | D33: -9 | E33: -6 | F33: -5 | H33: Intangible Assets | I33: 5591 | J33: 5991 | K33: 6331 | L33: 6418 | M33: 6082
A34: Net P/L After Minority Interest & Share Of Associates | B34: 16880 | C34: 10134 | D34: 10056 | E34: 13619 | F34: 5674 | H34: Capital Work-In-Progress | I34: 27023 | J34: 14643 | K34: 7340 | L34: 4727 | M34: 10013
A35: Total Value Addition | B35: 61742 | C35: 58235 | D35: 54675 | E35: 44705 | F35: 34380 | H35: Intangible Assets Under Development | I35: 0 | J35: 224 | K35: 360 | L35: 218 | M35: 189
A36: Equity Dividend | B36: 0 | C36: 0 | D36: 890 | E36: 667 | F36: 222 | H36: Fixed Assets | I36: 117270 | J36: 100602 | K36: 92581 | L36: 87854 | M36: 87154
A37: Per share data (annualised) | H37: Non-Current Investments | I37: 13626 | J37: 12172 | K37: 8259 | L37: 8667 | M37: 7716
A38: Shares in issue (lakhs) | B38: 22200 | C38: 22200 | D38: 22243.38 | E38: 22243.38 | F38: 22250.89 | H38: Deferred Tax Assets [Net] | I38: 1691 | J38: 1184 | K38: 1328 | L38: 1207 | M38: 887
A39: Earning Per Share (Rs) | B39: 72.07 | C39: 45.73 | D39: 45.35 | E39: 61.7 | F39: 15.63 | H39: Long Term Loans And Advances | I39: 6 | J39: 7 | K39: 47 | L39: 50 | M39: 12
A40: Book Value (Rs) | B40: 557.25 | C40: 478.14 | D40: 426.2 | E40: 351.51 | F40: 298.75 | H40: Other Non-Current Assets | I40: 4756 | J40: 9524 | K40: 7546 | L40: 2776 | M40: 2985
H41: Total Non-Current Assets | I41: 164032 | J41: 149564 | K41: 135506 | L41: 124519 | M41: 122071
H42: CURRENT ASSETS
H43: Current Investments | I43: 10532 | J43: 3272 | K43: 5857 | L43: 5452 | M43: 9417 | N43: 43891
H44: Inventories | I44: 48801 | J44: 40812 | K44: 42958 | L44: 44483 | M44: 30668 | N44: 22384
H45: Trade Receivables | I45: 19834 | J45: 16404 | K45: 16214 | L45: 21076 | M45: 12959 | N45: 9345
H46: Cash And Cash Equivalents | I46: 10846 | J46: 14437 | K46: 15368 | L46: 17392 | M46: 8809
H47: Short Term Loans And Advances | I47: 7 | J47: 32 | K47: 8 | L47: 7 | M47: 47
H48: OtherCurrentAssets | I48: 11939 | J48: 7386 | K48: 8906 | L48: 10133 | M48: 5728
H49: Total Current Assets | I49: 101959 | J49: 82343 | K49: 89311 | L49: 98543 | M49: 67628
H50: Total Assets | I50: 265991 | J50: 231907 | K50: 224817 | L50: 223062 | M50: 189699
H51: OTHER ADDITIONAL INFORMATION
H52: CONTINGENT LIABILITIES, COMMITMENTS
H53: Contingent Liabilities | I53: 0 | J53: 88564 | K53: 134161 | L53: 98014 | M53: 75698
H54: BONUS DETAILS
H55: Bonus Equity Share Capital | I55: 0 | J55: 49.18 | K55: 49.18 | L55: 49.18 | M55: 49.18
H56: NON-CURRENT INVESTMENTS
H57: Non-Current Investments Quoted Market Value | I57: 0 | J57: 11918 | K57: 8027 | L57: 8542 | M57: 7611
H58: Non-Current Investments Unquoted Book Value | I58: 0 | J58: 130 | K58: 134 | L58: 75 | M58: 53
H59: CURRENT INVESTMENTS
H60: Current Investments Quoted Market Value | I60: 0 | J60: 3272 | K60: 5857 | L60: 5452 | M60: 9417

Sheet Hindalco Indus. Ratio Analysis
A1: Hindalco Industries Ratio Analysis
A2: Ratio Type | B2: Ratio Formula | C2: 2025 | D2: 2024 | E2: 2023 | F2: 2022 | G2: 2021
A3: Liquidity Ratios
A4: Current Ratio | B4: = Current Assets/Current Liabilities | C4: ='Hindalco Industries'!I49/'Hindalco Industries'!I28 -> 1.5562458 | D4: ='Hindalco Industries'!J49/'Hindalco Industries'!J28 -> 1.3873903 | E4: ='Hindalco Industries'!K49/'Hindalco Industries'!K28 -> 1.4772648 | F4: ='Hindalco Industries'!L49/'Hindalco Industries'!L28 -> 1.2752579 | G4: ='Hindalco Industries'!M49/'Hindalco Industries'!M28 -> 1.394593
A5: Quick Ratio | B5: = (Current Assets - Inventory - Prepaid Expenses)/Current Liabilities | C5: =('Hindalco Industries'!I49-'Hindalco Industries'!I44)/'Hindalco Industries'!I28 -> 0.81137432 | D5: =('Hindalco Industries'!J49-'Hindalco Industries'!J44)/'Hindalco Industries'!J28 -> 0.69975232 | E5: =('Hindalco Industries'!K49-'Hindalco Industries'!K44)/'Hindalco Industries'!K28 -> 0.76671022 | F5: =('Hindalco Industries'!L49-'Hindalco Industries'!L44)/'Hindalco Industries'!L28 -> 0.69959753 | G5: =('Hindalco Industries'!M49-'Hindalco Industries'!M44)/'Hindalco Industries'!M28 -> 0.76217186
A6: Leverage Ratios
A7: Debt-Equity Ratio | B7: = Long Term Debt/Shareholders Equity | C7: ='Hindalco Industries'!I18/'Hindalco Industries'!I14 -> 0.45442935 | D7: ='Hindalco Industries'!J18/'Hindalco Industries'!J14 -> 0.44652447 | E7: ='Hindalco Industries'!K18/'Hindalco Industries'!K14 -> 0.5425413 | F7: ='Hindalco Industries'!L18/'Hindalco Industries'!L14 -> 0.6604039 | G7: ='Hindalco Industries'!M18/'Hindalco Industries'!M14 -> 0.88660584
A8: Debt to Total Assets Ratio | B8: = Total Debt/Total Assets | C8: =('Hindalco Industries'!I18+'Hindalco Industries'!I24)/'Hindalco Industries'!I50 -> 0.23283119 | D8: =('Hindalco Industries'!J18+'Hindalco Industries'!J24)/'Hindalco Industries'!J50 -> 0.23501231 | E8: =('Hindalco Industries'!K18+'Hindalco Industries'!K24)/'Hindalco Industries'!K50 -> 0.25947771 | F8: =('Hindalco Industries'!L18+'Hindalco Industries'!L24)/'Hindalco Industries'!L50 -> 0.28348621 | G8: =('Hindalco Industries'!M18+'Hindalco Industries'!M24)/'Hindalco Industries'!M50 -> 0.34272189
A9: Proprietary Ratio | B9: = Shareholders Equity/Total Assets | C9: ='Hindalco Industries'!I14/'Hindalco Industries'!I50 -> 0.46508716 | D9: ='Hindalco Industries'!J14/'Hindalco Industries'!J50 -> 0.45769209 | E9: ='Hindalco Industries'!K14/'Hindalco Industries'!K50 -> 0.42168519 | F9: ='Hindalco Industries'!L14/'Hindalco Industries'!L50 -> 0.3505169 | G9: ='Hindalco Industries'!M14/'Hindalco Industries'!M50 -> 0.35070823
A10: Interest Coverage Ratio | B10: = EBIT/Interest | C10: ='Hindalco Industries'!B23/'Hindalco Industries'!B25 -> 9.3024276 | D10: ='Hindalco Industries'!C23/'Hindalco Industries'!C25 -> 6.187662 | E10: ='Hindalco Industries'!D23/'Hindalco Industries'!D25 -> 6.2166758 | F10: ='Hindalco Industries'!E23/'Hindalco Industries'!E25 -> 7.5230892 | G10: ='Hindalco Industries'!F23/'Hindalco Industries'!F25 -> 4.6912788
A11: Profitability Ratios related to Sales
A12: Gross Profit Ratio | B12: = Gross Profit (Sales-COGS) / Sales | C12: =('Hindalco Industries'!B9-('Hindalco Industries'!J44-'Hindalco Industries'!I44+'Hindalco Industries'!B14))/'Hindalco Industries'!B9 -> 0.41597763 | D12: =('Hindalco Industries'!C9-('Hindalco Industries'!K44-'Hindalco Industries'!J44+'Hindalco Industries'!C14))/'Hindalco Industries'!C9 -> 0.37640881 | E12: =('Hindalco Industries'!D9-('Hindalco Industries'!L44-'Hindalco Industries'!K44+'Hindalco Industries'!D14))/'Hindalco Industries'!D9 -> 0.35419485 | F12: =('Hindalco Industries'!E9-('Hindalco Industries'!M44-'Hindalco Industries'!L44+'Hindalco Industries'!E14))/'Hindalco Industries'!E9 -> 0.3953368 | G12: =('Hindalco Industries'!F9-('Hindalco Industries'!N44-'Hindalco Industries'!M44+'Hindalco Industries'!F14))/'Hindalco Industries'!F9 -> 0.43985301
A13: Operating Profit Ratio | B13: = EBIT/Sales | C13: ='Hindalco Industries'!B23/'Hindalco Industries'!B9 -> 0.13335653 | D13: ='Hindalco Industries'!C23/'Hindalco Industries'!C9 -> 0.11053797 | E13: ='Hindalco Industries'!D23/'Hindalco Industries'!D9 -> 0.10154927 | F13: ='Hindalco Industries'!E23/'Hindalco Industries'!E9 -> 0.14532526 | G13: ='Hindalco Industries'!F23/'Hindalco Industries'!F9 -> 0.13286358
A14: Net Profit Ratio | B14: = EAT/Sales | C14: ='Hindalco Industries'!B31/'Hindalco Industries'!B9 -> 0.067082886 | D14: ='Hindalco Industries'!C31/'Hindalco Industries'!C9 -> 0.0470129 | E14: ='Hindalco Industries'!D31/'Hindalco Industries'!D9 -> 0.045196728 | F14: ='Hindalco Industries'!E31/'Hindalco Industries'!E9 -> 0.070358199 | G14: ='Hindalco Industries'!F31/'Hindalco Industries'!F9 -> 0.026351479
A15: Administrative Expenses Ratio | B15: = Admin Expenses/Sales | C15: =0/'Hindalco Industries'!B9 -> 0 | D15: =0/'Hindalco Industries'!C9 -> 0 | E15: =0/'Hindalco Industries'!D9 -> 0 | F15: =0/'Hindalco Industries'!E9 -> 0 | G15: =0/'Hindalco Industries'!F9 -> 0 | H15: No selling and admin expenses.
A16: Selling Expenses Ratio | B16: = Selling Expenses/Sales | C16: =0/'Hindalco Industries'!B9 -> 0 | D16: =0/'Hindalco Industries'!C9 -> 0 | E16: =0/'Hindalco Industries'!D9 -> 0 | F16: =0/'Hindalco Industries'!E9 -> 0 | G16: =0/'Hindalco Industries'!F9 -> 0 | H16: No selling and admin expenses.
A17: Operating Expenses Ratio | B17: = (Admin Expenses + Selling Expenses) / Sales | C17: =0/'Hindalco Industries'!B9 -> 0 | D17: =0/'Hindalco Industries'!C9 -> 0 | E17: =0/'Hindalco Industries'!D9 -> 0 | F17: =0/'Hindalco Industries'!E9 -> 0 | G17: =0/'Hindalco Industries'!F9 -> 0 | H17: No selling and admin expenses.
A18: Operating Ratio | B18: = (COGS+Operating Expenses) / Sales | C18: =('Hindalco Industries'!J44-'Hindalco Industries'!I44+'Hindalco Industries'!B14)/'Hindalco Industries'!B9 -> 0.58402237 | D18: =('Hindalco Industries'!K44-'Hindalco Industries'!J44+'Hindalco Industries'!C14)/'Hindalco Industries'!C9 -> 0.62359119 | E18: =('Hindalco Industries'!L44-'Hindalco Industries'!K44+'Hindalco Industries'!D14)/'Hindalco Industries'!D9 -> 0.64580515 | F18: =('Hindalco Industries'!M44-'Hindalco Industries'!L44+'Hindalco Industries'!E14)/'Hindalco Industries'!E9 -> 0.6046632 | G18: =('Hindalco Industries'!N44-'Hindalco Industries'!M44+'Hindalco Industries'!F14)/'Hindalco Industries'!F9 -> 0.56014699
A19: Profitability Ratios related to Investment
A20: Return on Assets | B20: = EAT/Total Assets | C20: ='Hindalco Industries'!B31/'Hindalco Industries'!I50 -> 0.060148652 | D20: ='Hindalco Industries'!C31/'Hindalco Industries'!J50 -> 0.043780481 | E20: ='Hindalco Industries'!D31/'Hindalco Industries'!K50 -> 0.044872051 | F20: ='Hindalco Industries'!E31/'Hindalco Industries'!L50 -> 0.061525495 | G20: ='Hindalco Industries'!F31/'Hindalco Industries'!M50 -> 0.018334309
A21: Return on Capital Employed | B21: = EBIT/Total Capital Employed | C21: ='Hindalco Industries'!B31/('Hindalco Industries'!I50-'Hindalco Industries'!I28) -> 0.079805462 | D21: ='Hindalco Industries'!C31/('Hindalco Industries'!J50-'Hindalco Industries'!J28) -> 0.05883887 | E21: ='Hindalco Industries'!D31/('Hindalco Industries'!K50-'Hindalco Industries'!K28) -> 0.061377464 | F21: ='Hindalco Industries'!E31/('Hindalco Industries'!L50-'Hindalco Industries'!L28) -> 0.094136046 | G21: ='Hindalco Industries'!F31/('Hindalco Industries'!M50-'Hindalco Industries'!M28) -> 0.024630681
A22: Return on Equity | B22: = EAT/Shareholders Equity | C22: ='Hindalco Industries'!B31/'Hindalco Industries'!I14 -> 0.1293277 | D22: ='Hindalco Industries'!C31/'Hindalco Industries'!J14 -> 0.095654877 | E22: ='Hindalco Industries'!D31/'Hindalco Industries'!K14 -> 0.10641126 | F22: ='Hindalco Industries'!E31/'Hindalco Industries'!L14 -> 0.1755279 | G22: ='Hindalco Industries'!F31/'Hindalco Industries'!M14 -> 0.052277954
A23: Profitability Ratios related to Equity Shares
A24: Earnings Per Share | B24: = Net Profit Available to Equity Shareholders/Number of Equity Shares | C24: ='Hindalco Industries'!B31/'Hindalco Industries'!B38*100 -> 72.067568 | D24: ='Hindalco Industries'!C31/'Hindalco Industries'!C38*100 -> 45.734234 | E24: ='Hindalco Industries'!D31/'Hindalco Industries'!D38*100 -> 45.35282 | F24: ='Hindalco Industries'!E31/'Hindalco Industries'!E38*100 -> 61.699256 | G24: ='Hindalco Industries'!F31/'Hindalco Industries'!F38*100 -> 15.630835
A25: Earnings Yield | B25: = EPS/Market Price Per Share | C25: =C24/682.45 -> 0.10560124 | D25: =D24/560.25 -> 0.081631833 | E25: =E24/405.35 -> 0.11188558 | F25: =F24/570.5 -> 0.10814944 | G25: =G24/350.25 -> 0.044627653 | H25: MPS from NSE.
A26: Dividend Yield | B26: = DPS/MPS | C26: =('Hindalco Industries'!B36/'Hindalco Industries'!B38*100)/682.45 -> 0 | D26: =('Hindalco Industries'!C36/'Hindalco Industries'!C38*100)/560.25 -> 0 | E26: =('Hindalco Industries'!D36/'Hindalco Industries'!D38*100)/405.35 -> 0.0098709522 | F26: =('Hindalco Industries'!E36/'Hindalco Industries'!E38*100)/570.5 -> 0.00525617 | G26: =('Hindalco Industries'!F36/'Hindalco Industries'!F38*100)/350.25 -> 0.0028485736 | H26: MPS from NSE.
A27: Dividend Payout Ratio | B27: = DPS/EPS | C27: =('Hindalco Industries'!B36/'Hindalco Industries'!B38*100)/C24 -> 0 | D27: =('Hindalco Industries'!C36/'Hindalco Industries'!C38*100)/D24 -> 0 | E27: =('Hindalco Industries'!D36/'Hindalco Industries'!D38*100)/E24 -> 0.088223632 | F27: =('Hindalco Industries'!E36/'Hindalco Industries'!E38*100)/F24 -> 0.048600991 | G27: =('Hindalco Industries'!F36/'Hindalco Industries'!F38*100)/G24 -> 0.063829787
A28: Price to Earnings Ratio | B28: = MPS/EPS | C28: =682.45/C24 -> 9.4695856 | D28: =560.25/D24 -> 12.250123 | E28: =405.35/E24 -> 8.9377023 | F28: =570.5/F24 -> 9.2464648 | G28: =350.25/G24 -> 22.407631 | H28: MPS from NSE.
A29: Profitability Ratios related to Earning Power
A30: Return on Investment (ROI) | B30: = EAT/Total Assets | C30: ='Hindalco Industries'!B31/'Hindalco Industries'!I50 -> 0.060148652 | D30: ='Hindalco Industries'!C31/'Hindalco Industries'!J50 -> 0.043780481 | E30: ='Hindalco Industries'!D31/'Hindalco Industries'!K50 -> 0.044872051 | F30: ='Hindalco Industries'!E31/'Hindalco Industries'!L50 -> 0.061525495 | G30: ='Hindalco Industries'!F31/'Hindalco Industries'!M50 -> 0.018334309
A31: Activity or Efficiency Ratios
A32: Current Assets Turnover | B32: = Sales/Current Assets | C32: ='Hindalco Industries'!B9/'Hindalco Industries'!I49 -> 2.3391363 | D32: ='Hindalco Industries'!C9/'Hindalco Industries'!J49 -> 2.6227123 | E32: ='Hindalco Industries'!D9/'Hindalco Industries'!K49 -> 2.4991546 | F32: ='Hindalco Industries'!E9/'Hindalco Industries'!L49 -> 1.9794303 | G32: ='Hindalco Industries'!F9/'Hindalco Industries'!M49 -> 1.9516325
A33: Fixed Assets Turnover | B33: = Sales/Fixed Assets | C33: ='Hindalco Industries'!B9/'Hindalco Industries'!I36 -> 2.0337341 | D33: ='Hindalco Industries'!C9/'Hindalco Industries'!J36 -> 2.1466969 | E33: ='Hindalco Industries'!D9/'Hindalco Industries'!K36 -> 2.4108834 | F33: ='Hindalco Industries'!E9/'Hindalco Industries'!L36 -> 2.2202632 | G33: ='Hindalco Industries'!F9/'Hindalco Industries'!M36 -> 1.5143883
A34: Total Assets Turnover | B34: = Sales/Total Assets | C34: ='Hindalco Industries'!B9/'Hindalco Industries'!I50 -> 0.89663184 | D34: ='Hindalco Industries'!C9/'Hindalco Industries'!J50 -> 0.93124399 | E34: ='Hindalco Industries'!D9/'Hindalco Industries'!K50 -> 0.99281638 | F34: ='Hindalco Industries'!E9/'Hindalco Industries'!L50 -> 0.87446091 | G34: ='Hindalco Industries'!F9/'Hindalco Industries'!M50 -> 0.69576013
A35: Inventory Turnover | B35: = Sales / Average Inventory | C35: ='Hindalco Industries'!B9/(AVERAGE('Hindalco Industries'!I44:J44)) -> 5.3227991 | D35: ='Hindalco Industries'!C9/(AVERAGE('Hindalco Industries'!J44:K44)) -> 5.1560702 | E35: ='Hindalco Industries'!D9/(AVERAGE('Hindalco Industries'!K44:L44)) -> 5.1052024 | F35: ='Hindalco Industries'!E9/(AVERAGE('Hindalco Industries'!L44:M44)) -> 5.1911219 | G35: ='Hindalco Industries'!F9/(AVERAGE('Hindalco Industries'!M44:N44)) -> 4.9756842
A36: Debtors Turnover | B36: = Sales / Average Debtors | C36: ='Hindalco Industries'!B9/(AVERAGE('Hindalco Industries'!I45:J45)) -> 13.162757 | D36: ='Hindalco Industries'!C9/(AVERAGE('Hindalco Industries'!J45:K45)) -> 13.241891 | E36: ='Hindalco Industries'!D9/(AVERAGE('Hindalco Industries'!K45:L45)) -> 11.971145 | F36: ='Hindalco Industries'!E9/(AVERAGE('Hindalco Industries'!L45:M45)) -> 11.462259 | G36: ='Hindalco Industries'!F9/(AVERAGE('Hindalco Industries'!M45:N45)) -> 11.835097
A37: Assessment of Risk
A38: DTL | B38: = Contribution/EBT | C38: =('Hindalco Industries'!B9-'Hindalco Industries'!B14-'Hindalco Industries'!B15-'Hindalco Industries'!B16)/'Hindalco Industries'!B28 -> 2.7499776 | D38: =('Hindalco Industries'!C9-'Hindalco Industries'!C14-'Hindalco Industries'!C15-'Hindalco Industries'!C16)/'Hindalco Industries'!C28 -> 4.64197 | E38: =('Hindalco Industries'!D9-'Hindalco Industries'!D14-'Hindalco Industries'!D15-'Hindalco Industries'!D16)/'Hindalco Industries'!D28 -> 3.6012776 | F38: =('Hindalco Industries'!E9-'Hindalco Industries'!E14-'Hindalco Industries'!E15-'Hindalco Industries'!E16)/'Hindalco Industries'!E28 -> 1.9828912 | G38: =('Hindalco Industries'!F9-'Hindalco Industries'!F14-'Hindalco Industries'!F15-'Hindalco Industries'!F16)/'Hindalco Industries'!F28 -> 4.2971251
A39: DOL | B39: = Contribution/EBIT | C39: =('Hindalco Industries'!B9-'Hindalco Industries'!B14-'Hindalco Industries'!B15-'Hindalco Industries'!B16)/'Hindalco Industries'!B23 -> 1.93108 | D39: =('Hindalco Industries'!C9-'Hindalco Industries'!C14-'Hindalco Industries'!C15-'Hindalco Industries'!C16)/'Hindalco Industries'!C23 -> 2.7242795 | E39: =('Hindalco Industries'!D9-'Hindalco Industries'!D14-'Hindalco Industries'!D15-'Hindalco Industries'!D16)/'Hindalco Industries'!D23 -> 2.2135798 | F39: =('Hindalco Industries'!E9-'Hindalco Industries'!E14-'Hindalco Industries'!E15-'Hindalco Industries'!E16)/'Hindalco Industries'!E23 -> 1.4187392 | G39: =('Hindalco Industries'!F9-'Hindalco Industries'!F14-'Hindalco Industries'!F15-'Hindalco Industries'!F16)/'Hindalco Industries'!F23 -> 1.7302692
A40: DFL | B40: = EBIT/EBT | C40: ='Hindalco Industries'!B23/'Hindalco Industries'!B28 -> 1.424062 | D40: ='Hindalco Industries'!C23/'Hindalco Industries'!C28 -> 1.7039258 | E40: ='Hindalco Industries'!D23/'Hindalco Industries'!D28 -> 1.6269021 | F40: ='Hindalco Industries'!E23/'Hindalco Industries'!E28 -> 1.3976432 | G40: ='Hindalco Industries'!F23/'Hindalco Industries'!F28 -> 2.4835009
