Workbook

Sheet Table of Contents
A1: Tab Name | B1: Tab Link
A2: Cover Page | B2: Cover
A3: Read Me | B3: Read Me
A4: Summary | B4: Summary
A5: DLF Financial Model | B5: DLF Model
A6: DLF Income Statement | B6: DLF_Income_Statement
A7: DLF Balance Sheet | B7: DLF_Balance_Sheet

Sheet Read Me
A1: This a 10 year historical financial model of DLF Limited dated from 31/03/2015 to 31/03/2024.
A2: We have performed a vertical model which comprises of the Income Statement, Balance Sheet and Cash Flow Statement.
A3: It includes a summary of the growth of Sales, Operating Profit and Net Income.
A4: It also includes a vertical and horizontal form of analysis along with ratio and DuPont analysis.
A5: Refer to the Table of Contents for the various tabs and the links to it.
A6: The below comprises of the necessary colour codes followed in the Financial Model..
A8: Colour Code | B8: What does it indicate?
A9: XXX | B9: Historical Data that needs to be calculated.
B10: Main Headers
B11: Sub Headers
B12: Notes in the Financial Model.
A13: XXX | B13: Important notes.

Sheet Cover
B4: AB FinMod Ltd
B5: Financial Modelling Services
B14: DLF LTD
B15: =TODAY() -> 46084
B25: Financial Model - Vertical Orientation | K25: Completed By:
K26: Abhimanyu Babbar

Sheet Summary
B2: DLF Ltd
B3: Summary Outputs
B5: =T5 -> SUMMARY VALUES | T5: SUMMARY VALUES
E7: Trend | G7: =W7 -> 2015 | H7: =X7 -> 2016 | I7: =Y7 -> 2017 | J7: =Z7 -> 2018 | K7: =AA7 -> 2019 | L7: =AB7 -> 2020 | M7: =AC7 -> 2021 | N7: =AD7 -> 2022 | ... P7: =AF7 -> 2024 | W7: 2015 | X7: =W7+1 -> 2016 | Y7: =X7+1 -> 2017 | Z7: =Y7+1 -> 2018 | AA7: =Z7+1 -> 2019 | AB7: =AA7+1 -> 2020 | AC7: =AB7+1 -> 2021 | AD7: =AC7+1 -> 2022 | AE7: =AD7+1 -> 2023 | AF7: =AE7+1 -> 2024
C8: Income Statement Items
C10: =U10 -> Sales | D10: =V10 -> (₹) | G10: =W10 -> 7649 | H10: =X10 -> 9926 | I10: =Y10 -> 8221 | J10: =Z10 -> 6707 | K10: =AA10 -> 8366 | L10: =AB10 -> 6083 | M10: =AC10 -> 5414 | N10: =AD10 -> 5717 | ... P10: =AF10 -> 6427 | U10: Sales | V10: (₹) | W10: ='DLF Model'!B9 -> 7649 | X10: ='DLF Model'!C9 -> 9926 | Y10: ='DLF Model'!D9 -> 8221 | Z10: ='DLF Model'!E9 -> 6707 | AA10: ='DLF Model'!F9 -> 8366 | AB10: ='DLF Model'!G9 -> 6083 | AC10: ='DLF Model'!H9 -> 5414 | AD10: ='DLF Model'!I9 -> 5717 | ... AF10: ='DLF Model'!K9 -> 6427
C11: =U11 -> Growth | D11: =V11 -> (%) | G11: =W11 -> -0.078211617 | H11: =X11 -> 0.29768597 | I11: =Y11 -> -0.17177111 | J11: =Z11 -> -0.18416251 | K11: =AA11 -> 0.24735351 | L11: =AB11 -> -0.27289027 | M11: =AC11 -> -0.10997863 | N11: =AD11 -> 0.055966014 | ... P11: =AF11 -> 0.1285338 | U11: Growth | V11: (%) | W11: =(W10-DLF_Income_Statement!B2)/DLF_Income_Statement!B2 -> -0.078211617 | X11: =(X10-W10)/W10 -> 0.29768597 | Y11: =(Y10-X10)/X10 -> -0.17177111 | Z11: =(Z10-Y10)/Y10 -> -0.18416251 | AA11: =(AA10-Z10)/Z10 -> 0.24735351 | AB11: =(AB10-AA10)/AA10 -> -0.27289027 | AC11: =(AC10-AB10)/AB10 -> -0.10997863 | AD11: =(AD10-AC10)/AC10 -> 0.055966014 | AE11: =(AE10-AD10)/AD10 -> -0.0038481721 | AF11: =(AF10-AE10)/AE10 -> 0.1285338
C14: =U14 -> Operating Profit | D14: =V14 -> (₹) | G14: =W14 -> 3014 | H14: =X14 -> 3966 | I14: =Y14 -> 3446 | J14: =Z14 -> 2378 | K14: =AA14 -> 2148 | L14: =AB14 -> 1146 | M14: =AC14 -> 1469 | N14: =AD14 -> 1743 | ... P14: =AF14 -> 2124 | U14: Operating Profit | V14: (₹) | W14: ='DLF Model'!B11 -> 3014 | X14: ='DLF Model'!C11 -> 3966 | Y14: ='DLF Model'!D11 -> 3446 | Z14: ='DLF Model'!E11 -> 2378 | AA14: ='DLF Model'!F11 -> 2148 | AB14: ='DLF Model'!G11 -> 1146 | AC14: ='DLF Model'!H11 -> 1469 | AD14: ='DLF Model'!I11 -> 1743 | ... AF14: ='DLF Model'!K11 -> 2124
C15: =U15 -> Margin | D15: =V15 -> (%) | G15: =W15 -> 0.39403844 | H15: =X15 -> 0.39955672 | I15: =Y15 -> 0.41917042 | J15: =Z15 -> 0.35455494 | K15: =AA15 -> 0.25675353 | L15: =AB15 -> 0.18839388 | M15: =AC15 -> 0.27133358 | N15: =AD15 -> 0.30488018 | ... P15: =AF15 -> 0.33048078 | U15: Margin | V15: (%) | W15: ='DLF Model'!B305 -> 0.39403844 | X15: ='DLF Model'!C305 -> 0.39955672 | Y15: ='DLF Model'!D305 -> 0.41917042 | Z15: ='DLF Model'!E305 -> 0.35455494 | AA15: ='DLF Model'!F305 -> 0.25675353 | AB15: ='DLF Model'!G305 -> 0.18839388 | AC15: ='DLF Model'!H305 -> 0.27133358 | AD15: ='DLF Model'!I305 -> 0.30488018 | ... AF15: ='DLF Model'!K305 -> 0.33048078
C16: =U16 -> Growth | D16: =V16 -> (%) | G16: =W16 -> 0.20898516 | H16: =X16 -> 0.31585932 | I16: =Y16 -> -0.13111447 | J16: =Z16 -> -0.30992455 | K16: =AA16 -> -0.096719933 | L16: =AB16 -> -0.46648045 | M16: =AC16 -> 0.28184991 | N16: =AD16 -> 0.18652144 | ... P16: =AF16 -> 0.23059096 | U16: Growth | V16: (%) | W16: =(W14-DLF_Income_Statement!B4)/DLF_Income_Statement!B4 -> 0.20898516 | X16: =(X14-W14)/W14 -> 0.31585932 | Y16: =(Y14-X14)/X14 -> -0.13111447 | Z16: =(Z14-Y14)/Y14 -> -0.30992455 | AA16: =(AA14-Z14)/Z14 -> -0.096719933 | AB16: =(AB14-AA14)/AA14 -> -0.46648045 | AC16: =(AC14-AB14)/AB14 -> 0.28184991 | AD16: =(AD14-AC14)/AC14 -> 0.18652144 | AE16: =(AE14-AD14)/AD14 -> -0.0097532989 | AF16: =(AF14-AE14)/AE14 -> 0.23059096
C19: =U19 -> Net Income | G19: =W19 -> 510 | H19: =X19 -> 462 | I19: =Y19 -> 800 | J19: =Z19 -> 4292 | K19: =AA19 -> 368 | L19: =AB19 -> -1479 | M19: =AC19 -> 478 | N19: =AD19 -> 843 | ... P19: =AF19 -> 1631 | U19: Net Income | V19: (₹) | W19: ='DLF Model'!B17 -> 510 | X19: ='DLF Model'!C17 -> 462 | Y19: ='DLF Model'!D17 -> 800 | Z19: ='DLF Model'!E17 -> 4292 | AA19: ='DLF Model'!F17 -> 368 | AB19: ='DLF Model'!G17 -> -1479 | AC19: ='DLF Model'!H17 -> 478 | AD19: ='DLF Model'!I17 -> 843 | ... AF19: ='DLF Model'!K17 -> 1631
C20: =U20 -> Margin | D20: =V20 -> (%) | G20: =W20 -> 0.066675382 | H20: =X20 -> 0.046544429 | I20: =Y20 -> 0.097311763 | J20: =Z20 -> 0.63992843 | K20: =AA20 -> 0.043987569 | L20: =AB20 -> -0.24313661 | M20: =AC20 -> 0.08828962 | N20: =AD20 -> 0.14745496 | ... P20: =AF20 -> 0.25377314 | U20: Margin | V20: (%) | W20: ='DLF Model'!B304 -> 0.066675382 | X20: ='DLF Model'!C304 -> 0.046544429 | Y20: ='DLF Model'!D304 -> 0.097311763 | Z20: ='DLF Model'!E304 -> 0.63992843 | AA20: ='DLF Model'!F304 -> 0.043987569 | AB20: ='DLF Model'!G304 -> -0.24313661 | AC20: ='DLF Model'!H304 -> 0.08828962 | AD20: ='DLF Model'!I304 -> 0.14745496 | ... AF20: ='DLF Model'!K304 -> 0.25377314
C21: =U21 -> Growth | D21: =V21 -> (%) | G21: =W21 -> 0.02 | H21: =X21 -> -0.094117647 | I21: =Y21 -> 0.73160173 | J21: =Z21 -> 4.365 | K21: =AA21 -> -0.91425909 | L21: =AB21 -> -5.0190217 | M21: =AC21 -> -1.3231913 | N21: =AD21 -> 0.76359833 | ... P21: =AF21 -> 0.48272727 | U21: Growth | V21: (%) | W21: =(W19-DLF_Income_Statement!B11)/DLF_Income_Statement!B11 -> 0.02 | X21: =(X19-DLF_Income_Statement!C11)/DLF_Income_Statement!C11 -> -0.094117647 | Y21: =(Y19-DLF_Income_Statement!D11)/DLF_Income_Statement!D11 -> 0.73160173 | Z21: =(Z19-DLF_Income_Statement!E11)/DLF_Income_Statement!E11 -> 4.365 | AA21: =(AA19-DLF_Income_Statement!F11)/DLF_Income_Statement!F11 -> -0.91425909 | AB21: =(AB19-DLF_Income_Statement!G11)/DLF_Income_Statement!G11 -> -5.0190217 | AC21: =(AC19-DLF_Income_Statement!H11)/DLF_Income_Statement!H11 -> -1.3231913 | AD21: =(AD19-DLF_Income_Statement!I11)/DLF_Income_Statement!I11 -> 0.76359833 | ... AF21: =(AF19-DLF_Income_Statement!K11)/DLF_Income_Statement!K11 -> 0.48272727

Sheet DLF Model
A1: FINANCIAL STATEMENTS | B1: Historical | L1: X | M1: Notes
A2: DLF Ltd | B2: 2015 | C2: =B2+1 -> 2016 | D2: =C2+1 -> 2017 | E2: =D2+1 -> 2018 | F2: =E2+1 -> 2019 | G2: =F2+1 -> 2020 | H2: =G2+1 -> 2021 | I2: =H2+1 -> 2022 | J2: =I2+1 -> 2023 | K2: =J2+1 -> 2024 | L2: X
A3: (₹) | L3: X
L4: X
A5: FINANCIAL STATEMENTS | L5: X
L6: X
A7: a) INCOME STATEMENT | L7: X
L8: X
A9: Sales | B9: =DLF_Income_Statement!C2 -> 7649 | C9: =DLF_Income_Statement!D2 -> 9926 | D9: =DLF_Income_Statement!E2 -> 8221 | E9: =DLF_Income_Statement!F2 -> 6707 | F9: =DLF_Income_Statement!G2 -> 8366 | G9: =DLF_Income_Statement!H2 -> 6083 | H9: =DLF_Income_Statement!I2 -> 5414 | I9: =DLF_Income_Statement!J2 -> 5717 | ... K9: =DLF_Income_Statement!L2 -> 6427 | L9: X
A10: (Less) Expenses | B10: =DLF_Income_Statement!C3 -> 4635 | C10: =DLF_Income_Statement!D3 -> 5960 | D10: =DLF_Income_Statement!E3 -> 4775 | E10: =DLF_Income_Statement!F3 -> 4329 | F10: =DLF_Income_Statement!G3 -> 6218 | G10: =DLF_Income_Statement!H3 -> 4937 | H10: =DLF_Income_Statement!I3 -> 3945 | I10: =DLF_Income_Statement!J3 -> 3974 | ... K10: =DLF_Income_Statement!L3 -> 4303 | L10: X
A11: Operating Profit | B11: =B9-B10 -> 3014 | C11: =C9-C10 -> 3966 | D11: =D9-D10 -> 3446 | E11: =E9-E10 -> 2378 | F11: =F9-F10 -> 2148 | G11: =G9-G10 -> 1146 | H11: =H9-H10 -> 1469 | I11: =I9-I10 -> 1743 | ... K11: =K9-K10 -> 2124 | L11: X
A12: Other Income | B12: =DLF_Income_Statement!C5 -> 503 | C12: =DLF_Income_Statement!D5 -> 506 | D12: =DLF_Income_Statement!E5 -> 1135 | E12: =DLF_Income_Statement!F5 -> 9722 | F12: =DLF_Income_Statement!G5 -> 784 | G12: =DLF_Income_Statement!H5 -> 1135 | H12: =DLF_Income_Statement!I5 -> 383 | I12: =DLF_Income_Statement!J5 -> 195 | ... K12: =DLF_Income_Statement!L5 -> 531 | L12: X
A13: Depreciation | B13: =DLF_Income_Statement!C6 -> 545 | C13: =DLF_Income_Statement!D6 -> 766 | D13: =DLF_Income_Statement!E6 -> 572 | E13: =DLF_Income_Statement!F6 -> 534 | F13: =DLF_Income_Statement!G6 -> 225 | G13: =DLF_Income_Statement!H6 -> 200 | H13: =DLF_Income_Statement!I6 -> 159 | I13: =DLF_Income_Statement!J6 -> 149 | ... K13: =DLF_Income_Statement!L6 -> 148 | L13: X
A14: Interest | B14: =DLF_Income_Statement!C7 -> 2304 | C14: =DLF_Income_Statement!D7 -> 2680 | D14: =DLF_Income_Statement!E7 -> 2980 | E14: =DLF_Income_Statement!F7 -> 2951 | F14: =DLF_Income_Statement!G7 -> 2062 | G14: =DLF_Income_Statement!H7 -> 1427 | H14: =DLF_Income_Statement!I7 -> 853 | I14: =DLF_Income_Statement!J7 -> 625 | ... K14: =DLF_Income_Statement!L7 -> 356 | L14: X
A15: Profit before tax | B15: =B11+B12-B13-B14 -> 668 | C15: =C11+C12-C13-C14 -> 1026 | D15: =D11+D12-D13-D14 -> 1029 | E15: =E11+E12-E13-E14 -> 8615 | F15: =F11+F12-F13-F14 -> 645 | G15: =G11+G12-G13-G14 -> 654 | H15: =H11+H12-H13-H14 -> 840 | I15: =I11+I12-I13-I14 -> 1164 | ... K15: =K11+K12-K13-K14 -> 2151 | L15: X
A16: Tax | B16: =DLF_Income_Statement!C9 -> 158 | C16: =DLF_Income_Statement!D9 -> 564 | D16: =DLF_Income_Statement!E9 -> 229 | E16: =DLF_Income_Statement!F9 -> 4323 | F16: =DLF_Income_Statement!G9 -> 277 | G16: =DLF_Income_Statement!H9 -> 2133 | H16: =DLF_Income_Statement!I9 -> 362 | I16: =DLF_Income_Statement!J9 -> 321 | ... K16: =DLF_Income_Statement!L9 -> 520 | L16: X
A17: Net profit | B17: =B15-B16 -> 510 | C17: =C15-C16 -> 462 | D17: =D15-D16 -> 800 | E17: =E15-E16 -> 4292 | F17: =F15-F16 -> 368 | G17: =G15-G16 -> -1479 | H17: =H15-H16 -> 478 | I17: =I15-I16 -> 843 | ... K17: =K15-K16 -> 1631 | L17: X
L18: X
A19: EBITDA | B19: =B11+B13 -> 3559 | C19: =C11+C13 -> 4732 | D19: =D11+D13 -> 4018 | E19: =E11+E13 -> 2912 | F19: =F11+F13 -> 2373 | G19: =G11+G13 -> 1346 | H19: =H11+H13 -> 1628 | I19: =I11+I13 -> 1892 | ... K19: =K11+K13 -> 2272 | L19: X
A20: EBIT | B20: =B11 -> 3014 | C20: =C11 -> 3966 | D20: =D11 -> 3446 | E20: =E11 -> 2378 | F20: =F11 -> 2148 | G20: =G11 -> 1146 | H20: =H11 -> 1469 | I20: =I11 -> 1743 | ... K20: =K11 -> 2124 | L20: X
A21: EBT | B21: =B11-B14 -> 710 | C21: =C11-C14 -> 1286 | D21: =D11-D14 -> 466 | E21: =E11-E14 -> -573 | F21: =F11-F14 -> 86 | G21: =G11-G14 -> -281 | H21: =H11-H14 -> 616 | I21: =I11-I14 -> 1118 | ... K21: =K11-K14 -> 1768 | L21: X
A22: EAT | B22: =B15-B16 -> 510 | C22: =C15-C16 -> 462 | D22: =D15-D16 -> 800 | E22: =E15-E16 -> 4292 | F22: =F15-F16 -> 368 | G22: =G15-G16 -> -1479 | H22: =H15-H16 -> 478 | I22: =I15-I16 -> 843 | ... K22: =K15-K16 -> 1631 | L22: X
L23: X
L24: X
A25: b) BALANCE SHEET | L25: X
L26: X
A27: ASSETS | L27: X
L28: X
A29: Current Assets | L29: X
A30: Trade Receivables | B30: =DLF_Balance_Sheet!C20 -> 1586 | C30: =DLF_Balance_Sheet!D20 -> 3417 | D30: =DLF_Balance_Sheet!E20 -> 1417 | E30: =DLF_Balance_Sheet!F20 -> 1286 | F30: =DLF_Balance_Sheet!G20 -> 832 | G30: =DLF_Balance_Sheet!H20 -> 721 | H30: =DLF_Balance_Sheet!I20 -> 581 | I30: =DLF_Balance_Sheet!J20 -> 564 | ... K30: =DLF_Balance_Sheet!L20 -> 538 | L30: X
A31: Inventory | B31: =DLF_Balance_Sheet!C21 -> 17610 | C31: =DLF_Balance_Sheet!D21 -> 16834 | D31: =DLF_Balance_Sheet!E21 -> 20099 | E31: =DLF_Balance_Sheet!F21 -> 19753 | F31: =DLF_Balance_Sheet!G21 -> 22009 | G31: =DLF_Balance_Sheet!H21 -> 22486 | H31: =DLF_Balance_Sheet!I21 -> 21087 | I31: =DLF_Balance_Sheet!J21 -> 20107 | ... K31: =DLF_Balance_Sheet!L21 -> 21154 | L31: X
A32: Cash and Bank | B32: =DLF_Balance_Sheet!C22 -> 2748 | C32: =DLF_Balance_Sheet!D22 -> 3381 | D32: =DLF_Balance_Sheet!E22 -> 4099 | E32: =DLF_Balance_Sheet!F22 -> 2278 | F32: =DLF_Balance_Sheet!G22 -> 4855 | G32: =DLF_Balance_Sheet!H22 -> 2420 | H32: =DLF_Balance_Sheet!I22 -> 1407 | I32: =DLF_Balance_Sheet!J22 -> 932 | ... K32: =DLF_Balance_Sheet!L22 -> 4384 | L32: X
A33: Loans and Advances | B33: =DLF_Balance_Sheet!C23 -> 49 | C33: =DLF_Balance_Sheet!D23 -> 1213 | D33: =DLF_Balance_Sheet!E23 -> 115 | E33: =DLF_Balance_Sheet!F23 -> 171 | F33: =DLF_Balance_Sheet!G23 -> 1154 | G33: =DLF_Balance_Sheet!H23 -> 753 | H33: =DLF_Balance_Sheet!I23 -> 1068 | I33: =DLF_Balance_Sheet!J23 -> 904 | ... K33: =DLF_Balance_Sheet!L23 -> 1573 | L33: X
A34: Other Assets | B34: =DLF_Balance_Sheet!C24 -> 18126 | C34: =DLF_Balance_Sheet!D24 -> 9852 | D34: =DLF_Balance_Sheet!E24 -> 12222 | E34: =DLF_Balance_Sheet!F24 -> 8046 | F34: =DLF_Balance_Sheet!G24 -> 10203 | G34: =DLF_Balance_Sheet!H24 -> 5669 | H34: =DLF_Balance_Sheet!I24 -> 4648 | I34: =DLF_Balance_Sheet!J24 -> 3938 | ... K34: =DLF_Balance_Sheet!L24 -> 7331 | L34: X
A35: Total Current Assets | B35: =SUM(B30:B34) -> 40119 | C35: =SUM(C30:C34) -> 34697 | D35: =SUM(D30:D34) -> 37952 | E35: =SUM(E30:E34) -> 31534 | F35: =SUM(F30:F34) -> 39053 | G35: =SUM(G30:G34) -> 32049 | H35: =SUM(H30:H34) -> 28791 | I35: =SUM(I30:I34) -> 26445 | ... K35: =SUM(K30:K34) -> 34980 | L35: X
L36: X
A37: Non-Current Assets | L37: X
A38: Net Block | B38: =DLF_Balance_Sheet!C16 -> 19619 | C38: =DLF_Balance_Sheet!D16 -> 3943 | D38: =DLF_Balance_Sheet!E16 -> 24640 | E38: =DLF_Balance_Sheet!F16 -> 8082 | F38: =DLF_Balance_Sheet!G16 -> 6322 | G38: =DLF_Balance_Sheet!H16 -> 5187 | H38: =DLF_Balance_Sheet!I16 -> 4856 | I38: =DLF_Balance_Sheet!J16 -> 4862 | ... K38: =DLF_Balance_Sheet!L16 -> 3880 | L38: X
A39: Capital Work in Progress | B39: =DLF_Balance_Sheet!C17 -> 5901 | C39: =DLF_Balance_Sheet!D17 -> 1779 | D39: =DLF_Balance_Sheet!E17 -> 153 | E39: =DLF_Balance_Sheet!F17 -> 137 | F39: =DLF_Balance_Sheet!G17 -> 103 | G39: =DLF_Balance_Sheet!H17 -> 89 | H39: =DLF_Balance_Sheet!I17 -> 95 | I39: =DLF_Balance_Sheet!J17 -> 81 | ... K39: =DLF_Balance_Sheet!L17 -> 71 | L39: X
A40: Investments | B40: =DLF_Balance_Sheet!C18 -> 623 | C40: =DLF_Balance_Sheet!D18 -> 21310 | D40: =DLF_Balance_Sheet!E18 -> 1209 | E40: =DLF_Balance_Sheet!F18 -> 20832 | F40: =DLF_Balance_Sheet!G18 -> 21005 | G40: =DLF_Balance_Sheet!H18 -> 18566 | H40: =DLF_Balance_Sheet!I18 -> 19746 | I40: =DLF_Balance_Sheet!J18 -> 19779 | ... K40: =DLF_Balance_Sheet!L18 -> 20138 | L40: X
A41: Total Non-Current Assets | B41: =SUM(B38:B40) -> 26143 | C41: =SUM(C38:C40) -> 27032 | D41: =SUM(D38:D40) -> 26002 | E41: =SUM(E38:E40) -> 29051 | F41: =SUM(F38:F40) -> 27430 | G41: =SUM(G38:G40) -> 23842 | H41: =SUM(H38:H40) -> 24697 | I41: =SUM(I38:I40) -> 24722 | ... K41: =SUM(K38:K40) -> 24089 | L41: X
L42: X
L43: X
A44: TOTAL ASSETS | B44: =B35+B41 -> 66262 | C44: =C35+C41 -> 61729 | D44: =D35+D41 -> 63954 | E44: =E35+E41 -> 60585 | F44: =F35+F41 -> 66483 | G44: =G35+G41 -> 55891 | H44: =H35+H41 -> 53488 | I44: =I35+I41 -> 51167 | ... K44: =K35+K41 -> 59069 | L44: X
L45: X
L46: X
A47: LIABILITIES | L47: X
L48: X
A49: Current Liabilities | L49: X
A50: Non Controlling Interest | B50: =DLF_Balance_Sheet!C8 -> 175 | C50: =DLF_Balance_Sheet!D8 -> 126 | D50: =DLF_Balance_Sheet!E8 -> 124 | E50: =DLF_Balance_Sheet!F8 -> 49 | F50: =DLF_Balance_Sheet!G8 -> 41 | G50: =DLF_Balance_Sheet!H8 -> 18 | H50: =DLF_Balance_Sheet!I8 -> 20 | I50: =DLF_Balance_Sheet!J8 -> 19 | ... K50: =DLF_Balance_Sheet!L8 -> 1 | L50: X
A51: Trade Payables | B51: =DLF_Balance_Sheet!C9 -> 1850 | C51: =DLF_Balance_Sheet!D9 -> 1514 | D51: =DLF_Balance_Sheet!E9 -> 1407 | E51: =DLF_Balance_Sheet!F9 -> 1217 | F51: =DLF_Balance_Sheet!G9 -> 1277 | G51: =DLF_Balance_Sheet!H9 -> 1057 | H51: =DLF_Balance_Sheet!I9 -> 1234 | I51: =DLF_Balance_Sheet!J9 -> 1529 | ... K51: =DLF_Balance_Sheet!L9 -> 1787 | L51: X
A52: Advance from Customers | B52: =DLF_Balance_Sheet!C10 -> 0 | C52: =DLF_Balance_Sheet!D10 -> 0 | D52: =DLF_Balance_Sheet!E10 -> 0 | E52: =DLF_Balance_Sheet!F10 -> 60 | F52: =DLF_Balance_Sheet!G10 -> 105 | G52: =DLF_Balance_Sheet!H10 -> 79 | H52: =DLF_Balance_Sheet!I10 -> 90 | I52: =DLF_Balance_Sheet!J10 -> 0 | ... K52: =DLF_Balance_Sheet!L10 -> 0 | L52: X
A53: Other Liabilities | B53: =DLF_Balance_Sheet!C11 -> 12373 | C53: =DLF_Balance_Sheet!D11 -> 10756 | D53: =DLF_Balance_Sheet!E11 -> 8648 | E53: =DLF_Balance_Sheet!F11 -> 6457 | F53: =DLF_Balance_Sheet!G11 -> 14262 | G53: =DLF_Balance_Sheet!H11 -> 12187 | H53: =DLF_Balance_Sheet!I11 -> 9914 | I53: =DLF_Balance_Sheet!J11 -> 9075 | ... K53: =DLF_Balance_Sheet!L11 -> 13016 | L53: X
A54: Total Current Labilities | B54: =SUM(B50:B53) -> 14398 | C54: =SUM(C50:C53) -> 12396 | D54: =SUM(D50:D53) -> 10179 | E54: =SUM(E50:E53) -> 7783 | F54: =SUM(F50:F53) -> 15685 | G54: =SUM(G50:G53) -> 13341 | H54: =SUM(H50:H53) -> 11258 | I54: =SUM(I50:I53) -> 10623 | ... K54: =SUM(K50:K53) -> 14804 | L54: X
L55: X
A56: Non-Current Liabilities | L56: X
A57: Borrowings | B57: =DLF_Balance_Sheet!C6 -> 24495 | C57: =DLF_Balance_Sheet!D6 -> 25264 | D57: =DLF_Balance_Sheet!E6 -> 29202 | E57: =DLF_Balance_Sheet!F6 -> 17491 | F57: =DLF_Balance_Sheet!G6 -> 17222 | G57: =DLF_Balance_Sheet!H6 -> 8103 | H57: =DLF_Balance_Sheet!I6 -> 6886 | I57: =DLF_Balance_Sheet!J6 -> 4182 | ... K57: =DLF_Balance_Sheet!L6 -> 4834 | L57: X
A58: Total Non-Current Liabilities | B58: =B57 -> 24495 | C58: =C57 -> 25264 | D58: =D57 -> 29202 | E58: =E57 -> 17491 | F58: =F57 -> 17222 | G58: =G57 -> 8103 | H58: =H57 -> 6886 | I58: =I57 -> 4182 | ... K58: =K57 -> 4834 | L58: X
L59: X
L60: X
A61: TOTAL LIABILITIES | B61: =B54+B58 -> 38893 | C61: =C54+C58 -> 37660 | D61: =D54+D58 -> 39381 | E61: =E54+E58 -> 25274 | F61: =F54+F58 -> 32907 | G61: =G54+G58 -> 21444 | H61: =H54+H58 -> 18144 | I61: =I54+I58 -> 14805 | ... K61: =K54+K58 -> 19638 | L61: X
L62: X
L63: X
A64: EQUITY | L64: X
A65: Equity Share Capital | B65: =DLF_Balance_Sheet!C3 -> 356 | C65: =DLF_Balance_Sheet!D3 -> 357 | D65: =DLF_Balance_Sheet!E3 -> 357 | E65: =DLF_Balance_Sheet!F3 -> 357 | F65: =DLF_Balance_Sheet!G3 -> 441 | G65: =DLF_Balance_Sheet!H3 -> 495 | H65: =DLF_Balance_Sheet!I3 -> 495 | I65: =DLF_Balance_Sheet!J3 -> 495 | ... K65: =DLF_Balance_Sheet!L3 -> 495 | L65: X
A66: Reserves | B66: =DLF_Balance_Sheet!C4 -> 27013 | C66: =DLF_Balance_Sheet!D4 -> 23712 | D66: =DLF_Balance_Sheet!E4 -> 24216 | E66: =DLF_Balance_Sheet!F4 -> 34954 | F66: =DLF_Balance_Sheet!G4 -> 33135 | G66: =DLF_Balance_Sheet!H4 -> 33952 | H66: =DLF_Balance_Sheet!I4 -> 34849 | I66: =DLF_Balance_Sheet!J4 -> 35867 | ... K66: =DLF_Balance_Sheet!L4 -> 38936 | L66: X
A67: Total Equity | B67: =SUM(B65:B66) -> 27369 | C67: =SUM(C65:C66) -> 24069 | D67: =SUM(D65:D66) -> 24573 | E67: =SUM(E65:E66) -> 35311 | F67: =SUM(F65:F66) -> 33576 | G67: =SUM(G65:G66) -> 34447 | H67: =SUM(H65:H66) -> 35344 | I67: =SUM(I65:I66) -> 36362 | ... K67: =SUM(K65:K66) -> 39431 | L67: X
L68: X
L69: X
A70: TOTAL LIABILITIES AND EQUITY | B70: =B61+B67 -> 66262 | C70: =C61+C67 -> 61729 | D70: =D61+D67 -> 63954 | E70: =E61+E67 -> 60585 | F70: =F61+F67 -> 66483 | G70: =G61+G67 -> 55891 | H70: =H61+H67 -> 53488 | I70: =I61+I67 -> 51167 | ... K70: =K61+K67 -> 59069 | L70: X
A71: CHECK | B71: =B44-B70 -> 0 | C71: =C44-C70 -> 0 | D71: =D44-D70 -> 0 | E71: =E44-E70 -> 0 | F71: =F44-F70 -> 0 | G71: =G44-G70 -> 0 | H71: =H44-H70 -> 0 | I71: =I44-I70 -> 0 | ... K71: =K44-K70 -> 0 | L71: X
L72: X
L73: X
A74: c) CASH FLOW STATEMENT | L74: X
L75: X
A76: A) Cash from Operating Activities | L76: X
L77: X
A78: Net Income | B78: =B17 -> 510 | C78: =C17 -> 462 | D78: =D17 -> 800 | E78: =E17 -> 4292 | F78: =F17 -> 368 | G78: =G17 -> -1479 | H78: =H17 -> 478 | I78: =I17 -> 843 | ... K78: =K17 -> 1631 | L78: X | M78: This already excludes tax, hence we are not deducting it towards the end.
L79: X
A80: Add: Non-Cash Items | L80: X
A81: Depreciation | B81: =B13 -> 545 | C81: =C13 -> 766 | D81: =D13 -> 572 | E81: =E13 -> 534 | F81: =F13 -> 225 | G81: =G13 -> 200 | H81: =H13 -> 159 | I81: =I13 -> 149 | ... K81: =K13 -> 148 | L81: X
L82: X
A83: Changes in Net Working Capital | L83: X
A84: (Less) Trade Receivables | B84: ='DLF Model'!B30-DLF_Balance_Sheet!B20 -> 25 | C84: =C30-B30 -> 1831 | D84: =D30-C30 -> -2000 | E84: =E30-D30 -> -131 | F84: =F30-E30 -> -454 | G84: =G30-F30 -> -111 | H84: =H30-G30 -> -140 | I84: =I30-H30 -> -17 | J84: =J30-I30 -> -15 | K84: =K30-J30 -> -11 | L84: X
A85: (Less) Inventory | B85: =B31-DLF_Balance_Sheet!B21 -> -901 | C85: =C31-B31 -> -776 | D85: =D31-C31 -> 3265 | E85: =E31-D31 -> -346 | F85: =F31-E31 -> 2256 | G85: =G31-F31 -> 477 | H85: =H31-G31 -> -1399 | I85: =I31-H31 -> -980 | J85: =J31-I31 -> -746 | K85: =K31-J31 -> 1793 | L85: X
A86: (Less) Loans and Advances | B86: =B33-DLF_Balance_Sheet!B23 -> 28 | C86: =C33-B33 -> 1164 | D86: =D33-C33 -> -1098 | E86: =E33-D33 -> 56 | F86: =F33-E33 -> 983 | G86: =G33-F33 -> -401 | H86: =H33-G33 -> 315 | I86: =I33-H33 -> -164 | J86: =J33-I33 -> 311 | K86: =K33-J33 -> 358 | L86: X
A87: (Less) Other Assets | B87: =B34-DLF_Balance_Sheet!B24 -> 1841 | C87: =C34-B34 -> -8274 | D87: =D34-C34 -> 2370 | E87: =E34-D34 -> -4176 | F87: =F34-E34 -> 2157 | G87: =G34-F34 -> -4534 | H87: =H34-G34 -> -1021 | I87: =I34-H34 -> -710 | J87: =J34-I34 -> 907 | K87: =K34-J34 -> 2486 | L87: X
A88: (Add) Non Controlling Interest | B88: =B50-DLF_Balance_Sheet!B8 -> -27 | C88: =C50-B50 -> -49 | D88: =D50-C50 -> -2 | E88: =E50-D50 -> -75 | F88: =F50-E50 -> -8 | G88: =G50-F50 -> -23 | H88: =H50-G50 -> 2 | I88: =I50-H50 -> -1 | J88: =J50-I50 -> -15 | K88: =K50-J50 -> -3 | L88: X
A89: (Add) Trade Payables | B89: =B51-DLF_Balance_Sheet!B9 -> -431 | C89: =C51-B51 -> -336 | D89: =D51-C51 -> -107 | E89: =E51-D51 -> -190 | F89: =F51-E51 -> 60 | G89: =G51-F51 -> -220 | H89: =H51-G51 -> 177 | I89: =I51-H51 -> 295 | J89: =J51-I51 -> 115 | K89: =K51-J51 -> 143 | L89: X
A90: (Add) Advance from Customers | B90: =B52-DLF_Balance_Sheet!B10 -> 0 | C90: =C52-B52 -> 0 | D90: =D52-C52 -> 0 | E90: =E52-D52 -> 60 | F90: =F52-E52 -> 45 | G90: =G52-F52 -> -26 | H90: =H52-G52 -> 11 | I90: =I52-H52 -> -90 | J90: =J52-I52 -> 0 | K90: =K52-J52 -> 0 | L90: X
A91: (Add) Other Liabilities | B91: =B53-DLF_Balance_Sheet!B11 -> 3658 | C91: =C53-B53 -> -1617 | D91: =D53-C53 -> -2108 | E91: =E53-D53 -> -2191 | F91: =F53-E53 -> 7805 | G91: =G53-F53 -> -2075 | H91: =H53-G53 -> -2273 | I91: =I53-H53 -> -839 | J91: =J53-I53 -> 828 | K91: =K53-J53 -> 3113 | L91: X
L92: X
L93: X
A94: Net Cash Flow generated from Operating Activities | B94: =B81-B84-B85-B86-B87+B88+B89+B90+B91 -> 2752 | C94: =C81-C84-C85-C86-C87+C88+C89+C90+C91 -> 4819 | D94: =D81-D84-D85-D86-D87+D88+D89+D90+D91 -> -4182 | E94: =E81-E84-E85-E86-E87+E88+E89+E90+E91 -> 2735 | F94: =F81-F84-F85-F86-F87+F88+F89+F90+F91 -> 3185 | G94: =G81-G84-G85-G86-G87+G88+G89+G90+G91 -> 2425 | H94: =H81-H84-H85-H86-H87+H88+H89+H90+H91 -> 321 | I94: =I81-I84-I85-I86-I87+I88+I89+I90+I91 -> 1385 | ... K94: =K81-K84-K85-K86-K87+K88+K89+K90+K91 -> -1225 | L94: X
L95: X
L96: X
A97: B) Cash from Investing Activities | L97: X
L98: X
A99: Changes in Work-In-Progress | B99: =B39-DLF_Balance_Sheet!B17 -> -78 | C99: =C39-B39 -> -4122 | D99: =D39-C39 -> -1626 | E99: =E39-D39 -> -16 | F99: =F39-E39 -> -34 | G99: =G39-F39 -> -14 | H99: =H39-G39 -> 6 | I99: =I39-H39 -> -14 | J99: =J39-I39 -> -20 | K99: =K39-J39 -> 10 | L99: X
A100: Changes in Investments | B100: =B40-DLF_Balance_Sheet!B18 -> -268 | C100: =C40-B40 -> 20687 | D100: =D40-C40 -> -20101 | E100: =E40-D40 -> 19623 | F100: =F40-E40 -> 173 | G100: =G40-F40 -> -2439 | H100: =H40-G40 -> 1180 | I100: =I40-H40 -> 33 | J100: =J40-I40 -> -298 | K100: =K40-J40 -> 657 | L100: X
...

Sheet DLF_Income_Statement
A1: Narration | B1: 41729 | C1: 42094 | D1: 42460 | E1: 42825 | F1: 43190 | G1: 43555 | H1: 43921 | I1: 44286 | J1: 44651 | K1: 45016 | L1: 45382
A2: Sales | B2: 8298 | C2: 7649 | D2: 9926 | E2: 8221 | F2: 6707 | G2: 8366 | H2: 6083 | I2: 5414 | J2: 5717 | K2: 5695 | L2: 6427
A3: Expenses | B3: 5805 | C3: 4635 | D3: 5960 | E3: 4775 | F3: 4329 | G3: 6218 | H3: 4937 | I3: 3945 | J3: 3974 | K3: 3969 | L3: 4303
A4: Operating Profit (EBIT) | B4: =B2-B3 -> 2493 | C4: =C2-C3 -> 3014 | D4: =D2-D3 -> 3966 | E4: =E2-E3 -> 3446 | F4: =F2-F3 -> 2378 | G4: =G2-G3 -> 2148 | H4: =H2-H3 -> 1146 | I4: =I2-I3 -> 1469 | ... L4: =L2-L3 -> 2124
A5: Other Income | B5: 1133 | C5: 503 | D5: 506 | E5: 1135 | F5: 9722 | G5: 784 | H5: 1135 | I5: 383 | J5: 195 | K5: 317 | L5: 531
A6: Depreciation | B6: 2463 | C6: 545 | D6: 766 | E6: 572 | F6: 534 | G6: 225 | H6: 200 | I6: 159 | J6: 149 | K6: 149 | L6: 148
A7: Interest | B7: 663 | C7: 2304 | D7: 2680 | E7: 2980 | F7: 2951 | G7: 2062 | H7: 1427 | I7: 853 | J7: 625 | K7: 392 | L7: 356
A8: Profit before tax | B8: =B4+B5-B6-B7 -> 500 | C8: =C4+C5-C6-C7 -> 668 | D8: =D4+D5-D6-D7 -> 1026 | E8: =E4+E5-E6-E7 -> 1029 | F8: =F4+F5-F6-F7 -> 8615 | G8: =G4+G5-G6-G7 -> 645 | H8: =H4+H5-H6-H7 -> 654 | I8: =I4+I5-I6-I7 -> 840 | ... L8: =L4+L5-L6-L7 -> 2151
A9: Tax | B9: 0 | C9: 158 | D9: 564 | E9: 229 | F9: 4323 | G9: 277 | H9: 2133 | I9: 362 | J9: 321 | K9: 402 | L9: 520
A10: Tax Rate | B10: 0 | C10: 0.23617339 | D10: 0.5497076 | E10: 0.22254616 | F10: 0.50179919 | G10: 0.42879257 | H10: 3.2614679 | I10: 0.43095238 | J10: 0.2757732 | K10: 0.26746507 | L10: 0.24174802
A11: Net profit | B11: =B8-B10 -> 500 | C11: =C8-C9 -> 510 | D11: =D8-D9 -> 462 | E11: =E8-E9 -> 800 | F11: =F8-F9 -> 4292 | G11: =G8-G9 -> 368 | H11: =H8-H9 -> -1479 | I11: =I8-I9 -> 478 | J11: =J8-J9 -> 843 | ... L11: =L8-L9 -> 1631
A13: EPS | B13: 3.63 | C13: 3.0317638 | D13: 1.7166564 | E13: 4.0067265 | F13: 25.020234 | G13: 5.9768032 | H13: -2.3560781 | I13: 4.4180503 | J13: 6.0633055 | K13: 8.2245788 | L13: 11.017291
A14: Dividend Payout % | B14: 0.55 | C14: 0.66 | D14: 1.17 | E14: 0.5 | F14: 0.08 | G14: 0.33 | H14: -0.85 | I14: 0.45 | J14: 0.49 | K14: 0.49 | L14: 0.45
A15: Price to Earning | B15: 48.443526 | C15: 52.197337 | D15: 66.84506 | E15: 37.100112 | F15: 8.0434898 | G15: 33.872623 | H15: -58.338475 | I15: 64.972098 | J15: 62.746303 | K15: 43.370002 | L15: 81.417475
A16: Price | B16: 175.85 | C16: 158.25 | D16: 114.75 | E16: 148.65 | F16: 201.25 | G16: 202.45 | H16: 137.45 | I16: 287.05 | J16: 380.45 | K16: 356.7 | L16: 897
A18: EBITDA | B18: =B4+B6 -> 4956 | C18: =C4+C6 -> 3559 | D18: =D4+D6 -> 4732 | E18: =E4+E6 -> 4018 | F18: =F4+F6 -> 2912 | G18: =G4+G6 -> 2373 | H18: =H4+H6 -> 1346 | I18: =I4+I6 -> 1628 | ... L18: =L4+L6 -> 2272
A19: EBIT | B19: =B4 -> 2493 | C19: =C4 -> 3014 | D19: =D4 -> 3966 | E19: =E4 -> 3446 | F19: =F4 -> 2378 | G19: =G4 -> 2148 | H19: =H4 -> 1146 | I19: =I4 -> 1469 | ... L19: =L4 -> 2124
A20: EBT | B20: =B4-B7 -> 1830 | C20: =C4-C7 -> 710 | D20: =D4-D7 -> 1286 | E20: =E4-E7 -> 466 | F20: =F4-F7 -> -573 | G20: =G4-G7 -> 86 | H20: =H4-H7 -> -281 | I20: =I4-I7 -> 616 | ... L20: =L4-L7 -> 1768
A21: EAT | B21: =B20-B9 -> 1830 | C21: =C20-C9 -> 552 | D21: =D20-D9 -> 722 | E21: =E20-E9 -> 237 | F21: =F20-F9 -> -4896 | G21: =G20-G9 -> -191 | H21: =H20-H9 -> -2414 | I21: =I20-I9 -> 254 | ... L21: =L20-L9 -> 1248

Sheet DLF_Balance_Sheet
A1: Narration | B1: 41729 | C1: 42094 | D1: 42460 | E1: 42825 | F1: 43190 | G1: 43555 | H1: 43921 | I1: 44286 | J1: 44651 | K1: 45016 | L1: 45382
A2: Equity and Shareholders Funds -
A3: Equity Share Capital | B3: 356 | C3: 356 | D3: 357 | E3: 357 | F3: 357 | G3: 441 | H3: 495 | I3: 495 | J3: 495 | K3: 495 | L3: 495
A4: Reserves | B4: 27039 | C4: 27013 | D4: 23712 | E4: 24216 | F4: 34954 | G4: 33135 | H4: 33952 | I4: 34849 | J4: 35867 | K4: 37192 | L4: 38936
A5: Non Current Liabilities -
A6: Borrowings | B6: 25932 | C6: 24495 | D6: 25264 | E6: 29202 | F6: 17491 | G6: 17222 | H6: 8103 | I6: 6886 | J6: 4182 | K6: 3334 | L6: 4834
A7: Current Liabilities -
A8: Non Controlling Interest | B8: 202 | C8: 175 | D8: 126 | E8: 124 | F8: 49 | G8: 41 | H8: 18 | I8: 20 | J8: 19 | K8: 4 | L8: 1
A9: Trade Payables | B9: 2281 | C9: 1850 | D9: 1514 | E9: 1407 | F9: 1217 | G9: 1277 | H9: 1057 | I9: 1234 | J9: 1529 | K9: 1644 | L9: 1787
A10: Advance from Customers | B10: 0 | C10: 0 | D10: 0 | E10: 0 | F10: 60 | G10: 105 | H10: 79 | I10: 90 | J10: 0 | K10: 0 | L10: 0
A11: Other Liability Items | B11: 8715 | C11: 12373 | D11: 10756 | E11: 8648 | F11: 6457 | G11: 14262 | H11: 12187 | I11: 9914 | J11: 9075 | K11: 9903 | L11: 13016
A13: Total Liabilities and Equity | B13: =SUM(B3:B11) -> 64525 | C13: =SUM(C3:C12) -> 66262 | D13: =SUM(D3:D12) -> 61729 | E13: =SUM(E3:E12) -> 63954 | F13: =SUM(F3:F12) -> 60585 | G13: =SUM(G3:G12) -> 66483 | H13: =SUM(H3:H12) -> 55891 | I13: =SUM(I3:I12) -> 53488 | J13: =SUM(J3:J12) -> 51167 | ... L13: =SUM(L3:L12) -> 59069
A15: Fixed Assets -
A16: Net Block | B16: 18835 | C16: 19619 | D16: 3943 | E16: 24640 | F16: 8082 | G16: 6322 | H16: 5187 | I16: 4856 | J16: 4862 | K16: 4785 | L16: 3880
A17: Capital Work in Progress | B17: 5979 | C17: 5901 | D17: 1779 | E17: 153 | F17: 137 | G17: 103 | H17: 89 | I17: 95 | J17: 81 | K17: 61 | L17: 71
A18: Investments | B18: 891 | C18: 623 | D18: 21310 | E18: 1209 | F18: 20832 | G18: 21005 | H18: 18566 | I18: 19746 | J18: 19779 | K18: 19481 | L18: 20138
A19: Current Assets -
A20: Trade Receivables | B20: 1561 | C20: 1586 | D20: 3417 | E20: 1417 | F20: 1286 | G20: 832 | H20: 721 | I20: 581 | J20: 564 | K20: 549 | L20: 538
A21: Inventory | B21: 18511 | C21: 17610 | D21: 16834 | E21: 20099 | F21: 19753 | G21: 22009 | H21: 22486 | I21: 21087 | J21: 20107 | K21: 19361 | L21: 21154
A22: Cash and Bank | B22: 2442 | C22: 2748 | D22: 3381 | E22: 4099 | F22: 2278 | G22: 4855 | H22: 2420 | I22: 1407 | J22: 932 | K22: 2275 | L22: 4384
A23: Loans and Advances | B23: 21 | C23: 49 | D23: 1213 | E23: 115 | F23: 171 | G23: 1154 | H23: 753 | I23: 1068 | J23: 904 | K23: 1215 | L23: 1573
A24: Other Assets | B24: 16285 | C24: 18126 | D24: 9852 | E24: 12222 | F24: 8046 | G24: 10203 | H24: 5669 | I24: 4648 | J24: 3938 | K24: 4845 | L24: 7331
A26: Total Assets | B26: =SUM(B16:B24) -> 64525 | C26: =SUM(C16:C24) -> 66262 | D26: =SUM(D16:D24) -> 61729 | E26: =SUM(E16:E24) -> 63954 | F26: =SUM(F16:F24) -> 60585 | G26: =SUM(G16:G24) -> 66483 | H26: =SUM(H16:H24) -> 55891 | I26: =SUM(I16:I24) -> 53488 | ... L26: =SUM(L16:L24) -> 59069
A28: Working Capital | B28: =SUM(B20:B24)-SUM(B8:B11) -> 27622 | C28: =SUM(C20:C24)-SUM(C8:C11) -> 25721 | D28: =SUM(D20:D24)-SUM(D8:D11) -> 22301 | E28: =SUM(E20:E24)-SUM(E8:E11) -> 27773 | F28: =SUM(F20:F24)-SUM(F8:F11) -> 23751 | G28: =SUM(G20:G24)-SUM(G8:G11) -> 23368 | H28: =SUM(H20:H24)-SUM(H8:H11) -> 18708 | I28: =SUM(I20:I24)-SUM(I8:I11) -> 17533 | ... L28: =SUM(L20:L24)-SUM(L8:L11) -> 20176
A29: No: of equity shares | C29: 1781927367 | D29: 1783716082 | E29: 1784003090 | F29: 1784067028 | G29: 2207221948 | H29: 2475311706 | I29: 2475311706 | J29: 2475311706 | K29: 2475311706 | L29: 2475311706
